Workbook

Sheet Checklist
B1: FY18 | C1: FY19 | D1: FY20 | E1: FY21 | F1: FY22 | G1: FY23 | H1: FY24 | I1: FY25 | J1: FY26
A2: JAC | F2: x | G2: o | I2: x | M2: To-dos:
A3: CDPH
A4: OFVP | B4: - | C4: - | D4: - | E4: - | F4: x | G4: x | H4: x | I4: x
A5: ICJIA | C5: x | D5: x | E5: x | F5: x | G5: x | H5: x | I5: x
A6: Private? | B6: CRED + PSPC (to CP4P) + SC2
A7: Federal?
A11: Jack | B11: Erin | C11: Jack | D11: Jack
A12: ICJIA | B12: OFVP | C12: JAC | D12: CDPH
A13: Done | B13: Done | C13: Cleaning | D13: Outreach

Sheet Private funding
A1: Private CVI direct programming funding
A3: SC2 - direct CVI programming investments (scaling). Source: SC2 Cash Flow Tracker, Oct 2025
B4: FY22 | C4: FY23 | D4: FY24 | E4: FY25 | F4: FY26 (budgeted) | G4: FY24-26 total
A5: North Lawndale | D5: 0 | E5: 4755519 | F5: 5919882 | G5: =SUM(D5:F5) -> 10675401
A6: Austin | D6: 346759 | E6: 4314101 | F6: 6497838 | G6: =SUM(D6:F6) -> 11158698
A7: Humboldt Park | D7: 422000 | E7: 4341756 | F7: 6834298 | G7: =SUM(D7:F7) -> 11598054
A8: Garfield Park | D8: 311938 | E8: 978512 | F8: 1000004 | G8: =SUM(D8:F8) -> 2290454
A9: Englewood | D9: 202400 | E9: 109250 | F9: 0 | G9: =SUM(D9:F9) -> 311650
A10: New City | D10: 0 | E10: 140510 | F10: 0 | G10: =SUM(D10:F10) -> 140510
A11: South Lawndale | D11: 257610 | E11: 1357934 | F11: 5835343 | G11: =SUM(D11:F11) -> 7450887
A12: Total | D12: =SUM(D5:D11) -> 1540707 | E12: =SUM(E5:E11) -> 15997582 | F12: =SUM(F5:F11) -> 26087365 | G12: =SUM(D12:F12) -> 43625654
A15: CRED - direct CVI programming investments (Baseline). Source: Jen Keeling, Oct. 2025
B16: FY22 | C16: FY23 | D16: FY24 | E16: FY25 | F16: FY26 (budgeted) | G16: FY22-26 total
A17: North Lawndale | B17: 6856474 | C17: 7068502 | D17: 8231858 | E17: 7298126 | F17: 7298126 | G17: =SUM(B17:F17) -> 36753086
A18: Austin | B18: 365000 | C18: 383250 | D18: 402413 | E18: 570545 | F18: 543375 | G18: =SUM(B18:F18) -> 2264583
A19: Humboldt Park | B19: 350000 | C19: 367500 | D19: 385875 | E19: 385875 | F19: 475875 | G19: =SUM(B19:F19) -> 1965125
A20: South Lawndale | B20: 0 | C20: 0 | D20: 0 | E20: 0 | F20: 0 | G20: =SUM(B20:F20) -> 0
A21: West Garfield Park | B21: 325000 | C21: 341250 | D21: 358313 | E21: 490182 | F21: 331125 | G21: =SUM(B21:F21) -> 1845870
A22: West Englewood | B22: 0 | C22: 0 | D22: 0 | E22: 0 | F22: 0 | G22: =SUM(B22:F22) -> 0
A23: Roseland | B23: 8807840 | C23: 9136270 | D23: 10092718 | E23: 11126084 | F23: 11126084 | G23: =SUM(B23:F23) -> 50288996
A24: Auburn Gresham | B24: 465000 | C24: 488250 | D24: 512663 | E24: 512663 | F24: 410000 | G24: =SUM(B24:F24) -> 2388576
A25: Englewood | B25: 0 | C25: 0 | D25: 0 | E25: 300000 | F25: 150000 | G25: =SUM(B25:F25) -> 450000
A26: Woodlawn | B26: 200000 | C26: 210000 | D26: 220500 | E26: 220500 | F26: 210000 | G26: =SUM(B26:F26) -> 1061000
A27: Washington Park | B27: 200000 | C27: 210000 | D27: 220500 | E27: 220500 | F27: 210000 | G27: =SUM(B27:F27) -> 1061000
A28: Total | B28: =SUM(B17:B27) -> 17569314 | C28: =SUM(C17:C27) -> 18205022 | D28: =SUM(D17:D27) -> 20424840 | E28: =SUM(E17:E27) -> 21124475 | F28: =SUM(F17:F27) -> 20754585 | G28: =SUM(B28:F28) -> 98078236
A31: CP4P (via PSPC) - private funding, excluding CRED direct funding. Source: Leticia Reyes, Summer 2025
B32: FY22 | C32: FY23 | D32: FY24 | E32: FY25 | F32: FY22-25 total
A33: Albany Park | B33: 25000 | C33: 25000 | D33: 25000 | E33: 25000 | F33: =SUM(B33:E33) -> 100000
A34: Auburn Gresham | B34: 200000 | C34: 200000 | D34: 25000 | E34: 25000 | F34: =SUM(B34:E34) -> 450000
A35: Austin | B35: 200000 | C35: 200000 | D35: 3275920 | E35: 1467562 | F35: =SUM(B35:E35) -> 5143482
A36: Avondale | B36: 25000 | C36: 25000 | D36: 25000 | E36: 25000 | F36: =SUM(B36:E36) -> 100000
A37: Belmont-Cragin | B37: 25000 | C37: 25000 | D37: 25000 | E37: 25000 | F37: =SUM(B37:E37) -> 100000
A38: Brighton Park | B38: 25000 | C38: 115000 | D38: 25000 | E38: 25000 | F38: =SUM(B38:E38) -> 190000
A39: Burnside | B39: 0 | C39: 0 | D39: 0 | E39: 0 | F39: =SUM(B39:E39) -> 0
A40: Chatham | B40: 25000 | C40: 25000 | D40: 25000 | E40: 25000 | F40: =SUM(B40:E40) -> 100000
A41: Chicago Lawn | B41: 25000 | C41: 25000 | D41: 25000 | E41: 25000 | F41: =SUM(B41:E41) -> 100000
A42: West Garfield Park | B42: 300000 | C42: 200000 | D42: 200000 | E42: 1474710 | F42: =SUM(B42:E42) -> 2174710
A43: East Garfield Park | B43: 300000 | C43: 280000 | D43: 200000 | E43: 200000 | F43: =SUM(B43:E43) -> 980000
A44: West Englewood | B44: 200000 | C44: 150000 | D44: 200000 | E44: 175000 | F44: =SUM(B44:E44) -> 725000
... A73: Citywide Services | B73: 7955000 | C73: 1456707 | D73: 2417265 | E73: 1833438 | F73: =SUM(B73:E73) -> 13662410
A74: Total | B74: =SUM(B33:B73) -> 13730000 | C74: =SUM(C33:C73) -> 6000000 | D74: =SUM(D33:D73) -> 14611315 | E74: =SUM(E33:E73) -> 9401320 | F74: =SUM(B74:E74) -> 43742635

Sheet OFVP Pivot
B4: Sum of Award Amount | C4: Column Labels
B5: Row Labels | C5: 2022 | D5: 2023 | E5: 2024 | F5: 2025 | G5: 2026 | H5: Grand Total
B6: Austin | C6: 368008.5 | D6: 3243146.1 | E6: 4282570 | F6: 4056668 | G6: 3948867 | H6: 15899260
B7: North Lawndale | C7: 249615 | D7: 2526283 | E7: 4525577 | F7: 4152894 | G7: 4197282 | H7: 15651651
B8: Greater Grand Crossing | C8: 162275 | D8: 1509810 | E8: 4025178 | F8: 2713061 | G8: 2537021 | H8: 10947345
B9: West Garfield Park | C9: 290751.5 | D9: 2027136.8 | E9: 2978877 | F9: 2775154 | G9: 2846582 | H9: 10918501
B10: Humboldt Park | C10: 219429 | D10: 2624859 | E10: 4087477 | F10: 2304355 | G10: 1659225 | H10: 10895345
B11: South Lawndale | C11: 286540 | D11: 1705603 | E11: 2807169 | F11: 2981801 | G11: 2837967 | H11: 10619080
B12: Waukegan-North Chicago Cluster | D12: 1646824 | E12: 4110198.7 | F12: 2585969 | G12: 2216619 | H12: 10559611
B13: Auburn Gresham | C13: 86426.95 | D13: 1371996 | E13: 3126557 | F13: 2846666 | G13: 2540591 | H13: 9972236.9
B14: East Garfield Park | C14: 174073 | D14: 1487871.6 | E14: 3166690 | F14: 2566849 | G14: 2320548 | H14: 9716031.6
B15: Roseland | C15: 260647 | D15: 879788 | E15: 3060867 | F15: 2632062 | G15: 2814947 | H15: 9648311
B16: West Pullman | C16: 281714 | D16: 1213036.2 | E16: 3196757 | F16: 2372775 | G16: 1732503 | H16: 8796785.2
B17: Englewood | C17: 181355.95 | D17: 1283982 | E17: 3334227 | F17: 2268966 | G17: 1589516 | H17: 8658046.9
B18: Northside Cluster | D18: 781929 | E18: 2364830 | F18: 2654250 | G18: 2722987 | H18: 8523996
B19: West Englewood | C19: 155616 | D19: 889277 | E19: 2451063.4 | F19: 2403518 | G19: 2393516 | H19: 8292990.4
B20: Calumet City Cluster | C20: 25433 | D20: 1244387 | E20: 2945687 | F20: 2360737 | G20: 1548299 | H20: 8124543
B21: Joliet | C21: 18088 | D21: 767373 | E21: 2949966 | F21: 2364873 | G21: 1916338 | H21: 8016638
B22: Chatham | C22: 82829 | D22: 757322 | E22: 1998951 | F22: 2338695 | G22: 2658224 | H22: 7836021
B23: South Shore | C23: 147706 | D23: 1118403 | E23: 2399492 | F23: 2039976 | G23: 1593498 | H23: 7299075
B24: Rockford | C24: 12396 | D24: 1226856 | E24: 2359764 | F24: 2211589 | G24: 1194966 | H24: 7005571
B25: Berwyn-Cicero Cluster | C25: 64692 | D25: 1118643 | E25: 1762665 | F25: 1765429 | G25: 1986323 | H25: 6697752
B26: Southwest Side Cluster | D26: 386932 | E26: 1485954 | F26: 2081653 | G26: 2630107 | H26: 6584646
B27: New City | C27: 108520 | D27: 1247834 | E27: 1858458 | F27: 1684415 | G27: 1251244 | H27: 6150471
B28: Aurora | C28: 25466 | D28: 779208 | E28: 2246833 | F28: 1630078 | G28: 1340443 | H28: 6022028
B29: Belleville Cluster | D29: 372781 | E29: 1695312.6 | F29: 1952934 | G29: 1961218 | H29: 5982245.6
B30: South Chicago | C30: 225743 | D30: 1024249 | E30: 1610049 | F30: 1516973 | G30: 1432328 | H30: 5809342
B31: Washington Park | C31: 111833 | D31: 747263 | E31: 1985595 | F31: 1209527 | G31: 1038408 | H31: 5092626
B32: Chicago Lawn | C32: 127575 | D32: 567296 | E32: 1140074 | F32: 1536640 | G32: 1673201 | H32: 5044786
B33: Woodlawn | C33: 275845 | D33: 936447 | E33: 1742882 | F33: 1167460 | G33: 749641 | H33: 4872275
B34: Riverdale | C34: 63385 | D34: 650406 | E34: 1347956 | F34: 1336839 | G34: 1390546 | H34: 4789132
B35: Fuller Park | C35: 75000 | D35: 400000 | E35: 1394548 | F35: 1497250 | G35: 1134948 | H35: 4501746
B36: Peoria | C36: 24110 | D36: 424759 | E36: 1183549 | F36: 1099154 | G36: 1500534 | H36: 4232106
B37: Decatur | C37: 51083 | D37: 477857 | E37: 1207340 | F37: 866770 | G37: 1217281 | H37: 3820331
B38: Kankakee | D38: 459111 | E38: 1170816 | F38: 1082339 | G38: 889260 | H38: 3601526
B39: Chicago Heights Cluster | D39: 171357 | E39: 892001 | F39: 1054490 | G39: 1254968 | H39: 3372816
B40: Rock Island | D40: 509171 | E40: 592397 | F40: 793059 | G40: 1207432 | H40: 3102059
B41: Urbana-Champaign Cluster | C41: 42750 | D41: 427857 | E41: 979843 | F41: 635083 | G41: 900434 | H41: 2985967
B42: Burnside | D42: 132298.64 | E42: 934020 | F42: 1012419 | G42: 868837 | H42: 2947574.6
B43: Maywood-Bellwood Cluster | D43: 134191 | E43: 385809 | F43: 869084 | G43: 1299700 | H43: 2688784
B44: Ashburn | F44: 901213 | G44: 1311994 | H44: 2213207
B45: Springfield | E45: 567567 | F45: 607335 | G45: 830342 | H45: 2005244
B46: 3621 Chicago Only | F46: 0 | G46: 2000000 | H46: 2000000
B47: Danville | D47: 195537 | E47: 555075 | F47: 461650 | G47: 415384 | H47: 1627646
B48: South Deering | E48: 180000 | F48: 534245 | G48: 750027 | H48: 1464272
B49: Grand Total | C49: 4198905.9 | D49: 39469080 | E49: 87090642 | F49: 77926897 | G49: 76304096 | H49: 2.8498962e+08

Sheet OFVP
A1: Source | B1: Grant Type | C1: Award ID | D1: CSFA | E1: Grantee Name | F1: Start Date | G1: End Date | H1: Award Amount | I1: Fiscal Year | J1: Chicago/Greater Illinois | K1: County | L1: Community Area | M1: CVI | N1: FLIP | O1: CP4P | P1: SC2o | Q1: SC2c
A2: =IF(ISBLANK(E2),"","OFVP") -> OFVP | B2: TA Services Violence Prevention | D2: 2771 | E2: Acclivus, Inc. | G2: 45930 | H2: 150000 | I2: 2022 | J2: Chicago | K2: Cook | L2: z TTAS - Chicago | M2: =IF(ISNUMBER(MATCH(E2,_xlfn.VSTACK('VLookup Lists'!$E$2:$E$17,'VLookup Lists'!$H$2:$H$38,'VLookup Lists'!$J$2:$J$8),0)),1,0) -> 1 | N2: =IFERROR(IF(VLOOKUP($D2,'VLookup Lists'!$B$11:$C$29,2,FALSE)="FLIP",1,0),"") -> 0 | O2: =ISNUMBER(MATCH($E2,'VLookup Lists'!$E$2:$E$17,0)) -> FALSE
A3: =IF(ISBLANK(E3),"","OFVP") -> OFVP | B3: TA Services Violence Prevention | D3: 2771 | E3: Metropolitan Family Services | G3: 45565 | H3: 188061 | I3: 2022 | J3: Chicago | K3: Cook | L3: z TTAS - Chicago | M3: =IF(ISNUMBER(MATCH(E3,_xlfn.VSTACK('VLookup Lists'!$E$2:$E$17,'VLookup Lists'!$H$2:$H$38,'VLookup Lists'!$J$2:$J$8),0)),1,0) -> 1 | N3: =IFERROR(IF(VLOOKUP($D3,'VLookup Lists'!$B$11:$C$29,2,FALSE)="FLIP",1,0),"") -> 0 | O3: =ISNUMBER(MATCH($E3,'VLookup Lists'!$E$2:$E$17,0)) -> TRUE
A4: =IF(ISBLANK(E4),"","OFVP") -> OFVP | B4: TA Services Violence Prevention | D4: 2771 | E4: UNIVERSAL FAMILY CONNECTION | G4: 45344 | H4: 159600 | I4: 2022 | J4: Chicago | K4: Cook | L4: z TTAS - Chicago | M4: =IF(ISNUMBER(MATCH(E4,_xlfn.VSTACK('VLookup Lists'!$E$2:$E$17,'VLookup Lists'!$H$2:$H$38,'VLookup Lists'!$J$2:$J$8),0)),1,0) -> 0 | N4: =IFERROR(IF(VLOOKUP($D4,'VLookup Lists'!$B$11:$C$29,2,FALSE)="FLIP",1,0),"") -> 0 | O4: =ISNUMBER(MATCH($E4,'VLookup Lists'!$E$2:$E$17,0)) -> FALSE
A5: =IF(ISBLANK(E5),"","OFVP") -> OFVP | B5: TA Services Youth Development | D5: 2772 | E5: BLACK COMMUNITY PROVIDER | G5: 45565 | H5: 145486 | I5: 2022 | J5: Chicago | K5: Cook | L5: z TTAS - Chicago | M5: =IF(ISNUMBER(MATCH(E5,_xlfn.VSTACK('VLookup Lists'!$E$2:$E$17,'VLookup Lists'!$H$2:$H$38,'VLookup Lists'!$J$2:$J$8),0)),1,0) -> 0 | N5: =IFERROR(IF(VLOOKUP($D5,'VLookup Lists'!$B$11:$C$29,2,FALSE)="FLIP",1,0),"") -> 0 | O5: =ISNUMBER(MATCH($E5,'VLookup Lists'!$E$2:$E$17,0)) -> FALSE
A6: =IF(ISBLANK(E6),"","OFVP") -> OFVP | B6: TA Services Youth Development | D6: 2772 | E6: Metropolitan Family Services | G6: 45565 | H6: 203463 | I6: 2022 | J6: Chicago | K6: Cook | L6: z TTAS - Chicago | M6: =IF(ISNUMBER(MATCH(E6,_xlfn.VSTACK('VLookup Lists'!$E$2:$E$17,'VLookup Lists'!$H$2:$H$38,'VLookup Lists'!$J$2:$J$8),0)),1,0) -> 1 | N6: =IFERROR(IF(VLOOKUP($D6,'VLookup Lists'!$B$11:$C$29,2,FALSE)="FLIP",1,0),"") -> 0 | O6: =ISNUMBER(MATCH($E6,'VLookup Lists'!$E$2:$E$17,0)) -> TRUE
A7: =IF(ISBLANK(E7),"","OFVP") -> OFVP | B7: TA Services Youth Development | D7: 2772 | E7: Prevention First, Inc | G7: 45565 | H7: 168150 | I7: 2022 | J7: Chicago | K7: Cook | L7: z TTAS - Chicago | M7: =IF(ISNUMBER(MATCH(E7,_xlfn.VSTACK('VLookup Lists'!$E$2:$E$17,'VLookup Lists'!$H$2:$H$38,'VLookup Lists'!$J$2:$J$8),0)),1,0) -> 0 | N7: =IFERROR(IF(VLOOKUP($D7,'VLookup Lists'!$B$11:$C$29,2,FALSE)="FLIP",1,0),"") -> 0 | O7: =ISNUMBER(MATCH($E7,'VLookup Lists'!$E$2:$E$17,0)) -> FALSE
A8: =IF(ISBLANK(E8),"","OFVP") -> OFVP | B8: Chicago Conveners | D8: 2773 | E8: Lawrence Hall Youth Services | G8: 45747 | H8: 25000 | I8: 2022 | J8: Chicago | K8: Cook | L8: South Shore | M8: =IF(ISNUMBER(MATCH(E8,_xlfn.VSTACK('VLookup Lists'!$E$2:$E$17,'VLookup Lists'!$H$2:$H$38,'VLookup Lists'!$J$2:$J$8),0)),1,0) -> 0 | N8: =IFERROR(IF(VLOOKUP($D8,'VLookup Lists'!$B$11:$C$29,2,FALSE)="FLIP",1,0),"") -> 0 | O8: =ISNUMBER(MATCH($E8,'VLookup Lists'!$E$2:$E$17,0)) -> FALSE
A9: =IF(ISBLANK(E9),"","OFVP") -> OFVP | B9: Chicago Conveners | D9: 2773 | E9: UNIVERSAL FAMILY CONNECTION | G9: 45747 | H9: 24999.95 | I9: 2022 | J9: Chicago | K9: Cook | L9: Auburn Gresham | M9: =IF(ISNUMBER(MATCH(E9,_xlfn.VSTACK('VLookup Lists'!$E$2:$E$17,'VLookup Lists'!$H$2:$H$38,'VLookup Lists'!$J$2:$J$8),0)),1,0) -> 0 | N9: =IFERROR(IF(VLOOKUP($D9,'VLookup Lists'!$B$11:$C$29,2,FALSE)="FLIP",1,0),"") -> 0 | O9: =ISNUMBER(MATCH($E9,'VLookup Lists'!$E$2:$E$17,0)) -> FALSE
A10: =IF(ISBLANK(E10),"","OFVP") -> OFVP | B10: Chicago Conveners | D10: 2773 | E10: UNIVERSAL FAMILY CONNECTION | G10: 45747 | H10: 24999.95 | I10: 2022 | J10: Chicago | K10: Cook | L10: Englewood | M10: =IF(ISNUMBER(MATCH(E10,_xlfn.VSTACK('VLookup Lists'!$E$2:$E$17,'VLookup Lists'!$H$2:$H$38,'VLookup Lists'!$J$2:$J$8),0)),1,0) -> 0 | N10: =IFERROR(IF(VLOOKUP($D10,'VLookup Lists'!$B$11:$C$29,2,FALSE)="FLIP",1,0),"") -> 0 | O10: =ISNUMBER(MATCH($E10,'VLookup Lists'!$E$2:$E$17,0)) -> FALSE
A11: =IF(ISBLANK(E11),"","OFVP") -> OFVP | B11: Chicago Conveners | D11: 2773 | E11: WHAT ABOUT US CHARITABLE | G11: 45747 | H11: 25000 | I11: 2022 | J11: Chicago | K11: Cook | L11: Austin | M11: =IF(ISNUMBER(MATCH(E11,_xlfn.VSTACK('VLookup Lists'!$E$2:$E$17,'VLookup Lists'!$H$2:$H$38,'VLookup Lists'!$J$2:$J$8),0)),1,0) -> 0 | N11: =IFERROR(IF(VLOOKUP($D11,'VLookup Lists'!$B$11:$C$29,2,FALSE)="FLIP",1,0),"") -> 0 | O11: =ISNUMBER(MATCH($E11,'VLookup Lists'!$E$2:$E$17,0)) -> FALSE
A12: =IF(ISBLANK(E12),"","OFVP") -> OFVP | B12: Chicago Conveners | D12: 2773 | E12: YMCA OF METROPOLITAN CHICAGO | G12: 45747 | H12: 24075 | I12: 2022 | J12: Chicago | K12: Cook | L12: Chicago Lawn | M12: =IF(ISNUMBER(MATCH(E12,_xlfn.VSTACK('VLookup Lists'!$E$2:$E$17,'VLookup Lists'!$H$2:$H$38,'VLookup Lists'!$J$2:$J$8),0)),1,0) -> 1 | N12: =IFERROR(IF(VLOOKUP($D12,'VLookup Lists'!$B$11:$C$29,2,FALSE)="FLIP",1,0),"") -> 0 | O12: =ISNUMBER(MATCH($E12,'VLookup Lists'!$E$2:$E$17,0)) -> FALSE
A13: =IF(ISBLANK(E13),"","OFVP") -> OFVP | B13: Chicago Conveners | D13: 2773 | E13: YMCA OF METROPOLITAN CHICAGO | G13: 45747 | H13: 24075 | I13: 2022 | J13: Chicago | K13: Cook | L13: East Garfield Park | M13: =IF(ISNUMBER(MATCH(E13,_xlfn.VSTACK('VLookup Lists'!$E$2:$E$17,'VLookup Lists'!$H$2:$H$38,'VLookup Lists'!$J$2:$J$8),0)),1,0) -> 1 | N13: =IFERROR(IF(VLOOKUP($D13,'VLookup Lists'!$B$11:$C$29,2,FALSE)="FLIP",1,0),"") -> 0 | O13: =ISNUMBER(MATCH($E13,'VLookup Lists'!$E$2:$E$17,0)) -> FALSE
... A42: =IF(ISBLANK(E42),"","OFVP") -> OFVP | B42: Violence Prevention | D42: 2774 | E42: The Restorative Project, Inc. | G42: 45688 | H42: 75000 | I42: 2022 | J42: Chicago | K42: Cook | L42: Chicago Lawn | M42: =IF(ISNUMBER(MATCH(E42,_xlfn.VSTACK('VLookup Lists'!$E$2:$E$17,'VLookup Lists'!$H$2:$H$38,'VLookup Lists'!$J$2:$J$8),0)),1,0) -> 1 | N42: =IFERROR(IF(VLOOKUP($D42,'VLookup Lists'!$B$11:$C$29,2,FALSE)="FLIP",1,0),"") -> 0 | O42: =ISNUMBER(MATCH($E42,'VLookup Lists'!$E$2:$E$17,0)) -> FALSE
A43: =IF(ISBLANK(E43),"","OFVP") -> OFVP | B43: Violence Prevention | D43: 2774 | E43: The Restorative Project, Inc. | H43: 75000 | I43: 2022 | J43: Chicago | K43: Cook | L43: Englewood | M43: =IF(ISNUMBER(MATCH(E43,_xlfn.VSTACK('VLookup Lists'!$E$2:$E$17,'VLookup Lists'!$H$2:$H$38,'VLookup Lists'!$J$2:$J$8),0)),1,0) -> 1 | N43: =IFERROR(IF(VLOOKUP($D43,'VLookup Lists'!$B$11:$C$29,2,FALSE)="FLIP",1,0),"") -> 0 | O43: =ISNUMBER(MATCH($E43,'VLookup Lists'!$E$2:$E$17,0)) -> FALSE
A44: =IF(ISBLANK(E44),"","OFVP") -> OFVP | B44: Violence Prevention | D44: 2774 | E44: The Restorative Project, Inc. | G44: 45688 | H44: 75000 | I44: 2022 | J44: Chicago | K44: Cook | L44: West Englewood | M44: =IF(ISNUMBER(MATCH(E44,_xlfn.VSTACK('VLookup Lists'!$E$2:$E$17,'VLookup Lists'!$H$2:$H$38,'VLookup Lists'!$J$2:$J$8),0)),1,0) -> 1 | N44: =IFERROR(IF(VLOOKUP($D44,'VLookup Lists'!$B$11:$C$29,2,FALSE)="FLIP",1,0),"") -> 0 | O44: =ISNUMBER(MATCH($E44,'VLookup Lists'!$E$2:$E$17,0)) -> FALSE
A45: =IF(ISBLANK(E45),"","OFVP") -> OFVP | B45: Violence Prevention | D45: 2774 | E45: Together Chicago, Inc. | G45: 45688 | H45: 74998 | I45: 2022 | J45: Chicago | K45: Cook | L45: Austin | M45: =IF(ISNUMBER(MATCH(E45,_xlfn.VSTACK('VLookup Lists'!$E$2:$E$17,'VLookup Lists'!$H$2:$H$38,'VLookup Lists'!$J$2:$J$8),0)),1,0) -> 1 | N45: =IFERROR(IF(VLOOKUP($D45,'VLookup Lists'!$B$11:$C$29,2,FALSE)="FLIP",1,0),"") -> 0 | O45: =ISNUMBER(MATCH($E45,'VLookup Lists'!$E$2:$E$17,0)) -> TRUE
A46: =IF(ISBLANK(E46),"","OFVP") -> OFVP | B46: Violence Prevention | D46: 2774 | E46: Together Chicago, Inc. | G46: 45688 | H46: 74998 | I46: 2022 | J46: Chicago | K46: Cook | L46: East Garfield Park | M46: =IF(ISNUMBER(MATCH(E46,_xlfn.VSTACK('VLookup Lists'!$E$2:$E$17,'VLookup Lists'!$H$2:$H$38,'VLookup Lists'!$J$2:$J$8),0)),1,0) -> 1 | N46: =IFERROR(IF(VLOOKUP($D46,'VLookup Lists'!$B$11:$C$29,2,FALSE)="FLIP",1,0),"") -> 0 | O46: =ISNUMBER(MATCH($E46,'VLookup Lists'!$E$2:$E$17,0)) -> TRUE
A47: =IF(ISBLANK(E47),"","OFVP") -> OFVP | B47: Violence Prevention | D47: 2774 | E47: UCAN | G47: 45688 | H47: 99223 | I47: 2022 | J47: Chicago | K47: Cook | L47: North Lawndale | M47: =IF(ISNUMBER(MATCH(E47,_xlfn.VSTACK('VLookup Lists'!$E$2:$E$17,'VLookup Lists'!$H$2:$H$38,'VLookup Lists'!$J$2:$J$8),0)),1,0) -> 1 | N47: =IFERROR(IF(VLOOKUP($D47,'VLookup Lists'!$B$11:$C$29,2,FALSE)="FLIP",1,0),"") -> 0 | O47: =ISNUMBER(MATCH($E47,'VLookup Lists'!$E$2:$E$17,0)) -> TRUE
A48: =IF(ISBLANK(E48),"","OFVP") -> OFVP | B48: Violence Prevention | D48: 2774 | E48: The University of Chicago Medical Center | G48: 45688 | H48: 43123 | I48: 2022 | J48: Chicago | K48: Cook | L48: South Chicago | M48: =IF(ISNUMBER(MATCH(E48,_xlfn.VSTACK('VLookup Lists'!$E$2:$E$17,'VLookup Lists'!$H$2:$H$38,'VLookup Lists'!$J$2:$J$8),0)),1,0) -> 0 | N48: =IFERROR(IF(VLOOKUP($D48,'VLookup Lists'!$B$11:$C$29,2,FALSE)="FLIP",1,0),"") -> 0 | O48: =ISNUMBER(MATCH($E48,'VLookup Lists'!$E$2:$E$17,0)) -> FALSE
A49: =IF(ISBLANK(E49),"","OFVP") -> OFVP | B49: Violence Prevention | D49: 2774 | E49: The University of Chicago Medical Center | G49: 45838 | H49: 43123 | I49: 2022 | J49: Chicago | K49: Cook | L49: South Shore | M49: =IF(ISNUMBER(MATCH(E49,_xlfn.VSTACK('VLookup Lists'!$E$2:$E$17,'VLookup Lists'!$H$2:$H$38,'VLookup Lists'!$J$2:$J$8),0)),1,0) -> 0 | N49: =IFERROR(IF(VLOOKUP($D49,'VLookup Lists'!$B$11:$C$29,2,FALSE)="FLIP",1,0),"") -> 0 | O49: =ISNUMBER(MATCH($E49,'VLookup Lists'!$E$2:$E$17,0)) -> FALSE
A50: =IF(ISBLANK(E50),"","OFVP") -> OFVP | B50: Violence Prevention | D50: 2774 | E50: The University of Chicago Medical Center | G50: 45688 | H50: 43123 | I50: 2022 | J50: Chicago | K50: Cook | L50: Woodlawn | M50: =IF(ISNUMBER(MATCH(E50,_xlfn.VSTACK('VLookup Lists'!$E$2:$E$17,'VLookup Lists'!$H$2:$H$38,'VLookup Lists'!$J$2:$J$8),0)),1,0) -> 0 | N50: =IFERROR(IF(VLOOKUP($D50,'VLookup Lists'!$B$11:$C$29,2,FALSE)="FLIP",1,0),"") -> 0 | O50: =ISNUMBER(MATCH($E50,'VLookup Lists'!$E$2:$E$17,0)) -> FALSE
A51: =IF(ISBLANK(E51),"","OFVP") -> OFVP | B51: Violence Prevention | D51: 2774 | E51: YMCA OF METROPOLITAN CHICAGO | G51: 45688 | H51: 74860 | I51: 2022 | J51: Chicago | K51: Cook | L51: Humboldt Park | M51: =IF(ISNUMBER(MATCH(E51,_xlfn.VSTACK('VLookup Lists'!$E$2:$E$17,'VLookup Lists'!$H$2:$H$38,'VLookup Lists'!$J$2:$J$8),0)),1,0) -> 1 | N51: =IFERROR(IF(VLOOKUP($D51,'VLookup Lists'!$B$11:$C$29,2,FALSE)="FLIP",1,0),"") -> 0 | O51: =ISNUMBER(MATCH($E51,'VLookup Lists'!$E$2:$E$17,0)) -> FALSE
A52: =IF(ISBLANK(E52),"","OFVP") -> OFVP | B52: Violence Prevention | D52: 2774 | E52: YMCA OF METROPOLITAN CHICAGO | G52: 45688 | H52: 73647 | I52: 2022 | J52: Chicago | K52: Cook | L52: South Lawndale | M52: =IF(ISNUMBER(MATCH(E52,_xlfn.VSTACK('VLookup Lists'!$E$2:$E$17,'VLookup Lists'!$H$2:$H$38,'VLookup Lists'!$J$2:$J$8),0)),1,0) -> 1 | N52: =IFERROR(IF(VLOOKUP($D52,'VLookup Lists'!$B$11:$C$29,2,FALSE)="FLIP",1,0),"") -> 0 | O52: =ISNUMBER(MATCH($E52,'VLookup Lists'!$E$2:$E$17,0)) -> FALSE
A53: =IF(ISBLANK(E53),"","OFVP") -> OFVP | B53: Violence Prevention | D53: 2774 | E53: YMCA OF METROPOLITAN CHICAGO | G53: 45688 | H53: 73647 | I53: 2022 | J53: Chicago | K53: Cook | L53: Woodlawn | M53: =IF(ISNUMBER(MATCH(E53,_xlfn.VSTACK('VLookup Lists'!$E$2:$E$17,'VLookup Lists'!$H$2:$H$38,'VLookup Lists'!$J$2:$J$8),0)),1,0) -> 1 | N53: =IFERROR(IF(VLOOKUP($D53,'VLookup Lists'!$B$11:$C$29,2,FALSE)="FLIP",1,0),"") -> 0 | O53: =ISNUMBER(MATCH($E53,'VLookup Lists'!$E$2:$E$17,0)) -> FALSE
A54: =IF(ISBLANK(E54),"","OFVP") -> OFVP | B54: Youth Development | D54: 2775 | E54: Artists ReEnvisioning Tomorrow Inc. | G54: 45473 | H54: 24110 | I54: 2022 | J54: Greater Illinois | K54: Peoria | L54: Peoria | M54: =IF(ISNUMBER(MATCH(E54,_xlfn.VSTACK('VLookup Lists'!$E$2:$E$17,'VLookup Lists'!$H$2:$H$38,'VLookup Lists'!$J$2:$J$8),0)),1,0) -> 0 | N54: =IFERROR(IF(VLOOKUP($D54,'VLookup Lists'!$B$11:$C$29,2,FALSE)="FLIP",1,0),"") -> 0 | O54: =ISNUMBER(MATCH($E54,'VLookup Lists'!$E$2:$E$17,0)) -> FALSE
A55: =IF(ISBLANK(E55),"","OFVP") -> OFVP | B55: Youth Development | D55: 2775 | E55: AURORA AREA AFRICAN AMERICAN MEN OF UNITY | G55: 45473 | H55: 25466 | I55: 2022 | J55: Greater Illinois | K55: Dupage, Kane, Kendall, Will | L55: Aurora | M55: =IF(ISNUMBER(MATCH(E55,_xlfn.VSTACK('VLookup Lists'!$E$2:$E$17,'VLookup Lists'!$H$2:$H$38,'VLookup Lists'!$J$2:$J$8),0)),1,0) -> 0 | N55: =IFERROR(IF(VLOOKUP($D55,'VLookup Lists'!$B$11:$C$29,2,FALSE)="FLIP",1,0),"") -> 0 | O55: =ISNUMBER(MATCH($E55,'VLookup Lists'!$E$2:$E$17,0)) -> FALSE
... A75: =IF(ISBLANK(E75),"","OFVP") -> OFVP | B75: Youth Development | D75: 2775 | E75: YMCA OF ROCK RIVER VALLEY | G75: 45473 | H75: 12396 | I75: 2022 | J75: Greater Illinois | K75: Winnebago | L75: Rockford | M75: =IF(ISNUMBER(MATCH(E75,_xlfn.VSTACK('VLookup Lists'!$E$2:$E$17,'VLookup Lists'!$H$2:$H$38,'VLookup Lists'!$J$2:$J$8),0)),1,0) -> 0 | N75: =IFERROR(IF(VLOOKUP($D75,'VLookup Lists'!$B$11:$C$29,2,FALSE)="FLIP",1,0),"") -> 0 | O75: =ISNUMBER(MATCH($E75,'VLookup Lists'!$E$2:$E$17,0)) -> FALSE
A76: =IF(ISBLANK(E76),"","OFVP") -> OFVP | B76: High Risk Youth Intervention Services | D76: 2776 | E76: Brightpoint (formerly Children's Home and Aid Society of Illinois) | H76: 74870 | I76: 2022 | J76: Chicago | K76: Cook | L76: z HRYIS | M76: =IF(ISNUMBER(MATCH(E76,_xlfn.VSTACK('VLookup Lists'!$E$2:$E$17,'VLookup Lists'!$H$2:$H$38,'VLookup Lists'!$J$2:$J$8),0)),1,0) -> 0 | N76: =IFERROR(IF(VLOOKUP($D76,'VLookup Lists'!$B$11:$C$29,2,FALSE)="FLIP",1,0),"") -> 0 | O76: =ISNUMBER(MATCH($E76,'VLookup Lists'!$E$2:$E$17,0)) -> FALSE
A77: =IF(ISBLANK(E77),"","OFVP") -> OFVP | B77: High Risk Youth Intervention Services | D77: 2776 | E77: Community Counseling Center (C4) | H77: 124409 | I77: 2022 | J77: Chicago | K77: Cook | L77: z HRYIS | M77: =IF(ISNUMBER(MATCH(E77,_xlfn.VSTACK('VLookup Lists'!$E$2:$E$17,'VLookup Lists'!$H$2:$H$38,'VLookup Lists'!$J$2:$J$8),0)),1,0) -> 0 | N77: =IFERROR(IF(VLOOKUP($D77,'VLookup Lists'!$B$11:$C$29,2,FALSE)="FLIP",1,0),"") -> 0 | O77: =ISNUMBER(MATCH($E77,'VLookup Lists'!$E$2:$E$17,0)) -> FALSE
A78: =IF(ISBLANK(E78),"","OFVP") -> OFVP | B78: High Risk Youth Intervention Services | D78: 2776 | E78: Metropolitan Family Services | H78: 100499 | I78: 2022 | J78: Chicago | K78: Cook | L78: z HRYIS | M78: =IF(ISNUMBER(MATCH(E78,_xlfn.VSTACK('VLookup Lists'!$E$2:$E$17,'VLookup Lists'!$H$2:$H$38,'VLookup Lists'!$J$2:$J$8),0)),1,0) -> 1 | N78: =IFERROR(IF(VLOOKUP($D78,'VLookup Lists'!$B$11:$C$29,2,FALSE)="FLIP",1,0),"") -> 0 | O78: =ISNUMBER(MATCH($E78,'VLookup Lists'!$E$2:$E$17,0)) -> TRUE
A79: =IF(ISBLANK(E79),"","OFVP") -> OFVP | B79: High Risk Youth Intervention Services | D79: 2776 | E79: MOUNT SINAI HOSP MEDICAL | G79: 45838 | H79: 49410 | I79: 2022 | J79: Chicago | K79: Cook | L79: z HRYIS | M79: =IF(ISNUMBER(MATCH(E79,_xlfn.VSTACK('VLookup Lists'!$E$2:$E$17,'VLookup Lists'!$H$2:$H$38,'VLookup Lists'!$J$2:$J$8),0)),1,0) -> 0 | N79: =IFERROR(IF(VLOOKUP($D79,'VLookup Lists'!$B$11:$C$29,2,FALSE)="FLIP",1,0),"") -> 0 | O79: =ISNUMBER(MATCH($E79,'VLookup Lists'!$E$2:$E$17,0)) -> FALSE
A80: =IF(ISBLANK(E80),"","OFVP") -> OFVP | B80: Trauma-Informed Behavioral Health | D80: 2600 | E80: Alternatives, Inc. | H80: 228823 | I80: 2023 | J80: Greater Illinois | K80: Lake | L80: Waukegan-North Chicago Cluster | M80: =IF(ISNUMBER(MATCH(E80,_xlfn.VSTACK('VLookup Lists'!$E$2:$E$17,'VLookup Lists'!$H$2:$H$38,'VLookup Lists'!$J$2:$J$8),0)),1,0) -> 0 | N80: =IFERROR(IF(VLOOKUP($D80,'VLookup Lists'!$B$11:$C$29,2,FALSE)="FLIP",1,0),"") -> 0 | O80: =ISNUMBER(MATCH($E80,'VLookup Lists'!$E$2:$E$17,0)) -> FALSE
A81: =IF(ISBLANK(E81),"","OFVP") -> OFVP | B81: Trauma-Informed Behavioral Health | D81: 2600 | E81: Brightpoint (formerly Children's Home and Aid Society of Illinois) | G81: 45838 | H81: 155307 | I81: 2023 | J81: Greater Illinois | K81: St. Clair | L81: Belleville Cluster | M81: =IF(ISNUMBER(MATCH(E81,_xlfn.VSTACK('VLookup Lists'!$E$2:$E$17,'VLookup Lists'!$H$2:$H$38,'VLookup Lists'!$J$2:$J$8),0)),1,0) -> 0 | N81: =IFERROR(IF(VLOOKUP($D81,'VLookup Lists'!$B$11:$C$29,2,FALSE)="FLIP",1,0),"") -> 0 | O81: =ISNUMBER(MATCH($E81,'VLookup Lists'!$E$2:$E$17,0)) -> FALSE
A82: =IF(ISBLANK(E82),"","OFVP") -> OFVP | B82: Trauma-Informed Behavioral Health | D82: 2600 | E82: Comprehensive Community Solutions, Inc. | H82: 318806 | I82: 2023 | J82: Greater Illinois | K82: Winnebago | L82: Rockford | M82: =IF(ISNUMBER(MATCH(E82,_xlfn.VSTACK('VLookup Lists'!$E$2:$E$17,'VLookup Lists'!$H$2:$H$38,'VLookup Lists'!$J$2:$J$8),0)),1,0) -> 0 | N82: =IFERROR(IF(VLOOKUP($D82,'VLookup Lists'!$B$11:$C$29,2,FALSE)="FLIP",1,0),"") -> 0 | O82: =ISNUMBER(MATCH($E82,'VLookup Lists'!$E$2:$E$17,0)) -> FALSE
A83: =IF(ISBLANK(E83),"","OFVP") -> OFVP | B83: Trauma-Informed Behavioral Health | D83: 2600 | E83: FAMILY SERVICE AND MENTAL HEALTH CENTER OF CICERO | H83: 175000 | I83: 2023 | J83: Greater Illinois | K83: Cook | L83: Berwyn-Cicero Cluster | M83: =IF(ISNUMBER(MATCH(E83,_xlfn.VSTACK('VLookup Lists'!$E$2:$E$17,'VLookup Lists'!$H$2:$H$38,'VLookup Lists'!$J$2:$J$8),0)),1,0) -> 0 | N83: =IFERROR(IF(VLOOKUP($D83,'VLookup Lists'!$B$11:$C$29,2,FALSE)="FLIP",1,0),"") -> 0 | O83: =ISNUMBER(MATCH($E83,'VLookup Lists'!$E$2:$E$17,0)) -> FALSE
A84: =IF(ISBLANK(E84),"","OFVP") -> OFVP | B84: Trauma-Informed Behavioral Health | D84: 2600 | E84: GOODWILL INDUSTRIES OF CENTRAL ILLINOIS | H84: 128028 | I84: 2023 | J84: Greater Illinois | K84: Peoria | L84: Peoria | M84: =IF(ISNUMBER(MATCH(E84,_xlfn.VSTACK('VLookup Lists'!$E$2:$E$17,'VLookup Lists'!$H$2:$H$38,'VLookup Lists'!$J$2:$J$8),0)),1,0) -> 0 | N84: =IFERROR(IF(VLOOKUP($D84,'VLookup Lists'!$B$11:$C$29,2,FALSE)="FLIP",1,0),"") -> 0 | O84: =ISNUMBER(MATCH($E84,'VLookup Lists'!$E$2:$E$17,0)) -> FALSE
A85: =IF(ISBLANK(E85),"","OFVP") -> OFVP | B85: Trauma-Informed Behavioral Health | D85: 2600 | E85: KIDS ABOVE ALL | H85: 177001 | I85: 2023 | J85: Greater Illinois | K85: Lake | L85: Waukegan-North Chicago Cluster | M85: =IF(ISNUMBER(MATCH(E85,_xlfn.VSTACK('VLookup Lists'!$E$2:$E$17,'VLookup Lists'!$H$2:$H$38,'VLookup Lists'!$J$2:$J$8),0)),1,0) -> 0 | N85: =IFERROR(IF(VLOOKUP($D85,'VLookup Lists'!$B$11:$C$29,2,FALSE)="FLIP",1,0),"") -> 0 | O85: =ISNUMBER(MATCH($E85,'VLookup Lists'!$E$2:$E$17,0)) -> FALSE
A86: =IF(ISBLANK(E86),"","OFVP") -> OFVP | B86: Trauma-Informed Behavioral Health | D86: 2600 | E86: Lake County Crisis Center for the Prevention and Treatment of Domestic Violence, INC DBA A Safe Place | H86: 175000 | I86: 2023 | J86: Greater Illinois | K86: Lake | L86: Waukegan-North Chicago Cluster | M86: =IF(ISNUMBER(MATCH(E86,_xlfn.VSTACK('VLookup Lists'!$E$2:$E$17,'VLookup Lists'!$H$2:$H$38,'VLookup Lists'!$J$2:$J$8),0)),1,0) -> 0 | N86: =IFERROR(IF(VLOOKUP($D86,'VLookup Lists'!$B$11:$C$29,2,FALSE)="FLIP",1,0),"") -> 0 | O86: =ISNUMBER(MATCH($E86,'VLookup Lists'!$E$2:$E$17,0)) -> FALSE
A87: =IF(ISBLANK(E87),"","OFVP") -> OFVP | B87: Trauma-Informed Behavioral Health | D87: 2600 | E87: Pilsen Wellness Center, Inc. | H87: 175000 | I87: 2023 | J87: Greater Illinois | K87: Cook | L87: Berwyn-Cicero Cluster | M87: =IF(ISNUMBER(MATCH(E87,_xlfn.VSTACK('VLookup Lists'!$E$2:$E$17,'VLookup Lists'!$H$2:$H$38,'VLookup Lists'!$J$2:$J$8),0)),1,0) -> 0 | N87: =IFERROR(IF(VLOOKUP($D87,'VLookup Lists'!$B$11:$C$29,2,FALSE)="FLIP",1,0),"") -> 0 | O87: =ISNUMBER(MATCH($E87,'VLookup Lists'!$E$2:$E$17,0)) -> FALSE
A88: =IF(ISBLANK(E88),"","OFVP") -> OFVP | B88: Trauma-Informed Behavioral Health | D88: 2600 | E88: SGA Youth and Family Services, NFP | H88: 175000 | I88: 2023 | J88: Greater Illinois | K88: Lake | L88: Waukegan-North Chicago Cluster | M88: =IF(ISNUMBER(MATCH(E88,_xlfn.VSTACK('VLookup Lists'!$E$2:$E$17,'VLookup Lists'!$H$2:$H$38,'VLookup Lists'!$J$2:$J$8),0)),1,0) -> 0 | N88: =IFERROR(IF(VLOOKUP($D88,'VLookup Lists'!$B$11:$C$29,2,FALSE)="FLIP",1,0),"") -> 0 | O88: =ISNUMBER(MATCH($E88,'VLookup Lists'!$E$2:$E$17,0)) -> FALSE
A89: =IF(ISBLANK(E89),"","OFVP") -> OFVP | B89: Trauma-Informed Behavioral Health | D89: 2600 | E89: TOUCHETTE REGIONAL HOSPITAL | G89: 45838 | H89: 164234 | I89: 2023 | J89: Greater Illinois | K89: St. Clair | L89: Belleville Cluster | M89: =IF(ISNUMBER(MATCH(E89,_xlfn.VSTACK('VLookup Lists'!$E$2:$E$17,'VLookup Lists'!$H$2:$H$38,'VLookup Lists'!$J$2:$J$8),0)),1,0) -> 0 | N89: =IFERROR(IF(VLOOKUP($D89,'VLookup Lists'!$B$11:$C$29,2,FALSE)="FLIP",1,0),"") -> 0 | O89: =ISNUMBER(MATCH($E89,'VLookup Lists'!$E$2:$E$17,0)) -> FALSE
A90: =IF(ISBLANK(E90),"","OFVP") -> OFVP | B90: Trauma-Informed Behavioral Health | D90: 2600 | E90: YOUTH CROSSROADS | H90: 180489 | I90: 2023 | J90: Greater Illinois | K90: Cook | L90: Berwyn-Cicero Cluster | M90: =IF(ISNUMBER(MATCH(E90,_xlfn.VSTACK('VLookup Lists'!$E$2:$E$17,'VLookup Lists'!$H$2:$H$38,'VLookup Lists'!$J$2:$J$8),0)),1,0) -> 0 | N90: =IFERROR(IF(VLOOKUP($D90,'VLookup Lists'!$B$11:$C$29,2,FALSE)="FLIP",1,0),"") -> 0 | O90: =ISNUMBER(MATCH($E90,'VLookup Lists'!$E$2:$E$17,0)) -> FALSE
A91: =IF(ISBLANK(E91),"","OFVP") -> OFVP | B91: TA Services Violence Prevention | D91: 2771 | E91: Acclivus, Inc. | G91: 45930 | H91: 1785237 | I91: 2023 | J91: Chicago | K91: Cook | L91: z TTAS - Chicago | M91: =IF(ISNUMBER(MATCH(E91,_xlfn.VSTACK('VLookup Lists'!$E$2:$E$17,'VLookup Lists'!$H$2:$H$38,'VLookup Lists'!$J$2:$J$8),0)),1,0) -> 1 | N91: =IFERROR(IF(VLOOKUP($D91,'VLookup Lists'!$B$11:$C$29,2,FALSE)="FLIP",1,0),"") -> 0 | O91: =ISNUMBER(MATCH($E91,'VLookup Lists'!$E$2:$E$17,0)) -> FALSE
A92: =IF(ISBLANK(E92),"","OFVP") -> OFVP | B92: TA Services Violence Prevention | D92: 2771 | E92: Metropolitan Family Services | G92: 45565 | H92: 733394 | I92: 2023 | J92: Chicago | K92: Cook | L92: z TTAS - Chicago | M92: =IF(ISNUMBER(MATCH(E92,_xlfn.VSTACK('VLookup Lists'!$E$2:$E$17,'VLookup Lists'!$H$2:$H$38,'VLookup Lists'!$J$2:$J$8),0)),1,0) -> 1 | N92: =IFERROR(IF(VLOOKUP($D92,'VLookup Lists'!$B$11:$C$29,2,FALSE)="FLIP",1,0),"") -> 0 | O92: =ISNUMBER(MATCH($E92,'VLookup Lists'!$E$2:$E$17,0)) -> TRUE
A93: =IF(ISBLANK(E93),"","OFVP") -> OFVP | B93: TA Services Violence Prevention | D93: 2771 | E93: UNIVERSAL FAMILY CONNECTION | G93: 45344 | H93: 595200 | I93: 2023 | J93: Chicago | K93: Cook | L93: z TTAS - Chicago | M93: =IF(ISNUMBER(MATCH(E93,_xlfn.VSTACK('VLookup Lists'!$E$2:$E$17,'VLookup Lists'!$H$2:$H$38,'VLookup Lists'!$J$2:$J$8),0)),1,0) -> 0 | N93: =IFERROR(IF(VLOOKUP($D93,'VLookup Lists'!$B$11:$C$29,2,FALSE)="FLIP",1,0),"") -> 0 | O93: =ISNUMBER(MATCH($E93,'VLookup Lists'!$E$2:$E$17,0)) -> FALSE
A94: =IF(ISBLANK(E94),"","OFVP") -> OFVP | B94: TA Services Youth Development | D94: 2772 | E94: BLACK COMMUNITY PROVIDER | G94: 45565 | H94: 534847 | I94: 2023 | J94: Chicago | K94: Cook | L94: z TTAS - Chicago | M94: =IF(ISNUMBER(MATCH(E94,_xlfn.VSTACK('VLookup Lists'!$E$2:$E$17,'VLookup Lists'!$H$2:$H$38,'VLookup Lists'!$J$2:$J$8),0)),1,0) -> 0 | N94: =IFERROR(IF(VLOOKUP($D94,'VLookup Lists'!$B$11:$C$29,2,FALSE)="FLIP",1,0),"") -> 0 | O94: =ISNUMBER(MATCH($E94,'VLookup Lists'!$E$2:$E$17,0)) -> FALSE
A95: =IF(ISBLANK(E95),"","OFVP") -> OFVP | B95: TA Services Youth Development | D95: 2772 | E95: Metropolitan Family Services | G95: 45565 | H95: 751678 | I95: 2023 | J95: Chicago | K95: Cook | L95: z TTAS - Chicago | M95: =IF(ISNUMBER(MATCH(E95,_xlfn.VSTACK('VLookup Lists'!$E$2:$E$17,'VLookup Lists'!$H$2:$H$38,'VLookup Lists'!$J$2:$J$8),0)),1,0) -> 1 | N95: =IFERROR(IF(VLOOKUP($D95,'VLookup Lists'!$B$11:$C$29,2,FALSE)="FLIP",1,0),"") -> 0 | O95: =ISNUMBER(MATCH($E95,'VLookup Lists'!$E$2:$E$17,0)) -> TRUE
A96: =IF(ISBLANK(E96),"","OFVP") -> OFVP | B96: TA Services Youth Development | D96: 2772 | E96: Prevention First, Inc | G96: 45565 | H96: 753663 | I96: 2023 | J96: Chicago | K96: Cook | L96: z TTAS - Chicago | M96: =IF(ISNUMBER(MATCH(E96,_xlfn.VSTACK('VLookup Lists'!$E$2:$E$17,'VLookup Lists'!$H$2:$H$38,'VLookup Lists'!$J$2:$J$8),0)),1,0) -> 0 | N96: =IFERROR(IF(VLOOKUP($D96,'VLookup Lists'!$B$11:$C$29,2,FALSE)="FLIP",1,0),"") -> 0 | O96: =ISNUMBER(MATCH($E96,'VLookup Lists'!$E$2:$E$17,0)) -> FALSE
A97: =IF(ISBLANK(E97),"","OFVP") -> OFVP | B97: Chicago Conveners | D97: 2773 | E97: ACCLIVUS, INC. | G97: 45747 | H97: 100000 | I97: 2023 | J97: Chicago | K97: Cook | L97: Fuller Park | M97: =IF(ISNUMBER(MATCH(E97,_xlfn.VSTACK('VLookup Lists'!$E$2:$E$17,'VLookup Lists'!$H$2:$H$38,'VLookup Lists'!$J$2:$J$8),0)),1,0) -> 1 | N97: =IFERROR(IF(VLOOKUP($D97,'VLookup Lists'!$B$11:$C$29,2,FALSE)="FLIP",1,0),"") -> 0 | O97: =ISNUMBER(MATCH($E97,'VLookup Lists'!$E$2:$E$17,0)) -> FALSE
A98: =IF(ISBLANK(E98),"","OFVP") -> OFVP | B98: Chicago Conveners | D98: 2773 | E98: ACCLIVUS, INC. | G98: 45747 | H98: 100000 | I98: 2023 | J98: Chicago | K98: Cook | L98: Greater Grand Crossing | M98: =IF(ISNUMBER(MATCH(E98,_xlfn.VSTACK('VLookup Lists'!$E$2:$E$17,'VLookup Lists'!$H$2:$H$38,'VLookup Lists'!$J$2:$J$8),0)),1,0) -> 1 | N98: =IFERROR(IF(VLOOKUP($D98,'VLookup Lists'!$B$11:$C$29,2,FALSE)="FLIP",1,0),"") -> 0 | O98: =ISNUMBER(MATCH($E98,'VLookup Lists'!$E$2:$E$17,0)) -> FALSE
A99: =IF(ISBLANK(E99),"","OFVP") -> OFVP | B99: Chicago Conveners | D99: 2773 | E99: ACCLIVUS, INC. | G99: 45747 | H99: 100000 | I99: 2023 | J99: Chicago | K99: Cook | L99: Washington Park | M99: =IF(ISNUMBER(MATCH(E99,_xlfn.VSTACK('VLookup Lists'!$E$2:$E$17,'VLookup Lists'!$H$2:$H$38,'VLookup Lists'!$J$2:$J$8),0)),1,0) -> 1 | N99: =IFERROR(IF(VLOOKUP($D99,'VLookup Lists'!$B$11:$C$29,2,FALSE)="FLIP",1,0),"") -> 0 | O99: =ISNUMBER(MATCH($E99,'VLookup Lists'!$E$2:$E$17,0)) -> FALSE
A100: =IF(ISBLANK(E100),"","OFVP") -> OFVP | B100: Chicago Conveners | D100: 2773 | E100: ACCLIVUS, INC. | G100: 45747 | H100: 100000 | I100: 2023 | J100: Chicago | K100: Cook | L100: West Pullman | M100: =IF(ISNUMBER(MATCH(E100,_xlfn.VSTACK('VLookup Lists'!$E$2:$E$17,'VLookup Lists'!$H$2:$H$38,'VLookup Lists'!$J$2:$J$8),0)),1,0) -> 1 | N100: =IFERROR(IF(VLOOKUP($D100,'VLookup Lists'!$B$11:$C$29,2,FALSE)="FLIP",1,0),"") -> 0 | O100: =ISNUMBER(MATCH($E100,'VLookup Lists'!$E$2:$E$17,0)) -> FALSE
A101: =IF(ISBLANK(E101),"","OFVP") -> OFVP | B101: Chicago Conveners | D101: 2773 | E101: HOPE OPPORTUNITY PURPOSE | G101: 45747 | H101: 100000 | I101: 2023 | J101: Chicago | K101: Cook | L101: New City | M101: =IF(ISNUMBER(MATCH(E101,_xlfn.VSTACK('VLookup Lists'!$E$2:$E$17,'VLookup Lists'!$H$2:$H$38,'VLookup Lists'!$J$2:$J$8),0)),1,0) -> 0 | N101: =IFERROR(IF(VLOOKUP($D101,'VLookup Lists'!$B$11:$C$29,2,FALSE)="FLIP",1,0),"") -> 0 | O101: =ISNUMBER(MATCH($E101,'VLookup Lists'!$E$2:$E$17,0)) -> FALSE
A102: =IF(ISBLANK(E102),"","OFVP") -> OFVP | B102: Chicago Conveners | D102: 2773 | E102: Lawrence Hall Youth Services | G102: 45747 | H102: 100000 | I102: 2023 | J102: Chicago | K102: Cook | L102: South Shore | M102: =IF(ISNUMBER(MATCH(E102,_xlfn.VSTACK('VLookup Lists'!$E$2:$E$17,'VLookup Lists'!$H$2:$H$38,'VLookup Lists'!$J$2:$J$8),0)),1,0) -> 0 | N102: =IFERROR(IF(VLOOKUP($D102,'VLookup Lists'!$B$11:$C$29,2,FALSE)="FLIP",1,0),"") -> 0 | O102: =ISNUMBER(MATCH($E102,'VLookup Lists'!$E$2:$E$17,0)) -> FALSE
... A136: =IF(ISBLANK(E136),"","OFVP") -> OFVP | B136: Violence Prevention | D136: 2774 | E136: HOPE OPPORTUNITY PURPOSE | G136: 45688 | H136: 559353 | I136: 2023 | J136: Chicago | K136: Cook | L136: South Lawndale | M136: =IF(ISNUMBER(MATCH(E136,_xlfn.VSTACK('VLookup Lists'!$E$2:$E$17,'VLookup Lists'!$H$2:$H$38,'VLookup Lists'!$J$2:$J$8),0)),1,0) -> 0 | N136: =IFERROR(IF(VLOOKUP($D136,'VLookup Lists'!$B$11:$C$29,2,FALSE)="FLIP",1,0),"") -> 0 | O136: =ISNUMBER(MATCH($E136,'VLookup Lists'!$E$2:$E$17,0)) -> FALSE
A137: =IF(ISBLANK(E137),"","OFVP") -> OFVP | B137: Violence Prevention | D137: 2774 | E137: I & F Incorporated, NFP | H137: 112422 | I137: 2023 | J137: Chicago | K137: Cook | L137: Englewood | M137: =IF(ISNUMBER(MATCH(E137,_xlfn.VSTACK('VLookup Lists'!$E$2:$E$17,'VLookup Lists'!$H$2:$H$38,'VLookup Lists'!$J$2:$J$8),0)),1,0) -> 0 | N137: =IFERROR(IF(VLOOKUP($D137,'VLookup Lists'!$B$11:$C$29,2,FALSE)="FLIP",1,0),"") -> 0 | O137: =ISNUMBER(MATCH($E137,'VLookup Lists'!$E$2:$E$17,0)) -> FALSE
A138: =IF(ISBLANK(E138),"","OFVP") -> OFVP | B138: Violence Prevention | D138: 2774 | E138: I & F Incorporated, NFP | G138: 45688 | H138: 112422 | I138: 2023 | J138: Chicago | K138: Cook | L138: West Englewood | M138: =IF(ISNUMBER(MATCH(E138,_xlfn.VSTACK('VLookup Lists'!$E$2:$E$17,'VLookup Lists'!$H$2:$H$38,'VLookup Lists'!$J$2:$J$8),0)),1,0) -> 0 | N138: =IFERROR(IF(VLOOKUP($D138,'VLookup Lists'!$B$11:$C$29,2,FALSE)="FLIP",1,0),"") -> 0 | O138: =ISNUMBER(MATCH($E138,'VLookup Lists'!$E$2:$E$17,0)) -> FALSE
A139: =IF(ISBLANK(E139),"","OFVP") -> OFVP | B139: Violence Prevention | D139: 2774 | E139: Institute for Nonviolence Chicago (INVC) | G139: 45688 | H139: 535714.45 | I139: 2023 | J139: Chicago | K139: Cook | L139: Austin | M139: =IF(ISNUMBER(MATCH(E139,_xlfn.VSTACK('VLookup Lists'!$E$2:$E$17,'VLookup Lists'!$H$2:$H$38,'VLookup Lists'!$J$2:$J$8),0)),1,0) -> 1 | N139: =IFERROR(IF(VLOOKUP($D139,'VLookup Lists'!$B$11:$C$29,2,FALSE)="FLIP",1,0),"") -> 0 | O139: =ISNUMBER(MATCH($E139,'VLookup Lists'!$E$2:$E$17,0)) -> TRUE
A140: =IF(ISBLANK(E140),"","OFVP") -> OFVP | B140: Violence Prevention | D140: 2774 | E140: Institute for Nonviolence Chicago (INVC) | G140: 45688 | H140: 300000 | I140: 2023 | J140: Chicago | K140: Cook | L140: New City | M140: =IF(ISNUMBER(MATCH(E140,_xlfn.VSTACK('VLookup Lists'!$E$2:$E$17,'VLookup Lists'!$H$2:$H$38,'VLookup Lists'!$J$2:$J$8),0)),1,0) -> 1 | N140: =IFERROR(IF(VLOOKUP($D140,'VLookup Lists'!$B$11:$C$29,2,FALSE)="FLIP",1,0),"") -> 0 | O140: =ISNUMBER(MATCH($E140,'VLookup Lists'!$E$2:$E$17,0)) -> TRUE
A141: =IF(ISBLANK(E141),"","OFVP") -> OFVP | B141: Violence Prevention | D141: 2774 | E141: Institute for Nonviolence Chicago (INVC) | G141: 45688 | H141: 579168.56 | I141: 2023 | J141: Chicago | K141: Cook | L141: West Garfield Park | M141: =IF(ISNUMBER(MATCH(E141,_xlfn.VSTACK('VLookup Lists'!$E$2:$E$17,'VLookup Lists'!$H$2:$H$38,'VLookup Lists'!$J$2:$J$8),0)),1,0) -> 1 | N141: =IFERROR(IF(VLOOKUP($D141,'VLookup Lists'!$B$11:$C$29,2,FALSE)="FLIP",1,0),"") -> 0 | O141: =ISNUMBER(MATCH($E141,'VLookup Lists'!$E$2:$E$17,0)) -> TRUE
A142: =IF(ISBLANK(E142),"","OFVP") -> OFVP | B142: Violence Prevention | D142: 2774 | E142: Korrecting Our Own Lives | G142: 45688 | H142: 90000 | I142: 2023 | J142: Chicago | K142: Cook | L142: East Garfield Park | M142: =IF(ISNUMBER(MATCH(E142,_xlfn.VSTACK('VLookup Lists'!$E$2:$E$17,'VLookup Lists'!$H$2:$H$38,'VLookup Lists'!$J$2:$J$8),0)),1,0) -> 0 | N142: =IFERROR(IF(VLOOKUP($D142,'VLookup Lists'!$B$11:$C$29,2,FALSE)="FLIP",1,0),"") -> 0 | O142: =ISNUMBER(MATCH($E142,'VLookup Lists'!$E$2:$E$17,0)) -> FALSE
A143: =IF(ISBLANK(E143),"","OFVP") -> OFVP | B143: Violence Prevention | D143: 2774 | E143: Korrecting Our Own Lives | G143: 45688 | H143: 90000 | I143: 2023 | J143: Chicago | K143: Cook | L143: West Garfield Park | M143: =IF(ISNUMBER(MATCH(E143,_xlfn.VSTACK('VLookup Lists'!$E$2:$E$17,'VLookup Lists'!$H$2:$H$38,'VLookup Lists'!$J$2:$J$8),0)),1,0) -> 0 | N143: =IFERROR(IF(VLOOKUP($D143,'VLookup Lists'!$B$11:$C$29,2,FALSE)="FLIP",1,0),"") -> 0 | O143: =ISNUMBER(MATCH($E143,'VLookup Lists'!$E$2:$E$17,0)) -> FALSE
A144: =IF(ISBLANK(E144),"","OFVP") -> OFVP | B144: Violence Prevention | D144: 2774 | E144: LAWNDALE CHRISTIAN LEGAL CENTER | G144: 45688 | H144: 202139 | I144: 2023 | J144: Chicago | K144: Cook | L144: North Lawndale | M144: =IF(ISNUMBER(MATCH(E144,_xlfn.VSTACK('VLookup Lists'!$E$2:$E$17,'VLookup Lists'!$H$2:$H$38,'VLookup Lists'!$J$2:$J$8),0)),1,0) -> 0 | N144: =IFERROR(IF(VLOOKUP($D144,'VLookup Lists'!$B$11:$C$29,2,FALSE)="FLIP",1,0),"") -> 0 | O144: =ISNUMBER(MATCH($E144,'VLookup Lists'!$E$2:$E$17,0)) -> FALSE
A145: =IF(ISBLANK(E145),"","OFVP") -> OFVP | B145: Violence Prevention | D145: 2774 | E145: Major Adams Community Committee | G145: 45688 | H145: 75000 | I145: 2023 | J145: Chicago | K145: Cook | L145: East Garfield Park | M145: =IF(ISNUMBER(MATCH(E145,_xlfn.VSTACK('VLookup Lists'!$E$2:$E$17,'VLookup Lists'!$H$2:$H$38,'VLookup Lists'!$J$2:$J$8),0)),1,0) -> 0 | N145: =IFERROR(IF(VLOOKUP($D145,'VLookup Lists'!$B$11:$C$29,2,FALSE)="FLIP",1,0),"") -> 0 | O145: =ISNUMBER(MATCH($E145,'VLookup Lists'!$E$2:$E$17,0)) -> FALSE
A146: =IF(ISBLANK(E146),"","OFVP") -> OFVP | B146: Violence Prevention | D146: 2774 | E146: National Youth Advocate Program, Inc. | G146: 45688 | H146: 293675 | I146: 2023 | J146: Chicago | K146: Cook | L146: Auburn Gresham | M146: =IF(ISNUMBER(MATCH(E146,_xlfn.VSTACK('VLookup Lists'!$E$2:$E$17,'VLookup Lists'!$H$2:$H$38,'VLookup Lists'!$J$2:$J$8),0)),1,0) -> 0 | N146: =IFERROR(IF(VLOOKUP($D146,'VLookup Lists'!$B$11:$C$29,2,FALSE)="FLIP",1,0),"") -> 0 | O146: =ISNUMBER(MATCH($E146,'VLookup Lists'!$E$2:$E$17,0)) -> FALSE
A147: =IF(ISBLANK(E147),"","OFVP") -> OFVP | B147: Violence Prevention | D147: 2774 | E147: National Youth Advocate Program, Inc. | G147: 45688 | H147: 299976 | I147: 2023 | J147: Chicago | K147: Cook | L147: Chatham | M147: =IF(ISNUMBER(MATCH(E147,_xlfn.VSTACK('VLookup Lists'!$E$2:$E$17,'VLookup Lists'!$H$2:$H$38,'VLookup Lists'!$J$2:$J$8),0)),1,0) -> 0 | N147: =IFERROR(IF(VLOOKUP($D147,'VLookup Lists'!$B$11:$C$29,2,FALSE)="FLIP",1,0),"") -> 0 | O147: =ISNUMBER(MATCH($E147,'VLookup Lists'!$E$2:$E$17,0)) -> FALSE
A148: =IF(ISBLANK(E148),"","OFVP") -> OFVP | B148: Violence Prevention | D148: 2774 | E148: National Youth Advocate Program, Inc. | G148: 45688 | H148: 293675 | I148: 2023 | J148: Chicago | K148: Cook | L148: Greater Grand Crossing | M148: =IF(ISNUMBER(MATCH(E148,_xlfn.VSTACK('VLookup Lists'!$E$2:$E$17,'VLookup Lists'!$H$2:$H$38,'VLookup Lists'!$J$2:$J$8),0)),1,0) -> 0 | N148: =IFERROR(IF(VLOOKUP($D148,'VLookup Lists'!$B$11:$C$29,2,FALSE)="FLIP",1,0),"") -> 0 | O148: =ISNUMBER(MATCH($E148,'VLookup Lists'!$E$2:$E$17,0)) -> FALSE
A149: =IF(ISBLANK(E149),"","OFVP") -> OFVP | B149: Violence Prevention | D149: 2774 | E149: New Life Centers | G149: 45688 | H149: 300000 | I149: 2023 | J149: Chicago | K149: Cook | L149: South Lawndale | M149: =IF(ISNUMBER(MATCH(E149,_xlfn.VSTACK('VLookup Lists'!$E$2:$E$17,'VLookup Lists'!$H$2:$H$38,'VLookup Lists'!$J$2:$J$8),0)),1,0) -> 1 | N149: =IFERROR(IF(VLOOKUP($D149,'VLookup Lists'!$B$11:$C$29,2,FALSE)="FLIP",1,0),"") -> 0 | O149: =ISNUMBER(MATCH($E149,'VLookup Lists'!$E$2:$E$17,0)) -> TRUE
... A163: =IF(ISBLANK(E163),"","OFVP") -> OFVP | B163: Violence Prevention | D163: 2774 | E163: The Restorative Project, Inc. | G163: 45688 | H163: 300000 | I163: 2023 | J163: Chicago | K163: Cook | L163: Chicago Lawn | M163: =IF(ISNUMBER(MATCH(E163,_xlfn.VSTACK('VLookup Lists'!$E$2:$E$17,'VLookup Lists'!$H$2:$H$38,'VLookup Lists'!$J$2:$J$8),0)),1,0) -> 1 | N163: =IFERROR(IF(VLOOKUP($D163,'VLookup Lists'!$B$11:$C$29,2,FALSE)="FLIP",1,0),"") -> 0 | O163: =ISNUMBER(MATCH($E163,'VLookup Lists'!$E$2:$E$17,0)) -> FALSE
A164: =IF(ISBLANK(E164),"","OFVP") -> OFVP | B164: Violence Prevention | D164: 2774 | E164: The Restorative Project, Inc. | H164: 300000 | I164: 2023 | J164: Chicago | K164: Cook | L164: Englewood | M164: =IF(ISNUMBER(MATCH(E164,_xlfn.VSTACK('VLookup Lists'!$E$2:$E$17,'VLookup Lists'!$H$2:$H$38,'VLookup Lists'!$J$2:$J$8),0)),1,0) -> 1 | N164: =IFERROR(IF(VLOOKUP($D164,'VLookup Lists'!$B$11:$C$29,2,FALSE)="FLIP",1,0),"") -> 0 | O164: =ISNUMBER(MATCH($E164,'VLookup Lists'!$E$2:$E$17,0)) -> FALSE
A165: =IF(ISBLANK(E165),"","OFVP") -> OFVP | B165: Violence Prevention | D165: 2774 | E165: The Restorative Project, Inc. | G165: 45688 | H165: 300000 | I165: 2023 | J165: Chicago | K165: Cook | L165: West Englewood | M165: =IF(ISNUMBER(MATCH(E165,_xlfn.VSTACK('VLookup Lists'!$E$2:$E$17,'VLookup Lists'!$H$2:$H$38,'VLookup Lists'!$J$2:$J$8),0)),1,0) -> 1 | N165: =IFERROR(IF(VLOOKUP($D165,'VLookup Lists'!$B$11:$C$29,2,FALSE)="FLIP",1,0),"") -> 0 | O165: =ISNUMBER(MATCH($E165,'VLookup Lists'!$E$2:$E$17,0)) -> FALSE
A166: =IF(ISBLANK(E166),"","OFVP") -> OFVP | B166: Violence Prevention | D166: 2774 | E166: Together Chicago, Inc. | G166: 45688 | H166: 376625.63 | I166: 2023 | J166: Chicago | K166: Cook | L166: Austin | M166: =IF(ISNUMBER(MATCH(E166,_xlfn.VSTACK('VLookup Lists'!$E$2:$E$17,'VLookup Lists'!$H$2:$H$38,'VLookup Lists'!$J$2:$J$8),0)),1,0) -> 1 | N166: =IFERROR(IF(VLOOKUP($D166,'VLookup Lists'!$B$11:$C$29,2,FALSE)="FLIP",1,0),"") -> 0 | O166: =ISNUMBER(MATCH($E166,'VLookup Lists'!$E$2:$E$17,0)) -> TRUE
A167: =IF(ISBLANK(E167),"","OFVP") -> OFVP | B167: Violence Prevention | D167: 2774 | E167: Together Chicago, Inc. | G167: 45688 | H167: 414942.48 | I167: 2023 | J167: Chicago | K167: Cook | L167: East Garfield Park | M167: =IF(ISNUMBER(MATCH(E167,_xlfn.VSTACK('VLookup Lists'!$E$2:$E$17,'VLookup Lists'!$H$2:$H$38,'VLookup Lists'!$J$2:$J$8),0)),1,0) -> 1 | N167: =IFERROR(IF(VLOOKUP($D167,'VLookup Lists'!$B$11:$C$29,2,FALSE)="FLIP",1,0),"") -> 0 | O167: =ISNUMBER(MATCH($E167,'VLookup Lists'!$E$2:$E$17,0)) -> TRUE
A168: =IF(ISBLANK(E168),"","OFVP") -> OFVP | B168: Violence Prevention | D168: 2774 | E168: UCAN | G168: 45688 | H168: 743389 | I168: 2023 | J168: Chicago | K168: Cook | L168: North Lawndale | M168: =IF(ISNUMBER(MATCH(E168,_xlfn.VSTACK('VLookup Lists'!$E$2:$E$17,'VLookup Lists'!$H$2:$H$38,'VLookup Lists'!$J$2:$J$8),0)),1,0) -> 1 | N168: =IFERROR(IF(VLOOKUP($D168,'VLookup Lists'!$B$11:$C$29,2,FALSE)="FLIP",1,0),"") -> 0 | O168: =ISNUMBER(MATCH($E168,'VLookup Lists'!$E$2:$E$17,0)) -> TRUE
A169: =IF(ISBLANK(E169),"","OFVP") -> OFVP | B169: Violence Prevention | D169: 2774 | E169: United Faith Christian Institute | G169: 45838 | H169: 108055 | I169: 2023 | J169: Chicago | K169: Cook | L169: Austin | M169: =IF(ISNUMBER(MATCH(E169,_xlfn.VSTACK('VLookup Lists'!$E$2:$E$17,'VLookup Lists'!$H$2:$H$38,'VLookup Lists'!$J$2:$J$8),0)),1,0) -> 0 | N169: =IFERROR(IF(VLOOKUP($D169,'VLookup Lists'!$B$11:$C$29,2,FALSE)="FLIP",1,0),"") -> 0 | O169: =ISNUMBER(MATCH($E169,'VLookup Lists'!$E$2:$E$17,0)) -> FALSE
A170: =IF(ISBLANK(E170),"","OFVP") -> OFVP | B170: Violence Prevention | D170: 2774 | E170: The University of Chicago Medical Center | G170: 45688 | H170: 275561 | I170: 2023 | J170: Chicago | K170: Cook | L170: South Chicago | M170: =IF(ISNUMBER(MATCH(E170,_xlfn.VSTACK('VLookup Lists'!$E$2:$E$17,'VLookup Lists'!$H$2:$H$38,'VLookup Lists'!$J$2:$J$8),0)),1,0) -> 0 | N170: =IFERROR(IF(VLOOKUP($D170,'VLookup Lists'!$B$11:$C$29,2,FALSE)="FLIP",1,0),"") -> 0 | O170: =ISNUMBER(MATCH($E170,'VLookup Lists'!$E$2:$E$17,0)) -> FALSE
A171: =IF(ISBLANK(E171),"","OFVP") -> OFVP | B171: Violence Prevention | D171: 2774 | E171: The University of Chicago Medical Center | G171: 45838 | H171: 275561 | I171: 2023 | J171: Chicago | K171: Cook | L171: South Shore | M171: =IF(ISNUMBER(MATCH(E171,_xlfn.VSTACK('VLookup Lists'!$E$2:$E$17,'VLookup Lists'!$H$2:$H$38,'VLookup Lists'!$J$2:$J$8),0)),1,0) -> 0 | N171: =IFERROR(IF(VLOOKUP($D171,'VLookup Lists'!$B$11:$C$29,2,FALSE)="FLIP",1,0),"") -> 0 | O171: =ISNUMBER(MATCH($E171,'VLookup Lists'!$E$2:$E$17,0)) -> FALSE
A172: =IF(ISBLANK(E172),"","OFVP") -> OFVP | B172: Violence Prevention | D172: 2774 | E172: The University of Chicago Medical Center | G172: 45688 | H172: 275561 | I172: 2023 | J172: Chicago | K172: Cook | L172: Woodlawn | M172: =IF(ISNUMBER(MATCH(E172,_xlfn.VSTACK('VLookup Lists'!$E$2:$E$17,'VLookup Lists'!$H$2:$H$38,'VLookup Lists'!$J$2:$J$8),0)),1,0) -> 0 | N172: =IFERROR(IF(VLOOKUP($D172,'VLookup Lists'!$B$11:$C$29,2,FALSE)="FLIP",1,0),"") -> 0 | O172: =ISNUMBER(MATCH($E172,'VLookup Lists'!$E$2:$E$17,0)) -> FALSE
A173: =IF(ISBLANK(E173),"","OFVP") -> OFVP | B173: Violence Prevention | D173: 2774 | E173: Work Foundation | G173: 45688 | H173: 75000 | I173: 2023 | J173: Chicago | K173: Cook | L173: West Englewood | M173: =IF(ISNUMBER(MATCH(E173,_xlfn.VSTACK('VLookup Lists'!$E$2:$E$17,'VLookup Lists'!$H$2:$H$38,'VLookup Lists'!$J$2:$J$8),0)),1,0) -> 0 | N173: =IFERROR(IF(VLOOKUP($D173,'VLookup Lists'!$B$11:$C$29,2,FALSE)="FLIP",1,0),"") -> 0 | O173: =ISNUMBER(MATCH($E173,'VLookup Lists'!$E$2:$E$17,0)) -> FALSE
A174: =IF(ISBLANK(E174),"","OFVP") -> OFVP | B174: Violence Prevention | D174: 2774 | E174: YMCA OF METROPOLITAN CHICAGO | G174: 45688 | H174: 299442 | I174: 2023 | J174: Chicago | K174: Cook | L174: Humboldt Park | M174: =IF(ISNUMBER(MATCH(E174,_xlfn.VSTACK('VLookup Lists'!$E$2:$E$17,'VLookup Lists'!$H$2:$H$38,'VLookup Lists'!$J$2:$J$8),0)),1,0) -> 1 | N174: =IFERROR(IF(VLOOKUP($D174,'VLookup Lists'!$B$11:$C$29,2,FALSE)="FLIP",1,0),"") -> 0 | O174: =ISNUMBER(MATCH($E174,'VLookup Lists'!$E$2:$E$17,0)) -> FALSE
A175: =IF(ISBLANK(E175),"","OFVP") -> OFVP | B175: Violence Prevention | D175: 2774 | E175: YMCA OF METROPOLITAN CHICAGO | G175: 45688 | H175: 294590 | I175: 2023 | J175: Chicago | K175: Cook | L175: South Lawndale | M175: =IF(ISNUMBER(MATCH(E175,_xlfn.VSTACK('VLookup Lists'!$E$2:$E$17,'VLookup Lists'!$H$2:$H$38,'VLookup Lists'!$J$2:$J$8),0)),1,0) -> 1 | N175: =IFERROR(IF(VLOOKUP($D175,'VLookup Lists'!$B$11:$C$29,2,FALSE)="FLIP",1,0),"") -> 0 | O175: =ISNUMBER(MATCH($E175,'VLookup Lists'!$E$2:$E$17,0)) -> FALSE
A176: =IF(ISBLANK(E176),"","OFVP") -> OFVP | B176: Violence Prevention | D176: 2774 | E176: YMCA OF METROPOLITAN CHICAGO | G176: 45688 | H176: 294590 | I176: 2023 | J176: Chicago | K176: Cook | L176: Woodlawn | M176: =IF(ISNUMBER(MATCH(E176,_xlfn.VSTACK('VLookup Lists'!$E$2:$E$17,'VLookup Lists'!$H$2:$H$38,'VLookup Lists'!$J$2:$J$8),0)),1,0) -> 1 | N176: =IFERROR(IF(VLOOKUP($D176,'VLookup Lists'!$B$11:$C$29,2,FALSE)="FLIP",1,0),"") -> 0 | O176: =ISNUMBER(MATCH($E176,'VLookup Lists'!$E$2:$E$17,0)) -> FALSE
... A220: =IF(ISBLANK(E220),"","OFVP") -> OFVP | B220: Youth Development | D220: 2775 | E220: YWCA Metropolitan Chicago | G220: 45473 | H220: 99738 | I220: 2023 | J220: Chicago | K220: Cook | L220: Englewood | M220: =IF(ISNUMBER(MATCH(E220,_xlfn.VSTACK('VLookup Lists'!$E$2:$E$17,'VLookup Lists'!$H$2:$H$38,'VLookup Lists'!$J$2:$J$8),0)),1,0) -> 0 | N220: =IFERROR(IF(VLOOKUP($D220,'VLookup Lists'!$B$11:$C$29,2,FALSE)="FLIP",1,0),"") -> 0 | O220: =ISNUMBER(MATCH($E220,'VLookup Lists'!$E$2:$E$17,0)) -> FALSE
A221: =IF(ISBLANK(E221),"","OFVP") -> OFVP | B221: High Risk Youth Intervention Services | D221: 2776 | E221: Brightpoint (formerly Children's Home and Aid Society of Illinois) | H221: 449216 | I221: 2023 | J221: Chicago | K221: Cook | L221: z HRYIS | M221: =IF(ISNUMBER(MATCH(E221,_xlfn.VSTACK('VLookup Lists'!$E$2:$E$17,'VLookup Lists'!$H$2:$H$38,'VLookup Lists'!$J$2:$J$8),0)),1,0) -> 0 | N221: =IFERROR(IF(VLOOKUP($D221,'VLookup Lists'!$B$11:$C$29,2,FALSE)="FLIP",1,0),"") -> 0 | O221: =ISNUMBER(MATCH($E221,'VLookup Lists'!$E$2:$E$17,0)) -> FALSE
A222: =IF(ISBLANK(E222),"","OFVP") -> OFVP | B222: High Risk Youth Intervention Services | D222: 2776 | E222: Community Counseling Center (C4) | H222: 562788 | I222: 2023 | J222: Chicago | K222: Cook | L222: z HRYIS | M222: =IF(ISNUMBER(MATCH(E222,_xlfn.VSTACK('VLookup Lists'!$E$2:$E$17,'VLookup Lists'!$H$2:$H$38,'VLookup Lists'!$J$2:$J$8),0)),1,0) -> 0 | N222: =IFERROR(IF(VLOOKUP($D222,'VLookup Lists'!$B$11:$C$29,2,FALSE)="FLIP",1,0),"") -> 0 | O222: =ISNUMBER(MATCH($E222,'VLookup Lists'!$E$2:$E$17,0)) -> FALSE
A223: =IF(ISBLANK(E223),"","OFVP") -> OFVP | B223: High Risk Youth Intervention Services | D223: 2776 | E223: Metropolitan Family Services | H223: 512251 | I223: 2023 | J223: Chicago | K223: Cook | L223: z HRYIS | M223: =IF(ISNUMBER(MATCH(E223,_xlfn.VSTACK('VLookup Lists'!$E$2:$E$17,'VLookup Lists'!$H$2:$H$38,'VLookup Lists'!$J$2:$J$8),0)),1,0) -> 1 | N223: =IFERROR(IF(VLOOKUP($D223,'VLookup Lists'!$B$11:$C$29,2,FALSE)="FLIP",1,0),"") -> 0 | O223: =ISNUMBER(MATCH($E223,'VLookup Lists'!$E$2:$E$17,0)) -> TRUE
A224: =IF(ISBLANK(E224),"","OFVP") -> OFVP | B224: High Risk Youth Intervention Services | D224: 2776 | E224: MOUNT SINAI HOSP MEDICAL | G224: 45838 | H224: 537795 | I224: 2023 | J224: Chicago | K224: Cook | L224: z HRYIS | M224: =IF(ISNUMBER(MATCH(E224,_xlfn.VSTACK('VLookup Lists'!$E$2:$E$17,'VLookup Lists'!$H$2:$H$38,'VLookup Lists'!$J$2:$J$8),0)),1,0) -> 0 | N224: =IFERROR(IF(VLOOKUP($D224,'VLookup Lists'!$B$11:$C$29,2,FALSE)="FLIP",1,0),"") -> 0 | O224: =ISNUMBER(MATCH($E224,'VLookup Lists'!$E$2:$E$17,0)) -> FALSE
A225: =IF(ISBLANK(E225),"","OFVP") -> OFVP | B225: Greater Illinois Reimagine Youth Intervention Services | D225: 3005 | E225: AURORA AREA AFRICAN AMERICAN MEN OF UNITY | G225: 45565 | H225: 120000 | I225: 2023 | J225: Greater Illinois | K225: Dupage, Kane, Kendall, Will | L225: Aurora | M225: =IF(ISNUMBER(MATCH(E225,_xlfn.VSTACK('VLookup Lists'!$E$2:$E$17,'VLookup Lists'!$H$2:$H$38,'VLookup Lists'!$J$2:$J$8),0)),1,0) -> 0 | N225: =IFERROR(IF(VLOOKUP($D225,'VLookup Lists'!$B$11:$C$29,2,FALSE)="FLIP",1,0),"") -> 0 | O225: =ISNUMBER(MATCH($E225,'VLookup Lists'!$E$2:$E$17,0)) -> FALSE
A226: =IF(ISBLANK(E226),"","OFVP") -> OFVP | B226: Greater Illinois Reimagine Youth Intervention Services | D226: 3005 | E226: Boys & Girls Club of Lake County | G226: 45565 | H226: 120000 | I226: 2023 | J226: Greater Illinois | K226: Lake | L226: Waukegan-North Chicago Cluster | M226: =IF(ISNUMBER(MATCH(E226,_xlfn.VSTACK('VLookup Lists'!$E$2:$E$17,'VLookup Lists'!$H$2:$H$38,'VLookup Lists'!$J$2:$J$8),0)),1,0) -> 0 | N226: =IFERROR(IF(VLOOKUP($D226,'VLookup Lists'!$B$11:$C$29,2,FALSE)="FLIP",1,0),"") -> 0 | O226: =ISNUMBER(MATCH($E226,'VLookup Lists'!$E$2:$E$17,0)) -> FALSE
A227: =IF(ISBLANK(E227),"","OFVP") -> OFVP | B227: Greater Illinois Reimagine Youth Intervention Services | D227: 3005 | E227: Christian Friendliness Association, Inc. dba Youth Hope | G227: 45565 | H227: 163633 | I227: 2023 | J227: Greater Illinois | K227: Rock Island | L227: Rock Island | M227: =IF(ISNUMBER(MATCH(E227,_xlfn.VSTACK('VLookup Lists'!$E$2:$E$17,'VLookup Lists'!$H$2:$H$38,'VLookup Lists'!$J$2:$J$8),0)),1,0) -> 0 | N227: =IFERROR(IF(VLOOKUP($D227,'VLookup Lists'!$B$11:$C$29,2,FALSE)="FLIP",1,0),"") -> 0 | O227: =ISNUMBER(MATCH($E227,'VLookup Lists'!$E$2:$E$17,0)) -> FALSE
A228: =IF(ISBLANK(E228),"","OFVP") -> OFVP | B228: Greater Illinois Reimagine Youth Intervention Services | D228: 3005 | E228: Comprehensive Community Solutions, Inc. | G228: 45565 | H228: 210992 | I228: 2023 | J228: Greater Illinois | K228: Winnebago | L228: Rockford | M228: =IF(ISNUMBER(MATCH(E228,_xlfn.VSTACK('VLookup Lists'!$E$2:$E$17,'VLookup Lists'!$H$2:$H$38,'VLookup Lists'!$J$2:$J$8),0)),1,0) -> 0 | N228: =IFERROR(IF(VLOOKUP($D228,'VLookup Lists'!$B$11:$C$29,2,FALSE)="FLIP",1,0),"") -> 0 | O228: =ISNUMBER(MATCH($E228,'VLookup Lists'!$E$2:$E$17,0)) -> FALSE
A229: =IF(ISBLANK(E229),"","OFVP") -> OFVP | B229: Greater Illinois Reimagine Youth Intervention Services | D229: 3005 | E229: National Youth Advocate Program, Inc. | G229: 45565 | H229: 171357 | I229: 2023 | J229: Greater Illinois | K229: Dupage, Kane, Kendall, Will | L229: Aurora | M229: =IF(ISNUMBER(MATCH(E229,_xlfn.VSTACK('VLookup Lists'!$E$2:$E$17,'VLookup Lists'!$H$2:$H$38,'VLookup Lists'!$J$2:$J$8),0)),1,0) -> 0 | N229: =IFERROR(IF(VLOOKUP($D229,'VLookup Lists'!$B$11:$C$29,2,FALSE)="FLIP",1,0),"") -> 0 | O229: =ISNUMBER(MATCH($E229,'VLookup Lists'!$E$2:$E$17,0)) -> FALSE
A230: =IF(ISBLANK(E230),"","OFVP") -> OFVP | B230: Greater Illinois Reimagine Youth Intervention Services | D230: 3005 | E230: National Youth Advocate Program, Inc. | G230: 45565 | H230: 171357 | I230: 2023 | J230: Greater Illinois | K230: Macon | L230: Chicago Heights Cluster | M230: =IF(ISNUMBER(MATCH(E230,_xlfn.VSTACK('VLookup Lists'!$E$2:$E$17,'VLookup Lists'!$H$2:$H$38,'VLookup Lists'!$J$2:$J$8),0)),1,0) -> 0 | N230: =IFERROR(IF(VLOOKUP($D230,'VLookup Lists'!$B$11:$C$29,2,FALSE)="FLIP",1,0),"") -> 0 | O230: =ISNUMBER(MATCH($E230,'VLookup Lists'!$E$2:$E$17,0)) -> FALSE
A231: =IF(ISBLANK(E231),"","OFVP") -> OFVP | B231: Greater Illinois Reimagine Youth Intervention Services | D231: 3005 | E231: National Youth Advocate Program, Inc. | G231: 45565 | H231: 171357 | I231: 2023 | J231: Greater Illinois | K231: Cook | L231: Decatur | M231: =IF(ISNUMBER(MATCH(E231,_xlfn.VSTACK('VLookup Lists'!$E$2:$E$17,'VLookup Lists'!$H$2:$H$38,'VLookup Lists'!$J$2:$J$8),0)),1,0) -> 0 | N231: =IFERROR(IF(VLOOKUP($D231,'VLookup Lists'!$B$11:$C$29,2,FALSE)="FLIP",1,0),"") -> 0 | O231: =ISNUMBER(MATCH($E231,'VLookup Lists'!$E$2:$E$17,0)) -> FALSE
A232: =IF(ISBLANK(E232),"","OFVP") -> OFVP | B232: Greater Illinois Reimagine Youth Intervention Services | D232: 3005 | E232: National Youth Advocate Program, Inc. | G232: 45565 | H232: 171357 | I232: 2023 | J232: Greater Illinois | K232: Winnebago | L232: Rockford | M232: =IF(ISNUMBER(MATCH(E232,_xlfn.VSTACK('VLookup Lists'!$E$2:$E$17,'VLookup Lists'!$H$2:$H$38,'VLookup Lists'!$J$2:$J$8),0)),1,0) -> 0 | N232: =IFERROR(IF(VLOOKUP($D232,'VLookup Lists'!$B$11:$C$29,2,FALSE)="FLIP",1,0),"") -> 0 | O232: =ISNUMBER(MATCH($E232,'VLookup Lists'!$E$2:$E$17,0)) -> FALSE
A233: =IF(ISBLANK(E233),"","OFVP") -> OFVP | B233: Greater Illinois Reimagine Youth Intervention Services | D233: 3005 | E233: National Youth Advocate Program, Inc. | G233: 45565 | H233: 171357 | I233: 2023 | J233: Greater Illinois | K233: Dupage, Kane, Kendall, Will | L233: Urbana-Champaign Cluster | M233: =IF(ISNUMBER(MATCH(E233,_xlfn.VSTACK('VLookup Lists'!$E$2:$E$17,'VLookup Lists'!$H$2:$H$38,'VLookup Lists'!$J$2:$J$8),0)),1,0) -> 0 | N233: =IFERROR(IF(VLOOKUP($D233,'VLookup Lists'!$B$11:$C$29,2,FALSE)="FLIP",1,0),"") -> 0 | O233: =ISNUMBER(MATCH($E233,'VLookup Lists'!$E$2:$E$17,0)) -> FALSE
A234: =IF(ISBLANK(E234),"","OFVP") -> OFVP | B234: Greater Illinois Reimagine Youth Intervention Services | D234: 3005 | E234: Project Success of Vermillion County, Inc. | G234: 45565 | H234: 195537 | I234: 2023 | J234: Greater Illinois | K234: Vermillion | L234: Danville | M234: =IF(ISNUMBER(MATCH(E234,_xlfn.VSTACK('VLookup Lists'!$E$2:$E$17,'VLookup Lists'!$H$2:$H$38,'VLookup Lists'!$J$2:$J$8),0)),1,0) -> 0 | N234: =IFERROR(IF(VLOOKUP($D234,'VLookup Lists'!$B$11:$C$29,2,FALSE)="FLIP",1,0),"") -> 0 | O234: =ISNUMBER(MATCH($E234,'VLookup Lists'!$E$2:$E$17,0)) -> FALSE
A235: =IF(ISBLANK(E235),"","OFVP") -> OFVP | B235: Greater Illinois Reimagine Youth Intervention Services | D235: 3005 | E235: Proviso-Leyden Council for Community Action, Inc. | G235: 45565 | H235: 134191 | I235: 2023 | J235: Greater Illinois | K235: Cook | L235: Maywood-Bellwood Cluster | M235: =IF(ISNUMBER(MATCH(E235,_xlfn.VSTACK('VLookup Lists'!$E$2:$E$17,'VLookup Lists'!$H$2:$H$38,'VLookup Lists'!$J$2:$J$8),0)),1,0) -> 0 | N235: =IFERROR(IF(VLOOKUP($D235,'VLookup Lists'!$B$11:$C$29,2,FALSE)="FLIP",1,0),"") -> 0 | O235: =ISNUMBER(MATCH($E235,'VLookup Lists'!$E$2:$E$17,0)) -> FALSE
... A262: =IF(ISBLANK(E262),"","OFVP") -> OFVP | B262: Chicago Youth Development and Intervention Services (CYDIS) | D262: 3007 | E262: YourPassion1st | G262: 45565 | H262: 110526 | I262: 2023 | J262: Chicago | K262: Cook | L262: Austin | M262: =IF(ISNUMBER(MATCH(E262,_xlfn.VSTACK('VLookup Lists'!$E$2:$E$17,'VLookup Lists'!$H$2:$H$38,'VLookup Lists'!$J$2:$J$8),0)),1,0) -> 0 | N262: =IFERROR(IF(VLOOKUP($D262,'VLookup Lists'!$B$11:$C$29,2,FALSE)="FLIP",1,0),"") -> 0 | O262: =ISNUMBER(MATCH($E262,'VLookup Lists'!$E$2:$E$17,0)) -> FALSE
...

Sheet IJCIA Pivot
B2: Source | C2: (All)
B4: Sum of Award Amount | C4: Column Labels
B5: Row Labels | C5: 2019 | D5: 2020 | E5: 2021 | F5: 2022 | G5: 2023 | H5: 2024 | I5: 2025 | J5: 2026 | K5: (blank) | L5: Grand Total
B7: 100 ways foundation | H7: 200000 | L7: 200000
B8: 1863FWD LLC | E8: 629347 | F8: 629347 | G8: 629347 | H8: 629347 | L8: 2517388
B9: A & L YOUTH AND FAMILY SERVICES | I9: 455590 | J9: 1366770 | L9: 1822360
B10: A Gift of Love Charity, Inc. | I10: 118047 | J10: 118047 | L10: 236094
B11: A Just Harvest | G11: 1731000 | H11: 1731000 | I11: 1731000 | L11: 5193000
B12: A Knock At Midnight, NFP | G12: 1950000 | H12: 1950000 | I12: 1950000 | J12: 175000 | L12: 6025000
B13: A Safe Haven Foundation | D13: 500000 | E13: 500000 | F13: 750000 | G13: 2728171 | H13: 1978171 | I13: 1978171 | L13: 8434513
B14: Academic Development Institute, Inc. | E14: 2788584 | F14: 2788584 | G14: 2788584 | H14: 2788584 | I14: 249960 | J14: 949877 | L14: 12354173
B15: Acclivus, Inc. | E15: 6546400 | F15: 7378370 | G15: 7087000 | H15: 7500000 | I15: 4759600 | J15: 7500000 | L15: 40771370
B16: Adler University | F16: 70399 | G16: 70399 | H16: 191000 | I16: 753700 | J16: 562700 | L16: 1648198
B17: ADV & SAS | G17: 92831 | H17: 92831 | I17: 92831 | L17: 278493
B18: Advocacy Network for Children | D18: 175975 | E18: 175975 | H18: 90584 | I18: 181168 | J18: 181168 | L18: 804870
B19: Advocate Condell Medical Center | F19: 781793 | G19: 1563586 | H19: 1531793 | I19: 1500000 | J19: 1500000 | L19: 6877172
B20: Advocate Health and Hospitals Corporation | F20: 1200000 | G20: 2400000 | H20: 2700000 | I20: 2250000 | J20: 1500000 | L20: 10050000
B21: Alliance Against Intoxicated Motorists | E21: 375750 | F21: 939375 | G21: 563625 | H21: 563625 | L21: 2442375
B22: Alliance of Local Service Organizations (ALSO) | E22: 324965 | F22: 812453 | G22: 664788 | H22: 1184488 | I22: 1197000 | J22: 697000 | L22: 4880694
B23: ALPHA AND OMEGA FOUNDATION | G23: 255000 | H23: 255000 | I23: 483700 | J23: 686100 | L23: 1679800
B24: Alternatives, Inc. | D24: 317210 | E24: 1859201 | F24: 1708272 | G24: 1541991 | H24: 1541991 | I24: 399074 | L24: 7367739
B25: AMO Athletics Foundation | J25: 200000 | L25: 200000
B26: Angel of God Resource Center, Inc. | I26: 925500 | J26: 625500 | L26: 1551000
B27: Angels Boxing Academy, Limited | G27: 270000 | H27: 300000 | I27: 300000 | J27: 300000 | L27: 1170000
B28: Ann & Robert H. Lurie Children's Hospital of Chicago | C28: 805814 | D28: 805814 | E28: 805814 | F28: 937385 | L28: 3354827
B29: Annie B. Jones Civic Arts Center. | H29: 253022 | L29: 253022
B30: Apna Ghar, Inc. | H30: 97858 | L30: 97858
B31: Area Consortium of Educational Services (ACES) 4 Our Youth | F31: 225436 | L31: 225436
B32: Arrowleaf (formerly Family Counseling Center, Inc.) | E32: 932524 | F32: 932524 | G32: 932524 | H32: 932524 | I32: 121624 | L32: 3851720
B33: Artists ReEnvisioning Tomorrow Inc. | G33: 1800000 | H33: 1800000 | I33: 1800000 | L33: 5400000
B34: Ascend Justice | E34: 478400 | F34: 837200 | G34: 837200 | H34: 478400 | I34: 500000 | J34: 478400 | L34: 3609600
B35: Ascending Knowledge Community Outreach International | I35: 477172 | J35: 477172 | L35: 954344
B36: Association for Individual Development | G36: 1472460 | H36: 1472460 | I36: 1472460 | L36: 4417380
B37: Aurora Area Interfaith Food Pantry | G37: 750000 | H37: 750000 | I37: 750000 | L37: 2250000
B38: BandWith Chicago | F38: 60465 | I38: 145116 | J38: 149604 | L38: 355185
B39: BEDS Plus Care, Inc. | D39: 327156 | E39: 327156 | F39: 446160 | G39: 446160 | L39: 1546632
B40: Bella Ease | G40: 600000 | H40: 829844 | I40: 600000 | J40: 200000 | L40: 2229844
B41: Bethel Family Resource Center | F41: 164860 | L41: 164860
B42: Between Friends | F42: 109399 | I42: 262558 | J42: 200000 | L42: 571957
B43: Beyond the Ball NFP | G43: 147000 | H43: 147000 | I43: 147000 | L43: 441000
B44: BIG BROTHERS-BIG SISTERS OF METROPOLITAN CHICAGO | D44: 291588 | E44: 291368 | L44: 582956
B45: Black Educational Advocacy Coalition | H45: 278264 | J45: 200000 | L45: 478264
B46: Black Expo Community Development Association Inc. | I46: 480311 | J46: 1440933 | L46: 1921244
B47: Black Oaks Foundation dba Black Oaks Center | E47: 54237 | F47: 54237 | G47: 54237 | H47: 54237 | L47: 216948
B48: Board of Education of the City of Peoria | E48: 2576007 | F48: 2576007 | G48: 2576007 | H48: 2576007 | L48: 10304028
B49: Board of Trustees of Community College District No. 508, d/b/a City Colleges of Chicago. | H49: 500000 | I49: 500000 | L49: 1000000
B50: Board of Trustees of the University of Illinois (University of Illinois at Chicago) | E50: 378933 | F50: 852599 | G50: 473666 | L50: 1705198
B51: Board of Trustees of the University of Illinois (University of Illinois at Urbana-Champaign) | E51: 1283345 | F51: 1283345 | G51: 1433345 | H51: 1433345 | I51: 150000 | L51: 5583380
B52: Board of Trustees of Western Illinois University | G52: 550827 | H52: 550827 | I52: 550827 | L52: 1652481
B53: Bond County Crisis Nursery | I53: 200000 | J53: 200000 | L53: 400000
B54: Books Over Balls | H54: 279864 | L54: 279864
B55: Boone County CASA | E55: 75189 | F55: 150378 | G55: 150378 | H55: 151495 | I55: 152612 | J55: 76306 | L55: 756358
B56: Boxing Out Negativity, Inc. | F56: 393442 | G56: 270000 | H56: 270000 | I56: 1600149 | J56: 1121745 | L56: 3655336
B57: Boys & Girls Club of Lake County | I57: 418150 | J57: 1254450 | L57: 1672600
B58: Braveheart Children's Advocacy Center | G58: 331344 | H58: 331344 | I58: 331344 | L58: 994032
B59: Breakthrough Urban Ministries | G59: 177300 | H59: 197000 | I59: 593660 | J59: 465083 | L59: 1433043
B60: Bridge to Freedom | G60: 615000 | H60: 615000 | I60: 615000 | J60: 862532 | L60: 2707532
B61: Bright Star Community Outreach | D61: 690921 | E61: 671649 | L61: 1362570
B62: BUILD Inc. | C62: 464751 | D62: 729912 | E62: 1233473 | F62: 1643712 | G62: 3038017 | H62: 2715712 | I62: 2979004 | J62: 543595 | L62: 13348176
B63: C.L.I.C.K. Services NFP | G63: 1493863 | H63: 1493863 | I63: 1493863 | L63: 4481589
B64: Cabrini Green Legal AId | D64: 173418 | E64: 172781 | L64: 346199
B65: Cairo School District #1 | G65: 289419 | H65: 289419 | I65: 289419 | L65: 868257
B66: Carbondale United | G66: 578838 | H66: 578838 | I66: 578838 | L66: 1736514
B67: CASA DeKalb County, Inc. | D67: 148426 | E67: 266620 | F67: 236388 | G67: 236388 | H67: 252473 | I67: 268558 | J67: 134279 | L67: 1543132
B68: CASA Kane County | D68: 747905 | E68: 747905 | H68: 134825 | I68: 269650 | J68: 269650 | L68: 2169935
B69: CASA Lake County | D69: 224732 | E69: 682922 | F69: 916380 | G69: 916380 | H69: 593190 | I69: 135000 | L69: 3468604
B70: CASA of East Central Illinois | D70: 133174 | E70: 133174 | L70: 266348
B71: CASA of Effingham County | D71: 75000 | E71: 75000 | L71: 150000
B72: CASA of Franklin County | D72: 68600 | E72: 68600 | L72: 137200
B73: CASA of McHenry County | D73: 67663 | E73: 106097 | F73: 212194 | G73: 212194 | H73: 106097 | L73: 704245
B74: CASA of River Valley | E74: 144707 | F74: 289414 | G74: 289414 | H74: 279491 | I74: 269568 | J74: 134784 | L74: 1407378
B75: CASA of Southwestern Illinois | D75: 318145 | E75: 683719 | F75: 731148 | G75: 731148 | H75: 500574 | I75: 270000 | J75: 135000 | L75: 3369734
B76: CASA of the Tenth Judicial Circuit | D76: 600000 | E76: 600000 | L76: 1200000
B77: CASA of Vermilion County | D77: 254671 | E77: 254671 | L77: 509342
B78: CASA of Williamson County | D78: 81280 | E78: 81280 | L78: 162560
B79: Catholic Bishop of Chicago - St. Sabina | H79: 137360 | L79: 137360
B80: Catholic Charities of the Archdiocese of Chicago | D80: 799317 | E80: 2276579 | F80: 3873204 | G80: 2394977 | H80: 1217340 | L80: 10561417
B81: Center for Community Academic Success Partnerships | E81: 730000 | F81: 730000 | G81: 730000 | H81: 730000 | L81: 2920000
B82: Center for Conflict Resolution | F82: 130042 | G82: 130042 | H82: 113693 | L82: 373777
B83: Center on Halsted | C83: 225000 | D83: 450000 | E83: 450000 | F83: 337500 | G83: 337500 | L83: 1800000
B84: Centers for New Horizons, Inc. | E84: 6132209 | F84: 6132209 | G84: 6269709 | H84: 6269709 | L84: 24803836
B85: Centro Corporativo Empresarial | H85: 250000 | J85: 250000 | L85: 500000
B86: Centro Romero | G86: 486803 | H86: 486803 | I86: 486803 | L86: 1460409
B87: Centro San Bonifacio | G87: 1256010 | H87: 1256010 | I87: 1256010 | L87: 3768030
B88: Centro Sanar | H88: 265650 | I88: 531300 | J88: 265650 | L88: 1062600
B89: CGG Law Partners LLC | G89: 1013267 | H89: 1013267 | I89: 1013267 | L89: 3039801
B90: Champaign County Christian Health Center | G90: 450000 | H90: 450000 | I90: 450000 | L90: 1350000
B91: Champaign County Court Appointed Special Advocates | D91: 193870 | E91: 421917 | F91: 456094 | G91: 456094 | H91: 228047 | L91: 1756022
B92: CHAMPS MALE MENTORING PROGRAM-CHIRISE | F92: 101459 | H92: 200000 | I92: 443502 | J92: 200000 | L92: 944961
B93: Chicago Alliance Against Sexual Exploitation | E93: 266055 | F93: 942254 | G93: 942254 | H93: 904767 | I93: 585354 | J93: 312869 | L93: 3953553
B94: Chicago Arts Partnerships in Education | I94: 379652 | J94: 1138956 | L94: 1518608
B95: Chicago Children's Advocacy Center | E95: 421060 | F95: 1052650 | G95: 631590 | H95: 1177040 | I95: 1090900 | J95: 545450 | L95: 4918690
B96: Chicago Community Arts Studio | I96: 70443 | J96: 211329 | L96: 281772
B97: Chicago Survivors | C97: 1499991 | D97: 1499991 | E97: 1499991 | F97: 195000 | G97: 195000 | L97: 4889973
B98: Chicago Torture Justice Center | E98: 693507 | F98: 693507 | G98: 693507 | H98: 693507 | L98: 2774028
B99: Chicago Urban League | E99: 8966848 | F99: 8966848 | G99: 8966848 | H99: 8966848 | L99: 35867392
B100: Chicago Westside Branch NAACP | E100: 6802965 | F100: 6802965 | G100: 6802965 | H100: 6802965 | I100: 6802965 | L100: 34014825
B101: CHICAGO WORKERS' COLLABORATIVE NFP | G101: 2681610 | H101: 2681610 | I101: 2681610 | L101: 8044830
B102: Chicago Youth Boxing Club Inc. | E102: 164400 | F102: 252093 | G102: 164400 | H102: 164400 | I102: 210000 | J102: 200000 | L102: 1155293
B103: Chicago Youth Programs | F103: 88450 | I103: 212280 | J103: 200000 | L103: 500730
...

Sheet ICJIA
A1: Source | B1: Grant Type | C1: Award ID | D1: CSFA | E1: Grantee Name | F1: Start Date | G1: End Date | H1: Award Amount | I1: Fiscal Year | J1: Chicago/Greater Illinois | K1: County | L1: Community Area | M1: CVI | N1: FLIP | O1: CP4P | P1: SC2o | Q1: SC2c
A2: =IF(ISBLANK(B2),"","ICJIA") -> ICJIA | B2: Community-based Violence Intervention & Prevention (Fed) | C2: 662314 JES | D2: 3380 | E2: Angel of God Resource Center, Inc. | F2: 45566 | G2: 45930 | H2: 300000 | I2: 2025 | M2: =IF(ISNUMBER(MATCH(E2,_xlfn.VSTACK('VLookup Lists'!$E$2:$E$17,'VLookup Lists'!$H$2:$H$38,'VLookup Lists'!$J$2:$J$8),0)),1,0) -> 0 | N2: =IFERROR(IF(VLOOKUP($D2,'VLookup Lists'!$B$11:$C$29,2,FALSE)="FLIP",1,0),"") | O2: =ISNUMBER(MATCH($E2,'VLookup Lists'!$E$2:$E$17,0)) -> FALSE
A3: =IF(ISBLANK(B3),"","ICJIA") -> ICJIA | B3: Community-based Violence Intervention & Prevention (Fed) | C3: 662315 JES | D3: 3380 | E3: Breakthrough Urban Ministries | F3: 45566 | G3: 45930 | H3: 128577 | I3: 2025 | M3: =IF(ISNUMBER(MATCH(E3,_xlfn.VSTACK('VLookup Lists'!$E$2:$E$17,'VLookup Lists'!$H$2:$H$38,'VLookup Lists'!$J$2:$J$8),0)),1,0) -> 1 | N3: =IFERROR(IF(VLOOKUP($D3,'VLookup Lists'!$B$11:$C$29,2,FALSE)="FLIP",1,0),"") | O3: =ISNUMBER(MATCH($E3,'VLookup Lists'!$E$2:$E$17,0)) -> TRUE
A4: =IF(ISBLANK(B4),"","ICJIA") -> ICJIA | B4: Community-based Violence Intervention & Prevention (Fed) | C4: 662313 JES | D4: 3380 | E4: BUILD Inc. | F4: 45566 | G4: 45930 | H4: 260640 | I4: 2025 | M4: =IF(ISNUMBER(MATCH(E4,_xlfn.VSTACK('VLookup Lists'!$E$2:$E$17,'VLookup Lists'!$H$2:$H$38,'VLookup Lists'!$J$2:$J$8),0)),1,0) -> 1 | N4: =IFERROR(IF(VLOOKUP($D4,'VLookup Lists'!$B$11:$C$29,2,FALSE)="FLIP",1,0),"") | O4: =ISNUMBER(MATCH($E4,'VLookup Lists'!$E$2:$E$17,0)) -> FALSE
A5: =IF(ISBLANK(B5),"","ICJIA") -> ICJIA | B5: Community-based Violence Intervention & Prevention (Fed) | C5: 662310 JES | D5: 3380 | E5: Lawndale Christian Legal Center | F5: 45474 | G5: 45838 | H5: 100000 | I5: 2025 | M5: =IF(ISNUMBER(MATCH(E5,_xlfn.VSTACK('VLookup Lists'!$E$2:$E$17,'VLookup Lists'!$H$2:$H$38,'VLookup Lists'!$J$2:$J$8),0)),1,0) -> 0 | N5: =IFERROR(IF(VLOOKUP($D5,'VLookup Lists'!$B$11:$C$29,2,FALSE)="FLIP",1,0),"") | O5: =ISNUMBER(MATCH($E5,'VLookup Lists'!$E$2:$E$17,0)) -> FALSE
A6: =IF(ISBLANK(B6),"","ICJIA") -> ICJIA | B6: Community-based Violence Intervention & Prevention (Fed) | C6: 662311 JES | D6: 3380 | E6: New Eclipse Community Alliance | F6: 45566 | G6: 45930 | H6: 614014 | I6: 2025 | M6: =IF(ISNUMBER(MATCH(E6,_xlfn.VSTACK('VLookup Lists'!$E$2:$E$17,'VLookup Lists'!$H$2:$H$38,'VLookup Lists'!$J$2:$J$8),0)),1,0) -> 0 | N6: =IFERROR(IF(VLOOKUP($D6,'VLookup Lists'!$B$11:$C$29,2,FALSE)="FLIP",1,0),"") | O6: =ISNUMBER(MATCH($E6,'VLookup Lists'!$E$2:$E$17,0)) -> FALSE
A7: =IF(ISBLANK(B7),"","ICJIA") -> ICJIA | B7: Community-based Violence Intervention & Prevention (Fed) | C7: 662312 JS | D7: 3380 | E7: Roseland Ceasefire Project Inc. | F7: 45474 | G7: 45838 | H7: 177455 | I7: 2025 | M7: =IF(ISNUMBER(MATCH(E7,_xlfn.VSTACK('VLookup Lists'!$E$2:$E$17,'VLookup Lists'!$H$2:$H$38,'VLookup Lists'!$J$2:$J$8),0)),1,0) -> 1 | N7: =IFERROR(IF(VLOOKUP($D7,'VLookup Lists'!$B$11:$C$29,2,FALSE)="FLIP",1,0),"") | O7: =ISNUMBER(MATCH($E7,'VLookup Lists'!$E$2:$E$17,0)) -> FALSE
A8: =IF(ISBLANK(B8),"","ICJIA") -> ICJIA | B8: Community-based Violence Intervention & Prevention (Fed) | C8: 662316 JES | D8: 3380 | E8: Southwest Organizing Project (SWOP) | F8: 45566 | G8: 45930 | H8: 214461 | I8: 2025 | M8: =IF(ISNUMBER(MATCH(E8,_xlfn.VSTACK('VLookup Lists'!$E$2:$E$17,'VLookup Lists'!$H$2:$H$38,'VLookup Lists'!$J$2:$J$8),0)),1,0) -> 1 | N8: =IFERROR(IF(VLOOKUP($D8,'VLookup Lists'!$B$11:$C$29,2,FALSE)="FLIP",1,0),"") | O8: =ISNUMBER(MATCH($E8,'VLookup Lists'!$E$2:$E$17,0)) -> TRUE
A9: =IF(ISBLANK(B9),"","ICJIA") -> ICJIA | B9: Community-Based Violence Intervention and Prevention (CB-VIP) | C9: 172000 SW | D9: 2117 | E9: Alternatives, Inc. | F9: 43647 | G9: 44012 | H9: 317210 | I9: 2020 | M9: =IF(ISNUMBER(MATCH(E9,_xlfn.VSTACK('VLookup Lists'!$E$2:$E$17,'VLookup Lists'!$H$2:$H$38,'VLookup Lists'!$J$2:$J$8),0)),1,0) -> 0 | N9: =IFERROR(IF(VLOOKUP($D9,'VLookup Lists'!$B$11:$C$29,2,FALSE)="FLIP",1,0),"") | O9: =ISNUMBER(MATCH($E9,'VLookup Lists'!$E$2:$E$17,0)) -> FALSE
A10: =IF(ISBLANK(B10),"","ICJIA") -> ICJIA | B10: Community-Based Violence Intervention and Prevention (CB-VIP) | C10: 172001 | D10: 2117 | E10: BIG BROTHERS-BIG SISTERS OF METROPOLITAN CHICAGO | F10: 43647 | G10: 44012 | H10: 291588 | I10: 2020 | M10: =IF(ISNUMBER(MATCH(E10,_xlfn.VSTACK('VLookup Lists'!$E$2:$E$17,'VLookup Lists'!$H$2:$H$38,'VLookup Lists'!$J$2:$J$8),0)),1,0) -> 0 | N10: =IFERROR(IF(VLOOKUP($D10,'VLookup Lists'!$B$11:$C$29,2,FALSE)="FLIP",1,0),"") | O10: =ISNUMBER(MATCH($E10,'VLookup Lists'!$E$2:$E$17,0)) -> FALSE
A11: =IF(ISBLANK(B11),"","ICJIA") -> ICJIA | B11: Community-Based Violence Intervention and Prevention (CB-VIP) | C11: 172002 STB | D11: 2117 | E11: Bright Star Community Outreach | F11: 43647 | G11: 44012 | H11: 690921 | I11: 2020 | M11: =IF(ISNUMBER(MATCH(E11,_xlfn.VSTACK('VLookup Lists'!$E$2:$E$17,'VLookup Lists'!$H$2:$H$38,'VLookup Lists'!$J$2:$J$8),0)),1,0) -> 0 | N11: =IFERROR(IF(VLOOKUP($D11,'VLookup Lists'!$B$11:$C$29,2,FALSE)="FLIP",1,0),"") | O11: =ISNUMBER(MATCH($E11,'VLookup Lists'!$E$2:$E$17,0)) -> FALSE
A12: =IF(ISBLANK(B12),"","ICJIA") -> ICJIA | B12: Community-Based Violence Intervention and Prevention (CB-VIP) | C12: 172003 STB | D12: 2117 | E12: Cabrini Green Legal AId | F12: 43647 | G12: 44012 | H12: 173418 | I12: 2020 | M12: =IF(ISNUMBER(MATCH(E12,_xlfn.VSTACK('VLookup Lists'!$E$2:$E$17,'VLookup Lists'!$H$2:$H$38,'VLookup Lists'!$J$2:$J$8),0)),1,0) -> 0 | N12: =IFERROR(IF(VLOOKUP($D12,'VLookup Lists'!$B$11:$C$29,2,FALSE)="FLIP",1,0),"") | O12: =ISNUMBER(MATCH($E12,'VLookup Lists'!$E$2:$E$17,0)) -> FALSE
A13: =IF(ISBLANK(B13),"","ICJIA") -> ICJIA | B13: Community-Based Violence Intervention and Prevention (CB-VIP) | C13: 172004 | D13: 2117 | E13: Catholic Charities of the Archdiocese of Chicago | F13: 43647 | G13: 44012 | H13: 569782 | I13: 2020 | M13: =IF(ISNUMBER(MATCH(E13,_xlfn.VSTACK('VLookup Lists'!$E$2:$E$17,'VLookup Lists'!$H$2:$H$38,'VLookup Lists'!$J$2:$J$8),0)),1,0) -> 0 | N13: =IFERROR(IF(VLOOKUP($D13,'VLookup Lists'!$B$11:$C$29,2,FALSE)="FLIP",1,0),"") | O13: =ISNUMBER(MATCH($E13,'VLookup Lists'!$E$2:$E$17,0)) -> FALSE
A14: =IF(ISBLANK(B14),"","ICJIA") -> ICJIA | B14: Community-Based Violence Intervention and Prevention (CB-VIP) | C14: 172005 | D14: 2117 | E14: Children's Home & Aid Society of Illinois dba Brightpoint | F14: 43647 | G14: 44012 | H14: 102173 | I14: 2020 | M14: =IF(ISNUMBER(MATCH(E14,_xlfn.VSTACK('VLookup Lists'!$E$2:$E$17,'VLookup Lists'!$H$2:$H$38,'VLookup Lists'!$J$2:$J$8),0)),1,0) -> 0 | N14: =IFERROR(IF(VLOOKUP($D14,'VLookup Lists'!$B$11:$C$29,2,FALSE)="FLIP",1,0),"") | O14: =ISNUMBER(MATCH($E14,'VLookup Lists'!$E$2:$E$17,0)) -> FALSE
A15: =IF(ISBLANK(B15),"","ICJIA") -> ICJIA | B15: Community-Based Violence Intervention and Prevention (CB-VIP) | C15: 172006 STB | D15: 2117 | E15: Gary Comer Youth Center, Inc. | F15: 43647 | G15: 44012 | H15: 807505 | I15: 2020 | M15: =IF(ISNUMBER(MATCH(E15,_xlfn.VSTACK('VLookup Lists'!$E$2:$E$17,'VLookup Lists'!$H$2:$H$38,'VLookup Lists'!$J$2:$J$8),0)),1,0) -> 0 | N15: =IFERROR(IF(VLOOKUP($D15,'VLookup Lists'!$B$11:$C$29,2,FALSE)="FLIP",1,0),"") | O15: =ISNUMBER(MATCH($E15,'VLookup Lists'!$E$2:$E$17,0)) -> FALSE
A16: =IF(ISBLANK(B16),"","ICJIA") -> ICJIA | B16: Community-Based Violence Intervention and Prevention (CB-VIP) | C16: 172007 STB | D16: 2117 | E16: Heartland Alliance | F16: 43647 | G16: 44012 | H16: 659942 | I16: 2020 | M16: =IF(ISNUMBER(MATCH(E16,_xlfn.VSTACK('VLookup Lists'!$E$2:$E$17,'VLookup Lists'!$H$2:$H$38,'VLookup Lists'!$J$2:$J$8),0)),1,0) -> 0 | N16: =IFERROR(IF(VLOOKUP($D16,'VLookup Lists'!$B$11:$C$29,2,FALSE)="FLIP",1,0),"") | O16: =ISNUMBER(MATCH($E16,'VLookup Lists'!$E$2:$E$17,0)) -> FALSE
A17: =IF(ISBLANK(B17),"","ICJIA") -> ICJIA | B17: Community-Based Violence Intervention and Prevention (CB-VIP) | C17: 172008 SW | D17: 2117 | E17: Illinois Association of Juvenile Justice Councils | F17: 43647 | G17: 44012 | H17: 929606 | I17: 2020 | M17: =IF(ISNUMBER(MATCH(E17,_xlfn.VSTACK('VLookup Lists'!$E$2:$E$17,'VLookup Lists'!$H$2:$H$38,'VLookup Lists'!$J$2:$J$8),0)),1,0) -> 0 | N17: =IFERROR(IF(VLOOKUP($D17,'VLookup Lists'!$B$11:$C$29,2,FALSE)="FLIP",1,0),"") | O17: =ISNUMBER(MATCH($E17,'VLookup Lists'!$E$2:$E$17,0)) -> FALSE
A18: =IF(ISBLANK(B18),"","ICJIA") -> ICJIA | B18: Community-Based Violence Intervention and Prevention (CB-VIP) | C18: 172014 SW | D18: 2117 | E18: Lawrence Hall Youth Services | F18: 43647 | G18: 44012 | H18: 192556 | I18: 2020 | M18: =IF(ISNUMBER(MATCH(E18,_xlfn.VSTACK('VLookup Lists'!$E$2:$E$17,'VLookup Lists'!$H$2:$H$38,'VLookup Lists'!$J$2:$J$8),0)),1,0) -> 0 | N18: =IFERROR(IF(VLOOKUP($D18,'VLookup Lists'!$B$11:$C$29,2,FALSE)="FLIP",1,0),"") | O18: =ISNUMBER(MATCH($E18,'VLookup Lists'!$E$2:$E$17,0)) -> FALSE
A19: =IF(ISBLANK(B19),"","ICJIA") -> ICJIA | B19: Community-Based Violence Intervention and Prevention (CB-VIP) | C19: 172010 SW | D19: 2117 | E19: Northeast DuPage Family and Youth Services | F19: 43647 | G19: 44012 | H19: 132352 | I19: 2020 | M19: =IF(ISNUMBER(MATCH(E19,_xlfn.VSTACK('VLookup Lists'!$E$2:$E$17,'VLookup Lists'!$H$2:$H$38,'VLookup Lists'!$J$2:$J$8),0)),1,0) -> 0 | N19: =IFERROR(IF(VLOOKUP($D19,'VLookup Lists'!$B$11:$C$29,2,FALSE)="FLIP",1,0),"") | O19: =ISNUMBER(MATCH($E19,'VLookup Lists'!$E$2:$E$17,0)) -> FALSE
A20: =IF(ISBLANK(B20),"","ICJIA") -> ICJIA | B20: Community-Based Violence Intervention and Prevention (CB-VIP) | C20: 172011 SW | D20: 2117 | E20: Pilsen Wellness Center, Inc. | F20: 43647 | G20: 44012 | H20: 251072 | I20: 2020 | M20: =IF(ISNUMBER(MATCH(E20,_xlfn.VSTACK('VLookup Lists'!$E$2:$E$17,'VLookup Lists'!$H$2:$H$38,'VLookup Lists'!$J$2:$J$8),0)),1,0) -> 0 | N20: =IFERROR(IF(VLOOKUP($D20,'VLookup Lists'!$B$11:$C$29,2,FALSE)="FLIP",1,0),"") | O20: =ISNUMBER(MATCH($E20,'VLookup Lists'!$E$2:$E$17,0)) -> FALSE
A21: =IF(ISBLANK(B21),"","ICJIA") -> ICJIA | B21: Community-Based Violence Intervention and Prevention (CB-VIP) | C21: 172012 SW | D21: 2117 | E21: Region 1 Planning Council | F21: 43647 | G21: 44012 | H21: 195923 | I21: 2020 | M21: =IF(ISNUMBER(MATCH(E21,_xlfn.VSTACK('VLookup Lists'!$E$2:$E$17,'VLookup Lists'!$H$2:$H$38,'VLookup Lists'!$J$2:$J$8),0)),1,0) -> 0 | N21: =IFERROR(IF(VLOOKUP($D21,'VLookup Lists'!$B$11:$C$29,2,FALSE)="FLIP",1,0),"") | O21: =ISNUMBER(MATCH($E21,'VLookup Lists'!$E$2:$E$17,0)) -> FALSE
A22: =IF(ISBLANK(B22),"","ICJIA") -> ICJIA | B22: Community-Based Violence Intervention and Prevention (CB-VIP) | C22: 172015 SW | D22: 2117 | E22: South Shore Drill Team & Performing Arts Ensemble | F22: 43647 | G22: 44012 | H22: 83195 | I22: 2020 | M22: =IF(ISNUMBER(MATCH(E22,_xlfn.VSTACK('VLookup Lists'!$E$2:$E$17,'VLookup Lists'!$H$2:$H$38,'VLookup Lists'!$J$2:$J$8),0)),1,0) -> 0 | N22: =IFERROR(IF(VLOOKUP($D22,'VLookup Lists'!$B$11:$C$29,2,FALSE)="FLIP",1,0),"") | O22: =ISNUMBER(MATCH($E22,'VLookup Lists'!$E$2:$E$17,0)) -> FALSE
A23: =IF(ISBLANK(B23),"","ICJIA") -> ICJIA | B23: Community-Based Violence Intervention and Prevention (CB-VIP) | C23: 172004 | D23: 2117 | E23: Springfield Urban League, Inc. | F23: 43647 | G23: 44012 | H23: 313943 | I23: 2020 | M23: =IF(ISNUMBER(MATCH(E23,_xlfn.VSTACK('VLookup Lists'!$E$2:$E$17,'VLookup Lists'!$H$2:$H$38,'VLookup Lists'!$J$2:$J$8),0)),1,0) -> 0 | N23: =IFERROR(IF(VLOOKUP($D23,'VLookup Lists'!$B$11:$C$29,2,FALSE)="FLIP",1,0),"") | O23: =ISNUMBER(MATCH($E23,'VLookup Lists'!$E$2:$E$17,0)) -> FALSE
A24: =IF(ISBLANK(B24),"","ICJIA") -> ICJIA | B24: Community-Based Violence Intervention and Prevention (CB-VIP) | C24: 172017 SW | D24: 2117 | E24: UNIVERSAL FAMILY CONNECTION, INC. | F24: 43647 | G24: 44012 | H24: 682382 | I24: 2020 | M24: =IF(ISNUMBER(MATCH(E24,_xlfn.VSTACK('VLookup Lists'!$E$2:$E$17,'VLookup Lists'!$H$2:$H$38,'VLookup Lists'!$J$2:$J$8),0)),1,0) -> 0 | N24: =IFERROR(IF(VLOOKUP($D24,'VLookup Lists'!$B$11:$C$29,2,FALSE)="FLIP",1,0),"") | O24: =ISNUMBER(MATCH($E24,'VLookup Lists'!$E$2:$E$17,0)) -> FALSE
A25: =IF(ISBLANK(B25),"","ICJIA") -> ICJIA | B25: Community-Based Violence Intervention and Prevention (CB-VIP) | D25: 2117 | E25: Alternatives, Inc. | F25: 44013 | G25: 44377 | H25: 317210 | I25: 2021 | M25: =IF(ISNUMBER(MATCH(E25,_xlfn.VSTACK('VLookup Lists'!$E$2:$E$17,'VLookup Lists'!$H$2:$H$38,'VLookup Lists'!$J$2:$J$8),0)),1,0) -> 0 | N25: =IFERROR(IF(VLOOKUP($D25,'VLookup Lists'!$B$11:$C$29,2,FALSE)="FLIP",1,0),"") | O25: =ISNUMBER(MATCH($E25,'VLookup Lists'!$E$2:$E$17,0)) -> FALSE
A26: =IF(ISBLANK(B26),"","ICJIA") -> ICJIA | B26: Community-Based Violence Intervention and Prevention (CB-VIP) | C26: 172101 LM | D26: 2117 | E26: BIG BROTHERS-BIG SISTERS OF METROPOLITAN CHICAGO | F26: 44013 | G26: 44377 | H26: 291368 | I26: 2021 | M26: =IF(ISNUMBER(MATCH(E26,_xlfn.VSTACK('VLookup Lists'!$E$2:$E$17,'VLookup Lists'!$H$2:$H$38,'VLookup Lists'!$J$2:$J$8),0)),1,0) -> 0 | N26: =IFERROR(IF(VLOOKUP($D26,'VLookup Lists'!$B$11:$C$29,2,FALSE)="FLIP",1,0),"") | O26: =ISNUMBER(MATCH($E26,'VLookup Lists'!$E$2:$E$17,0)) -> FALSE
A27: =IF(ISBLANK(B27),"","ICJIA") -> ICJIA | B27: Community-Based Violence Intervention and Prevention (CB-VIP) | D27: 2117 | E27: Bright Star Community Outreach | F27: 44013 | G27: 44377 | H27: 671649 | I27: 2021 | M27: =IF(ISNUMBER(MATCH(E27,_xlfn.VSTACK('VLookup Lists'!$E$2:$E$17,'VLookup Lists'!$H$2:$H$38,'VLookup Lists'!$J$2:$J$8),0)),1,0) -> 0 | N27: =IFERROR(IF(VLOOKUP($D27,'VLookup Lists'!$B$11:$C$29,2,FALSE)="FLIP",1,0),"") | O27: =ISNUMBER(MATCH($E27,'VLookup Lists'!$E$2:$E$17,0)) -> FALSE
A28: =IF(ISBLANK(B28),"","ICJIA") -> ICJIA | B28: Community-Based Violence Intervention and Prevention (CB-VIP) | D28: 2117 | E28: Cabrini Green Legal Aid | F28: 44013 | G28: 44377 | H28: 172781 | I28: 2021 | M28: =IF(ISNUMBER(MATCH(E28,_xlfn.VSTACK('VLookup Lists'!$E$2:$E$17,'VLookup Lists'!$H$2:$H$38,'VLookup Lists'!$J$2:$J$8),0)),1,0) -> 0 | N28: =IFERROR(IF(VLOOKUP($D28,'VLookup Lists'!$B$11:$C$29,2,FALSE)="FLIP",1,0),"") | O28: =ISNUMBER(MATCH($E28,'VLookup Lists'!$E$2:$E$17,0)) -> FALSE
A29: =IF(ISBLANK(B29),"","ICJIA") -> ICJIA | B29: Community-Based Violence Intervention and Prevention (CB-VIP) | D29: 2117 | E29: Catholic Charities of the Archdiocese of Chicago | F29: 44013 | G29: 44377 | H29: 568817 | I29: 2021 | M29: =IF(ISNUMBER(MATCH(E29,_xlfn.VSTACK('VLookup Lists'!$E$2:$E$17,'VLookup Lists'!$H$2:$H$38,'VLookup Lists'!$J$2:$J$8),0)),1,0) -> 0 | N29: =IFERROR(IF(VLOOKUP($D29,'VLookup Lists'!$B$11:$C$29,2,FALSE)="FLIP",1,0),"") | O29: =ISNUMBER(MATCH($E29,'VLookup Lists'!$E$2:$E$17,0)) -> FALSE
A30: =IF(ISBLANK(B30),"","ICJIA") -> ICJIA | B30: Community-Based Violence Intervention and Prevention (CB-VIP) | C30: 172105 LM | D30: 2117 | E30: Children's Home & Aid Society of Illinois dba Brightpoint | F30: 44013 | G30: 44377 | H30: 102173 | I30: 2021 | M30: =IF(ISNUMBER(MATCH(E30,_xlfn.VSTACK('VLookup Lists'!$E$2:$E$17,'VLookup Lists'!$H$2:$H$38,'VLookup Lists'!$J$2:$J$8),0)),1,0) -> 0 | N30: =IFERROR(IF(VLOOKUP($D30,'VLookup Lists'!$B$11:$C$29,2,FALSE)="FLIP",1,0),"") | O30: =ISNUMBER(MATCH($E30,'VLookup Lists'!$E$2:$E$17,0)) -> FALSE
A31: =IF(ISBLANK(B31),"","ICJIA") -> ICJIA | B31: Community-Based Violence Intervention and Prevention (CB-VIP) | D31: 2117 | E31: Gary Comer Youth Center, Inc. | F31: 44013 | G31: 44377 | H31: 807505 | I31: 2021 | M31: =IF(ISNUMBER(MATCH(E31,_xlfn.VSTACK('VLookup Lists'!$E$2:$E$17,'VLookup Lists'!$H$2:$H$38,'VLookup Lists'!$J$2:$J$8),0)),1,0) -> 0 | N31: =IFERROR(IF(VLOOKUP($D31,'VLookup Lists'!$B$11:$C$29,2,FALSE)="FLIP",1,0),"") | O31: =ISNUMBER(MATCH($E31,'VLookup Lists'!$E$2:$E$17,0)) -> FALSE
A32: =IF(ISBLANK(B32),"","ICJIA") -> ICJIA | B32: Community-Based Violence Intervention and Prevention (CB-VIP) | D32: 2117 | E32: Heartland Alliance | F32: 44013 | G32: 44377 | H32: 659942 | I32: 2021 | M32: =IF(ISNUMBER(MATCH(E32,_xlfn.VSTACK('VLookup Lists'!$E$2:$E$17,'VLookup Lists'!$H$2:$H$38,'VLookup Lists'!$J$2:$J$8),0)),1,0) -> 0 | N32: =IFERROR(IF(VLOOKUP($D32,'VLookup Lists'!$B$11:$C$29,2,FALSE)="FLIP",1,0),"") | O32: =ISNUMBER(MATCH($E32,'VLookup Lists'!$E$2:$E$17,0)) -> FALSE
A33: =IF(ISBLANK(B33),"","ICJIA") -> ICJIA | B33: Community-Based Violence Intervention and Prevention (CB-VIP) | D33: 2117 | E33: Illinois Association of Juvenile Justice Councils | F33: 44013 | G33: 44377 | H33: 928239 | I33: 2021 | M33: =IF(ISNUMBER(MATCH(E33,_xlfn.VSTACK('VLookup Lists'!$E$2:$E$17,'VLookup Lists'!$H$2:$H$38,'VLookup Lists'!$J$2:$J$8),0)),1,0) -> 0 | N33: =IFERROR(IF(VLOOKUP($D33,'VLookup Lists'!$B$11:$C$29,2,FALSE)="FLIP",1,0),"") | O33: =ISNUMBER(MATCH($E33,'VLookup Lists'!$E$2:$E$17,0)) -> FALSE
A34: =IF(ISBLANK(B34),"","ICJIA") -> ICJIA | B34: Community-Based Violence Intervention and Prevention (CB-VIP) | D34: 2117 | E34: Lawrence Hall Youth Services | F34: 44013 | G34: 44377 | H34: 192556 | I34: 2021 | M34: =IF(ISNUMBER(MATCH(E34,_xlfn.VSTACK('VLookup Lists'!$E$2:$E$17,'VLookup Lists'!$H$2:$H$38,'VLookup Lists'!$J$2:$J$8),0)),1,0) -> 0 | N34: =IFERROR(IF(VLOOKUP($D34,'VLookup Lists'!$B$11:$C$29,2,FALSE)="FLIP",1,0),"") | O34: =ISNUMBER(MATCH($E34,'VLookup Lists'!$E$2:$E$17,0)) -> FALSE
A35: =IF(ISBLANK(B35),"","ICJIA") -> ICJIA | B35: Community-Based Violence Intervention and Prevention (CB-VIP) | D35: 2117 | E35: Northeast DuPage Family and Youth Services | F35: 44013 | G35: 44377 | H35: 132035 | I35: 2021 | M35: =IF(ISNUMBER(MATCH(E35,_xlfn.VSTACK('VLookup Lists'!$E$2:$E$17,'VLookup Lists'!$H$2:$H$38,'VLookup Lists'!$J$2:$J$8),0)),1,0) -> 0 | N35: =IFERROR(IF(VLOOKUP($D35,'VLookup Lists'!$B$11:$C$29,2,FALSE)="FLIP",1,0),"") | O35: =ISNUMBER(MATCH($E35,'VLookup Lists'!$E$2:$E$17,0)) -> FALSE
A36: =IF(ISBLANK(B36),"","ICJIA") -> ICJIA | B36: Community-Based Violence Intervention and Prevention (CB-VIP) | C36: 172111 LM | D36: 2117 | E36: Pilsen Wellness Center, Inc. | F36: 44013 | G36: 44377 | H36: 251061 | I36: 2021 | M36: =IF(ISNUMBER(MATCH(E36,_xlfn.VSTACK('VLookup Lists'!$E$2:$E$17,'VLookup Lists'!$H$2:$H$38,'VLookup Lists'!$J$2:$J$8),0)),1,0) -> 0 | N36: =IFERROR(IF(VLOOKUP($D36,'VLookup Lists'!$B$11:$C$29,2,FALSE)="FLIP",1,0),"") | O36: =ISNUMBER(MATCH($E36,'VLookup Lists'!$E$2:$E$17,0)) -> FALSE
A37: =IF(ISBLANK(B37),"","ICJIA") -> ICJIA | B37: Community-Based Violence Intervention and Prevention (CB-VIP) | C37: 172112 KE | D37: 2117 | E37: Region 1 Planning Council | F37: 44013 | G37: 44377 | H37: 195923 | I37: 2021 | M37: =IF(ISNUMBER(MATCH(E37,_xlfn.VSTACK('VLookup Lists'!$E$2:$E$17,'VLookup Lists'!$H$2:$H$38,'VLookup Lists'!$J$2:$J$8),0)),1,0) -> 0 | N37: =IFERROR(IF(VLOOKUP($D37,'VLookup Lists'!$B$11:$C$29,2,FALSE)="FLIP",1,0),"") | O37: =ISNUMBER(MATCH($E37,'VLookup Lists'!$E$2:$E$17,0)) -> FALSE
A38: =IF(ISBLANK(B38),"","ICJIA") -> ICJIA | B38: Community-Based Violence Intervention and Prevention (CB-VIP) | C38: 172115 SA | D38: 2117 | E38: South Shore Drill Team & Performing Arts Ensemble | F38: 44013 | G38: 44377 | H38: 83195 | I38: 2021 | M38: =IF(ISNUMBER(MATCH(E38,_xlfn.VSTACK('VLookup Lists'!$E$2:$E$17,'VLookup Lists'!$H$2:$H$38,'VLookup Lists'!$J$2:$J$8),0)),1,0) -> 0 | N38: =IFERROR(IF(VLOOKUP($D38,'VLookup Lists'!$B$11:$C$29,2,FALSE)="FLIP",1,0),"") | O38: =ISNUMBER(MATCH($E38,'VLookup Lists'!$E$2:$E$17,0)) -> FALSE
A39: =IF(ISBLANK(B39),"","ICJIA") -> ICJIA | B39: Community-Based Violence Intervention and Prevention (CB-VIP) | C39: 172113 AB | D39: 2117 | E39: Springfield Urban League, Inc. | F39: 44013 | G39: 44377 | H39: 313943 | I39: 2021 | M39: =IF(ISNUMBER(MATCH(E39,_xlfn.VSTACK('VLookup Lists'!$E$2:$E$17,'VLookup Lists'!$H$2:$H$38,'VLookup Lists'!$J$2:$J$8),0)),1,0) -> 0 | N39: =IFERROR(IF(VLOOKUP($D39,'VLookup Lists'!$B$11:$C$29,2,FALSE)="FLIP",1,0),"") | O39: =ISNUMBER(MATCH($E39,'VLookup Lists'!$E$2:$E$17,0)) -> FALSE
A40: =IF(ISBLANK(B40),"","ICJIA") -> ICJIA | B40: Community-Based Violence Intervention and Prevention (CB-VIP) | D40: 2117 | E40: UNIVERSAL FAMILY CONNECTION, INC. | F40: 44013 | G40: 44377 | H40: 682375 | I40: 2021 | M40: =IF(ISNUMBER(MATCH(E40,_xlfn.VSTACK('VLookup Lists'!$E$2:$E$17,'VLookup Lists'!$H$2:$H$38,'VLookup Lists'!$J$2:$J$8),0)),1,0) -> 0 | N40: =IFERROR(IF(VLOOKUP($D40,'VLookup Lists'!$B$11:$C$29,2,FALSE)="FLIP",1,0),"") | O40: =ISNUMBER(MATCH($E40,'VLookup Lists'!$E$2:$E$17,0)) -> FALSE
A41: =IF(ISBLANK(B41),"","ICJIA") -> ICJIA | B41: Community-Based Violence Intervention and Prevention (CB-VIP) | C41: 172200 LMurphy | D41: 2117 | E41: Alternatives, Inc. | F41: 44593 | G41: 44742 | H41: 166281 | I41: 2022 | M41: =IF(ISNUMBER(MATCH(E41,_xlfn.VSTACK('VLookup Lists'!$E$2:$E$17,'VLookup Lists'!$H$2:$H$38,'VLookup Lists'!$J$2:$J$8),0)),1,0) -> 0 | N41: =IFERROR(IF(VLOOKUP($D41,'VLookup Lists'!$B$11:$C$29,2,FALSE)="FLIP",1,0),"") | O41: =ISNUMBER(MATCH($E41,'VLookup Lists'!$E$2:$E$17,0)) -> FALSE
A42: =IF(ISBLANK(B42),"","ICJIA") -> ICJIA | B42: Community-Based Violence Intervention and Prevention (CB-VIP) | C42: 172201- LM | D42: 2117 | E42: Area Consortium of Educational Services (ACES) 4 Our Youth | F42: 44593 | G42: 44742 | H42: 225436 | I42: 2022 | M42: =IF(ISNUMBER(MATCH(E42,_xlfn.VSTACK('VLookup Lists'!$E$2:$E$17,'VLookup Lists'!$H$2:$H$38,'VLookup Lists'!$J$2:$J$8),0)),1,0) -> 0 | N42: =IFERROR(IF(VLOOKUP($D42,'VLookup Lists'!$B$11:$C$29,2,FALSE)="FLIP",1,0),"") | O42: =ISNUMBER(MATCH($E42,'VLookup Lists'!$E$2:$E$17,0)) -> FALSE
A43: =IF(ISBLANK(B43),"","ICJIA") -> ICJIA | B43: Community-Based Violence Intervention and Prevention (CB-VIP) | D43: 2117 | E43: BandWith Chicago | F43: 44593 | G43: 44742 | H43: 60465 | I43: 2022 | M43: =IF(ISNUMBER(MATCH(E43,_xlfn.VSTACK('VLookup Lists'!$E$2:$E$17,'VLookup Lists'!$H$2:$H$38,'VLookup Lists'!$J$2:$J$8),0)),1,0) -> 0 | N43: =IFERROR(IF(VLOOKUP($D43,'VLookup Lists'!$B$11:$C$29,2,FALSE)="FLIP",1,0),"") | O43: =ISNUMBER(MATCH($E43,'VLookup Lists'!$E$2:$E$17,0)) -> FALSE
A44: =IF(ISBLANK(B44),"","ICJIA") -> ICJIA | B44: Community-Based Violence Intervention and Prevention (CB-VIP) | C44: 172203 HA | D44: 2117 | E44: Between Friends | F44: 44593 | G44: 44742 | H44: 109399 | I44: 2022 | M44: =IF(ISNUMBER(MATCH(E44,_xlfn.VSTACK('VLookup Lists'!$E$2:$E$17,'VLookup Lists'!$H$2:$H$38,'VLookup Lists'!$J$2:$J$8),0)),1,0) -> 0 | N44: =IFERROR(IF(VLOOKUP($D44,'VLookup Lists'!$B$11:$C$29,2,FALSE)="FLIP",1,0),"") | O44: =ISNUMBER(MATCH($E44,'VLookup Lists'!$E$2:$E$17,0)) -> FALSE
A45: =IF(ISBLANK(B45),"","ICJIA") -> ICJIA | B45: Community-Based Violence Intervention and Prevention (CB-VIP) | D45: 2117 | E45: Boxing Out Negativity, Inc. | F45: 44593 | G45: 44742 | H45: 199335 | I45: 2022 | M45: =IF(ISNUMBER(MATCH(E45,_xlfn.VSTACK('VLookup Lists'!$E$2:$E$17,'VLookup Lists'!$H$2:$H$38,'VLookup Lists'!$J$2:$J$8),0)),1,0) -> 0 | N45: =IFERROR(IF(VLOOKUP($D45,'VLookup Lists'!$B$11:$C$29,2,FALSE)="FLIP",1,0),"") | O45: =ISNUMBER(MATCH($E45,'VLookup Lists'!$E$2:$E$17,0)) -> FALSE
A46: =IF(ISBLANK(B46),"","ICJIA") -> ICJIA | B46: Community-Based Violence Intervention and Prevention (CB-VIP) | C46: 822019 MSC | D46: 2117 | E46: Center for Conflict Resolution | F46: 44666 | G46: 45030 | H46: 130042 | I46: 2022 | M46: =IF(ISNUMBER(MATCH(E46,_xlfn.VSTACK('VLookup Lists'!$E$2:$E$17,'VLookup Lists'!$H$2:$H$38,'VLookup Lists'!$J$2:$J$8),0)),1,0) -> 0 | N46: =IFERROR(IF(VLOOKUP($D46,'VLookup Lists'!$B$11:$C$29,2,FALSE)="FLIP",1,0),"") | O46: =ISNUMBER(MATCH($E46,'VLookup Lists'!$E$2:$E$17,0)) -> FALSE
A47: =IF(ISBLANK(B47),"","ICJIA") -> ICJIA | B47: Community-Based Violence Intervention and Prevention (CB-VIP) | D47: 2117 | E47: CHAMPS MALE MENTORING PROGRAM-CHIRISE | F47: 44593 | G47: 44742 | H47: 101459 | I47: 2022 | M47: =IF(ISNUMBER(MATCH(E47,_xlfn.VSTACK('VLookup Lists'!$E$2:$E$17,'VLookup Lists'!$H$2:$H$38,'VLookup Lists'!$J$2:$J$8),0)),1,0) -> 0 | N47: =IFERROR(IF(VLOOKUP($D47,'VLookup Lists'!$B$11:$C$29,2,FALSE)="FLIP",1,0),"") | O47: =ISNUMBER(MATCH($E47,'VLookup Lists'!$E$2:$E$17,0)) -> FALSE
A48: =IF(ISBLANK(B48),"","ICJIA") -> ICJIA | B48: Community-Based Violence Intervention and Prevention (CB-VIP) | C48: 822020 MSC | D48: 2117 | E48: Chicago Alliance Against Sexual Exploitation | F48: 44666 | G48: 45030 | H48: 476658 | I48: 2022 | M48: =IF(ISNUMBER(MATCH(E48,_xlfn.VSTACK('VLookup Lists'!$E$2:$E$17,'VLookup Lists'!$H$2:$H$38,'VLookup Lists'!$J$2:$J$8),0)),1,0) -> 0 | N48: =IFERROR(IF(VLOOKUP($D48,'VLookup Lists'!$B$11:$C$29,2,FALSE)="FLIP",1,0),"") | O48: =ISNUMBER(MATCH($E48,'VLookup Lists'!$E$2:$E$17,0)) -> FALSE
A49: =IF(ISBLANK(B49),"","ICJIA") -> ICJIA | B49: Community-Based Violence Intervention and Prevention (CB-VIP) | C49: 172206 FSGU AB | D49: 2117 | E49: Chicago Youth Boxing Club Inc. | F49: 44593 | G49: 44742 | H49: 87693 | I49: 2022 | M49: =IF(ISNUMBER(MATCH(E49,_xlfn.VSTACK('VLookup Lists'!$E$2:$E$17,'VLookup Lists'!$H$2:$H$38,'VLookup Lists'!$J$2:$J$8),0)),1,0) -> 0 | N49: =IFERROR(IF(VLOOKUP($D49,'VLookup Lists'!$B$11:$C$29,2,FALSE)="FLIP",1,0),"") | O49: =ISNUMBER(MATCH($E49,'VLookup Lists'!$E$2:$E$17,0)) -> FALSE
A50: =IF(ISBLANK(B50),"","ICJIA") -> ICJIA | B50: Community-Based Violence Intervention and Prevention (CB-VIP) | D50: 2117 | E50: Chicago Youth Programs | F50: 44593 | G50: 44742 | H50: 88450 | I50: 2022 | M50: =IF(ISNUMBER(MATCH(E50,_xlfn.VSTACK('VLookup Lists'!$E$2:$E$17,'VLookup Lists'!$H$2:$H$38,'VLookup Lists'!$J$2:$J$8),0)),1,0) -> 0 | N50: =IFERROR(IF(VLOOKUP($D50,'VLookup Lists'!$B$11:$C$29,2,FALSE)="FLIP",1,0),"") | O50: =ISNUMBER(MATCH($E50,'VLookup Lists'!$E$2:$E$17,0)) -> FALSE
A51: =IF(ISBLANK(B51),"","ICJIA") -> ICJIA | B51: Community-Based Violence Intervention and Prevention (CB-VIP) | C51: 172208 FSGU SBB | D51: 2117 | E51: CircEsteem, Inc. | F51: 44593 | G51: 44742 | H51: 182144 | I51: 2022 | M51: =IF(ISNUMBER(MATCH(E51,_xlfn.VSTACK('VLookup Lists'!$E$2:$E$17,'VLookup Lists'!$H$2:$H$38,'VLookup Lists'!$J$2:$J$8),0)),1,0) -> 0 | N51: =IFERROR(IF(VLOOKUP($D51,'VLookup Lists'!$B$11:$C$29,2,FALSE)="FLIP",1,0),"") | O51: =ISNUMBER(MATCH($E51,'VLookup Lists'!$E$2:$E$17,0)) -> FALSE
A52: =IF(ISBLANK(B52),"","ICJIA") -> ICJIA | B52: Community-Based Violence Intervention and Prevention (CB-VIP) | C52: 822024 | D52: 2117 | E52: Cullar Consulting, LLC | F52: 44666 | G52: 45396 | H52: 811745 | I52: 2022 | M52: =IF(ISNUMBER(MATCH(E52,_xlfn.VSTACK('VLookup Lists'!$E$2:$E$17,'VLookup Lists'!$H$2:$H$38,'VLookup Lists'!$J$2:$J$8),0)),1,0) -> 0 | N52: =IFERROR(IF(VLOOKUP($D52,'VLookup Lists'!$B$11:$C$29,2,FALSE)="FLIP",1,0),"") | O52: =ISNUMBER(MATCH($E52,'VLookup Lists'!$E$2:$E$17,0)) -> FALSE
A53: =IF(ISBLANK(B53),"","ICJIA") -> ICJIA | B53: Community-Based Violence Intervention and Prevention (CB-VIP) | C53: 172209 CAC | D53: 2117 | E53: Duane Dean Behavioral Health Center | F53: 44593 | G53: 44742 | H53: 125000 | I53: 2022 | M53: =IF(ISNUMBER(MATCH(E53,_xlfn.VSTACK('VLookup Lists'!$E$2:$E$17,'VLookup Lists'!$H$2:$H$38,'VLookup Lists'!$J$2:$J$8),0)),1,0) -> 0 | N53: =IFERROR(IF(VLOOKUP($D53,'VLookup Lists'!$B$11:$C$29,2,FALSE)="FLIP",1,0),"") | O53: =ISNUMBER(MATCH($E53,'VLookup Lists'!$E$2:$E$17,0)) -> FALSE
A54: =IF(ISBLANK(B54),"","ICJIA") -> ICJIA | B54: Community-Based Violence Intervention and Prevention (CB-VIP) | C54: 172210 CAC | D54: 2117 | E54: Entrepreneurs Academy | F54: 44593 | G54: 44742 | H54: 193684 | I54: 2022 | M54: =IF(ISNUMBER(MATCH(E54,_xlfn.VSTACK('VLookup Lists'!$E$2:$E$17,'VLookup Lists'!$H$2:$H$38,'VLookup Lists'!$J$2:$J$8),0)),1,0) -> 0 | N54: =IFERROR(IF(VLOOKUP($D54,'VLookup Lists'!$B$11:$C$29,2,FALSE)="FLIP",1,0),"") | O54: =ISNUMBER(MATCH($E54,'VLookup Lists'!$E$2:$E$17,0)) -> FALSE
A55: =IF(ISBLANK(B55),"","ICJIA") -> ICJIA | B55: Community-Based Violence Intervention and Prevention (CB-VIP) | C55: 822027 Cortisa Evans | D55: 2117 | E55: Friends of the Children - Chicago | F55: 44666 | G55: 45030 | H55: 491918 | I55: 2022 | M55: =IF(ISNUMBER(MATCH(E55,_xlfn.VSTACK('VLookup Lists'!$E$2:$E$17,'VLookup Lists'!$H$2:$H$38,'VLookup Lists'!$J$2:$J$8),0)),1,0) -> 0 | N55: =IFERROR(IF(VLOOKUP($D55,'VLookup Lists'!$B$11:$C$29,2,FALSE)="FLIP",1,0),"") | O55: =ISNUMBER(MATCH($E55,'VLookup Lists'!$E$2:$E$17,0)) -> FALSE
A56: =IF(ISBLANK(B56),"","ICJIA") -> ICJIA | B56: Community-Based Violence Intervention and Prevention (CB-VIP) | C56: 822028 Cortisa Evans | D56: 2117 | E56: George Washington Carver Association | F56: 44666 | G56: 45030 | H56: 479664 | I56: 2022 | M56: =IF(ISNUMBER(MATCH(E56,_xlfn.VSTACK('VLookup Lists'!$E$2:$E$17,'VLookup Lists'!$H$2:$H$38,'VLookup Lists'!$J$2:$J$8),0)),1,0) -> 0 | N56: =IFERROR(IF(VLOOKUP($D56,'VLookup Lists'!$B$11:$C$29,2,FALSE)="FLIP",1,0),"") | O56: =ISNUMBER(MATCH($E56,'VLookup Lists'!$E$2:$E$17,0)) -> FALSE
A57: =IF(ISBLANK(B57),"","ICJIA") -> ICJIA | B57: Community-Based Violence Intervention and Prevention (CB-VIP) | C57: 172211 CAC | D57: 2117 | E57: Girls Inc. of Chicago | F57: 44593 | G57: 44742 | H57: 181200 | I57: 2022 | M57: =IF(ISNUMBER(MATCH(E57,_xlfn.VSTACK('VLookup Lists'!$E$2:$E$17,'VLookup Lists'!$H$2:$H$38,'VLookup Lists'!$J$2:$J$8),0)),1,0) -> 0 | N57: =IFERROR(IF(VLOOKUP($D57,'VLookup Lists'!$B$11:$C$29,2,FALSE)="FLIP",1,0),"") | O57: =ISNUMBER(MATCH($E57,'VLookup Lists'!$E$2:$E$17,0)) -> FALSE
A58: =IF(ISBLANK(B58),"","ICJIA") -> ICJIA | B58: Community-Based Violence Intervention and Prevention (CB-VIP) | C58: 172212 CAC | D58: 2117 | E58: Greater Chatham Initiative | F58: 44593 | G58: 45473 | H58: 156229 | I58: 2022 | M58: =IF(ISNUMBER(MATCH(E58,_xlfn.VSTACK('VLookup Lists'!$E$2:$E$17,'VLookup Lists'!$H$2:$H$38,'VLookup Lists'!$J$2:$J$8),0)),1,0) -> 0 | N58: =IFERROR(IF(VLOOKUP($D58,'VLookup Lists'!$B$11:$C$29,2,FALSE)="FLIP",1,0),"") | O58: =ISNUMBER(MATCH($E58,'VLookup Lists'!$E$2:$E$17,0)) -> FALSE
A59: =IF(ISBLANK(B59),"","ICJIA") -> ICJIA | B59: Community-Based Violence Intervention and Prevention (CB-VIP) | D59: 2117 | E59: GRO Community | F59: 44666 | G59: 45396 | H59: 379466 | I59: 2022 | M59: =IF(ISNUMBER(MATCH(E59,_xlfn.VSTACK('VLookup Lists'!$E$2:$E$17,'VLookup Lists'!$H$2:$H$38,'VLookup Lists'!$J$2:$J$8),0)),1,0) -> 0 | N59: =IFERROR(IF(VLOOKUP($D59,'VLookup Lists'!$B$11:$C$29,2,FALSE)="FLIP",1,0),"") | O59: =ISNUMBER(MATCH($E59,'VLookup Lists'!$E$2:$E$17,0)) -> FALSE
A60: =IF(ISBLANK(B60),"","ICJIA") -> ICJIA | B60: Community-Based Violence Intervention and Prevention (CB-VIP) | C60: 172213 SBB FSGU | D60: 2117 | E60: Hope Center Foundation | F60: 44593 | G60: 44742 | H60: 142678 | I60: 2022 | M60: =IF(ISNUMBER(MATCH(E60,_xlfn.VSTACK('VLookup Lists'!$E$2:$E$17,'VLookup Lists'!$H$2:$H$38,'VLookup Lists'!$J$2:$J$8),0)),1,0) -> 0 | N60: =IFERROR(IF(VLOOKUP($D60,'VLookup Lists'!$B$11:$C$29,2,FALSE)="FLIP",1,0),"") | O60: =ISNUMBER(MATCH($E60,'VLookup Lists'!$E$2:$E$17,0)) -> FALSE
A61: =IF(ISBLANK(B61),"","ICJIA") -> ICJIA | B61: Community-Based Violence Intervention and Prevention (CB-VIP) | C61: 172214 SBB | D61: 2117 | E61: Illinois Association of Juvenile Justice Councils | F61: 44593 | G61: 44742 | H61: 130220 | I61: 2022 | M61: =IF(ISNUMBER(MATCH(E61,_xlfn.VSTACK('VLookup Lists'!$E$2:$E$17,'VLookup Lists'!$H$2:$H$38,'VLookup Lists'!$J$2:$J$8),0)),1,0) -> 0 | N61: =IFERROR(IF(VLOOKUP($D61,'VLookup Lists'!$B$11:$C$29,2,FALSE)="FLIP",1,0),"") | O61: =ISNUMBER(MATCH($E61,'VLookup Lists'!$E$2:$E$17,0)) -> FALSE
A62: =IF(ISBLANK(B62),"","ICJIA") -> ICJIA | B62: Community-Based Violence Intervention and Prevention (CB-VIP) | C62: 172215 FSGU SBB | D62: 2117 | E62: Ladies of Virtue | F62: 44593 | G62: 44742 | H62: 100000 | I62: 2022 | M62: =IF(ISNUMBER(MATCH(E62,_xlfn.VSTACK('VLookup Lists'!$E$2:$E$17,'VLookup Lists'!$H$2:$H$38,'VLookup Lists'!$J$2:$J$8),0)),1,0) -> 0 | N62: =IFERROR(IF(VLOOKUP($D62,'VLookup Lists'!$B$11:$C$29,2,FALSE)="FLIP",1,0),"") | O62: =ISNUMBER(MATCH($E62,'VLookup Lists'!$E$2:$E$17,0)) -> FALSE
A63: =IF(ISBLANK(B63),"","ICJIA") -> ICJIA | B63: Community-Based Violence Intervention and Prevention (CB-VIP) | C63: 172216- LM | D63: 2117 | E63: Leaders in Transformational Education | F63: 44593 | G63: 44742 | H63: 57254 | I63: 2022 | M63: =IF(ISNUMBER(MATCH(E63,_xlfn.VSTACK('VLookup Lists'!$E$2:$E$17,'VLookup Lists'!$H$2:$H$38,'VLookup Lists'!$J$2:$J$8),0)),1,0) -> 0 | N63: =IFERROR(IF(VLOOKUP($D63,'VLookup Lists'!$B$11:$C$29,2,FALSE)="FLIP",1,0),"") | O63: =ISNUMBER(MATCH($E63,'VLookup Lists'!$E$2:$E$17,0)) -> FALSE
A64: =IF(ISBLANK(B64),"","ICJIA") -> ICJIA | B64: Community-Based Violence Intervention and Prevention (CB-VIP) | C64: 172217 AB | D64: 2117 | E64: Lost Boyz, Inc. | F64: 44593 | G64: 45473 | H64: 203834 | I64: 2022 | M64: =IF(ISNUMBER(MATCH(E64,_xlfn.VSTACK('VLookup Lists'!$E$2:$E$17,'VLookup Lists'!$H$2:$H$38,'VLookup Lists'!$J$2:$J$8),0)),1,0) -> 0 | N64: =IFERROR(IF(VLOOKUP($D64,'VLookup Lists'!$B$11:$C$29,2,FALSE)="FLIP",1,0),"") | O64: =ISNUMBER(MATCH($E64,'VLookup Lists'!$E$2:$E$17,0)) -> FALSE
A65: =IF(ISBLANK(B65),"","ICJIA") -> ICJIA | B65: Community-Based Violence Intervention and Prevention (CB-VIP) | C65: 172218 CAC | D65: 2117 | E65: Project HOOD | F65: 44593 | G65: 44742 | H65: 198921 | I65: 2022 | M65: =IF(ISNUMBER(MATCH(E65,_xlfn.VSTACK('VLookup Lists'!$E$2:$E$17,'VLookup Lists'!$H$2:$H$38,'VLookup Lists'!$J$2:$J$8),0)),1,0) -> 1 | N65: =IFERROR(IF(VLOOKUP($D65,'VLookup Lists'!$B$11:$C$29,2,FALSE)="FLIP",1,0),"") | O65: =ISNUMBER(MATCH($E65,'VLookup Lists'!$E$2:$E$17,0)) -> TRUE
A66: =IF(ISBLANK(B66),"","ICJIA") -> ICJIA | B66: Community-Based Violence Intervention and Prevention (CB-VIP) | C66: 822039 AB | D66: 2117 | E66: Promise Academy of Peoria | F66: 44666 | G66: 45396 | H66: 220998 | I66: 2022 | M66: =IF(ISNUMBER(MATCH(E66,_xlfn.VSTACK('VLookup Lists'!$E$2:$E$17,'VLookup Lists'!$H$2:$H$38,'VLookup Lists'!$J$2:$J$8),0)),1,0) -> 0 | N66: =IFERROR(IF(VLOOKUP($D66,'VLookup Lists'!$B$11:$C$29,2,FALSE)="FLIP",1,0),"") | O66: =ISNUMBER(MATCH($E66,'VLookup Lists'!$E$2:$E$17,0)) -> FALSE
A67: =IF(ISBLANK(B67),"","ICJIA") -> ICJIA | B67: Community-Based Violence Intervention and Prevention (CB-VIP) | C67: 172219- LM | D67: 2117 | E67: Reflections Foundation | F67: 44593 | G67: 44742 | H67: 50005 | I67: 2022 | M67: =IF(ISNUMBER(MATCH(E67,_xlfn.VSTACK('VLookup Lists'!$E$2:$E$17,'VLookup Lists'!$H$2:$H$38,'VLookup Lists'!$J$2:$J$8),0)),1,0) -> 0 | N67: =IFERROR(IF(VLOOKUP($D67,'VLookup Lists'!$B$11:$C$29,2,FALSE)="FLIP",1,0),"") | O67: =ISNUMBER(MATCH($E67,'VLookup Lists'!$E$2:$E$17,0)) -> FALSE
A68: =IF(ISBLANK(B68),"","ICJIA") -> ICJIA | B68: Community-Based Violence Intervention and Prevention (CB-VIP) | C68: 172220 - AB | D68: 2117 | E68: Ring of Hope | F68: 44593 | G68: 45473 | H68: 639443 | I68: 2022 | M68: =IF(ISNUMBER(MATCH(E68,_xlfn.VSTACK('VLookup Lists'!$E$2:$E$17,'VLookup Lists'!$H$2:$H$38,'VLookup Lists'!$J$2:$J$8),0)),1,0) -> 0 | N68: =IFERROR(IF(VLOOKUP($D68,'VLookup Lists'!$B$11:$C$29,2,FALSE)="FLIP",1,0),"") | O68: =ISNUMBER(MATCH($E68,'VLookup Lists'!$E$2:$E$17,0)) -> FALSE
A69: =IF(ISBLANK(B69),"","ICJIA") -> ICJIA | B69: Community-Based Violence Intervention and Prevention (CB-VIP) | C69: 172221 JG | D69: 2117 | E69: River City Community Development Center | F69: 44593 | G69: 45473 | H69: 1216721 | I69: 2022 | M69: =IF(ISNUMBER(MATCH(E69,_xlfn.VSTACK('VLookup Lists'!$E$2:$E$17,'VLookup Lists'!$H$2:$H$38,'VLookup Lists'!$J$2:$J$8),0)),1,0) -> 0 | N69: =IFERROR(IF(VLOOKUP($D69,'VLookup Lists'!$B$11:$C$29,2,FALSE)="FLIP",1,0),"") | O69: =ISNUMBER(MATCH($E69,'VLookup Lists'!$E$2:$E$17,0)) -> FALSE
A70: =IF(ISBLANK(B70),"","ICJIA") -> ICJIA | B70: Community-Based Violence Intervention and Prevention (CB-VIP) | C70: 172222 SBB | D70: 2117 | E70: Roseland Ceasefire Project Inc. | F70: 44593 | G70: 44742 | H70: 199682 | I70: 2022 | M70: =IF(ISNUMBER(MATCH(E70,_xlfn.VSTACK('VLookup Lists'!$E$2:$E$17,'VLookup Lists'!$H$2:$H$38,'VLookup Lists'!$J$2:$J$8),0)),1,0) -> 1 | N70: =IFERROR(IF(VLOOKUP($D70,'VLookup Lists'!$B$11:$C$29,2,FALSE)="FLIP",1,0),"") | O70: =ISNUMBER(MATCH($E70,'VLookup Lists'!$E$2:$E$17,0)) -> FALSE
A71: =IF(ISBLANK(B71),"","ICJIA") -> ICJIA | B71: Community-Based Violence Intervention and Prevention (CB-VIP) | D71: 2117 | E71: Storycatchers Theatre | F71: 44666 | G71: 45030 | H71: 482160 | I71: 2022 | M71: =IF(ISNUMBER(MATCH(E71,_xlfn.VSTACK('VLookup Lists'!$E$2:$E$17,'VLookup Lists'!$H$2:$H$38,'VLookup Lists'!$J$2:$J$8),0)),1,0) -> 0 | N71: =IFERROR(IF(VLOOKUP($D71,'VLookup Lists'!$B$11:$C$29,2,FALSE)="FLIP",1,0),"") | O71: =ISNUMBER(MATCH($E71,'VLookup Lists'!$E$2:$E$17,0)) -> FALSE
A72: =IF(ISBLANK(B72),"","ICJIA") -> ICJIA | B72: Community-Based Violence Intervention and Prevention (CB-VIP) | C72: 172223 - SW | D72: 2117 | E72: Taking Back Our Lives | F72: 44593 | G72: 44742 | H72: 113116 | I72: 2022 | M72: =IF(ISNUMBER(MATCH(E72,_xlfn.VSTACK('VLookup Lists'!$E$2:$E$17,'VLookup Lists'!$H$2:$H$38,'VLookup Lists'!$J$2:$J$8),0)),1,0) -> 0 | N72: =IFERROR(IF(VLOOKUP($D72,'VLookup Lists'!$B$11:$C$29,2,FALSE)="FLIP",1,0),"") | O72: =ISNUMBER(MATCH($E72,'VLookup Lists'!$E$2:$E$17,0)) -> FALSE
A73: =IF(ISBLANK(B73),"","ICJIA") -> ICJIA | B73: Community-Based Violence Intervention and Prevention (CB-VIP) | C73: 172224 J.G | D73: 2117 | E73: The Blessed Child | F73: 44593 | G73: 44742 | H73: 199311 | I73: 2022 | M73: =IF(ISNUMBER(MATCH(E73,_xlfn.VSTACK('VLookup Lists'!$E$2:$E$17,'VLookup Lists'!$H$2:$H$38,'VLookup Lists'!$J$2:$J$8),0)),1,0) -> 0 | N73: =IFERROR(IF(VLOOKUP($D73,'VLookup Lists'!$B$11:$C$29,2,FALSE)="FLIP",1,0),"") | O73: =ISNUMBER(MATCH($E73,'VLookup Lists'!$E$2:$E$17,0)) -> FALSE
A74: =IF(ISBLANK(B74),"","ICJIA") -> ICJIA | B74: Community-Based Violence Intervention and Prevention (CB-VIP) | C74: 172225 CAC | D74: 2117 | E74: The Firehouse Community Arts Center | F74: 44593 | G74: 44742 | H74: 176550 | I74: 2022 | M74: =IF(ISNUMBER(MATCH(E74,_xlfn.VSTACK('VLookup Lists'!$E$2:$E$17,'VLookup Lists'!$H$2:$H$38,'VLookup Lists'!$J$2:$J$8),0)),1,0) -> 1 | N74: =IFERROR(IF(VLOOKUP($D74,'VLookup Lists'!$B$11:$C$29,2,FALSE)="FLIP",1,0),"") | O74: =ISNUMBER(MATCH($E74,'VLookup Lists'!$E$2:$E$17,0)) -> FALSE
A75: =IF(ISBLANK(B75),"","ICJIA") -> ICJIA | B75: Community-Based Violence Intervention and Prevention (CB-VIP) | C75: 172226-CW | D75: 2117 | E75: The Support Group | F75: 44593 | G75: 45473 | H75: 199980 | I75: 2022 | M75: =IF(ISNUMBER(MATCH(E75,_xlfn.VSTACK('VLookup Lists'!$E$2:$E$17,'VLookup Lists'!$H$2:$H$38,'VLookup Lists'!$J$2:$J$8),0)),1,0) -> 0 | N75: =IFERROR(IF(VLOOKUP($D75,'VLookup Lists'!$B$11:$C$29,2,FALSE)="FLIP",1,0),"") | O75: =ISNUMBER(MATCH($E75,'VLookup Lists'!$E$2:$E$17,0)) -> FALSE
A76: =IF(ISBLANK(B76),"","ICJIA") -> ICJIA | B76: Community-Based Violence Intervention and Prevention (CB-VIP) | D76: 2117 | E76: Trickster Art Gallery | F76: 44593 | G76: 44742 | H76: 50535 | I76: 2022 | M76: =IF(ISNUMBER(MATCH(E76,_xlfn.VSTACK('VLookup Lists'!$E$2:$E$17,'VLookup Lists'!$H$2:$H$38,'VLookup Lists'!$J$2:$J$8),0)),1,0) -> 0 | N76: =IFERROR(IF(VLOOKUP($D76,'VLookup Lists'!$B$11:$C$29,2,FALSE)="FLIP",1,0),"") | O76: =ISNUMBER(MATCH($E76,'VLookup Lists'!$E$2:$E$17,0)) -> FALSE
A77: =IF(ISBLANK(B77),"","ICJIA") -> ICJIA | B77: Community-Based Violence Intervention and Prevention (CB-VIP) | D77: 2117 | E77: True to Life Foundation | F77: 44593 | G77: 44742 | H77: 137807 | I77: 2022 | M77: =IF(ISNUMBER(MATCH(E77,_xlfn.VSTACK('VLookup Lists'!$E$2:$E$17,'VLookup Lists'!$H$2:$H$38,'VLookup Lists'!$J$2:$J$8),0)),1,0) -> 0 | N77: =IFERROR(IF(VLOOKUP($D77,'VLookup Lists'!$B$11:$C$29,2,FALSE)="FLIP",1,0),"") | O77: =ISNUMBER(MATCH($E77,'VLookup Lists'!$E$2:$E$17,0)) -> FALSE
A78: =IF(ISBLANK(B78),"","ICJIA") -> ICJIA | B78: Community-Based Violence Intervention and Prevention (CB-VIP) | C78: 172229 | D78: 2117 | E78: Vermilion County Rape Crisis Center | F78: 44593 | G78: 44742 | H78: 88000 | I78: 2022 | M78: =IF(ISNUMBER(MATCH(E78,_xlfn.VSTACK('VLookup Lists'!$E$2:$E$17,'VLookup Lists'!$H$2:$H$38,'VLookup Lists'!$J$2:$J$8),0)),1,0) -> 0 | N78: =IFERROR(IF(VLOOKUP($D78,'VLookup Lists'!$B$11:$C$29,2,FALSE)="FLIP",1,0),"") | O78: =ISNUMBER(MATCH($E78,'VLookup Lists'!$E$2:$E$17,0)) -> FALSE
A79: =IF(ISBLANK(B79),"","ICJIA") -> ICJIA | B79: Community-Based Violence Intervention and Prevention (CB-VIP) | D79: 2117 | E79: Youth With A Positive Direction | F79: 44593 | G79: 44742 | H79: 212380 | I79: 2022 | M79: =IF(ISNUMBER(MATCH(E79,_xlfn.VSTACK('VLookup Lists'!$E$2:$E$17,'VLookup Lists'!$H$2:$H$38,'VLookup Lists'!$J$2:$J$8),0)),1,0) -> 0 | N79: =IFERROR(IF(VLOOKUP($D79,'VLookup Lists'!$B$11:$C$29,2,FALSE)="FLIP",1,0),"") | O79: =ISNUMBER(MATCH($E79,'VLookup Lists'!$E$2:$E$17,0)) -> FALSE
A80: =IF(ISBLANK(B80),"","ICJIA") -> ICJIA | B80: Community-Based Violence Intervention and Prevention (CB-VIP) | C80: 822019 MSC | D80: 2117 | E80: Center for Conflict Resolution | F80: 44666 | G80: 45030 | H80: 130042 | I80: 2023 | M80: =IF(ISNUMBER(MATCH(E80,_xlfn.VSTACK('VLookup Lists'!$E$2:$E$17,'VLookup Lists'!$H$2:$H$38,'VLookup Lists'!$J$2:$J$8),0)),1,0) -> 0 | N80: =IFERROR(IF(VLOOKUP($D80,'VLookup Lists'!$B$11:$C$29,2,FALSE)="FLIP",1,0),"") | O80: =ISNUMBER(MATCH($E80,'VLookup Lists'!$E$2:$E$17,0)) -> FALSE
A81: =IF(ISBLANK(B81),"","ICJIA") -> ICJIA | B81: Community-Based Violence Intervention and Prevention (CB-VIP) | C81: 822020 MSC | D81: 2117 | E81: Chicago Alliance Against Sexual Exploitation | F81: 44666 | G81: 45030 | H81: 476658 | I81: 2023 | M81: =IF(ISNUMBER(MATCH(E81,_xlfn.VSTACK('VLookup Lists'!$E$2:$E$17,'VLookup Lists'!$H$2:$H$38,'VLookup Lists'!$J$2:$J$8),0)),1,0) -> 0 | N81: =IFERROR(IF(VLOOKUP($D81,'VLookup Lists'!$B$11:$C$29,2,FALSE)="FLIP",1,0),"") | O81: =ISNUMBER(MATCH($E81,'VLookup Lists'!$E$2:$E$17,0)) -> FALSE
A82: =IF(ISBLANK(B82),"","ICJIA") -> ICJIA | B82: Community-Based Violence Intervention and Prevention (CB-VIP) | C82: 822024 | D82: 2117 | E82: Cullar Consulting, LLC | F82: 44666 | G82: 45396 | H82: 811745 | I82: 2023 | M82: =IF(ISNUMBER(MATCH(E82,_xlfn.VSTACK('VLookup Lists'!$E$2:$E$17,'VLookup Lists'!$H$2:$H$38,'VLookup Lists'!$J$2:$J$8),0)),1,0) -> 0 | N82: =IFERROR(IF(VLOOKUP($D82,'VLookup Lists'!$B$11:$C$29,2,FALSE)="FLIP",1,0),"") | O82: =ISNUMBER(MATCH($E82,'VLookup Lists'!$E$2:$E$17,0)) -> FALSE
A83: =IF(ISBLANK(B83),"","ICJIA") -> ICJIA | B83: Community-Based Violence Intervention and Prevention (CB-VIP) | C83: 822027 Cortisa Evans | D83: 2117 | E83: Friends of the Children - Chicago | F83: 44666 | G83: 45030 | H83: 491918 | I83: 2023 | M83: =IF(ISNUMBER(MATCH(E83,_xlfn.VSTACK('VLookup Lists'!$E$2:$E$17,'VLookup Lists'!$H$2:$H$38,'VLookup Lists'!$J$2:$J$8),0)),1,0) -> 0 | N83: =IFERROR(IF(VLOOKUP($D83,'VLookup Lists'!$B$11:$C$29,2,FALSE)="FLIP",1,0),"") | O83: =ISNUMBER(MATCH($E83,'VLookup Lists'!$E$2:$E$17,0)) -> FALSE
A84: =IF(ISBLANK(B84),"","ICJIA") -> ICJIA | B84: Community-Based Violence Intervention and Prevention (CB-VIP) | C84: 822028 Cortisa Evans | D84: 2117 | E84: George Washington Carver Association | F84: 44666 | G84: 45030 | H84: 479664 | I84: 2023 | M84: =IF(ISNUMBER(MATCH(E84,_xlfn.VSTACK('VLookup Lists'!$E$2:$E$17,'VLookup Lists'!$H$2:$H$38,'VLookup Lists'!$J$2:$J$8),0)),1,0) -> 0 | N84: =IFERROR(IF(VLOOKUP($D84,'VLookup Lists'!$B$11:$C$29,2,FALSE)="FLIP",1,0),"") | O84: =ISNUMBER(MATCH($E84,'VLookup Lists'!$E$2:$E$17,0)) -> FALSE
A85: =IF(ISBLANK(B85),"","ICJIA") -> ICJIA | B85: Community-Based Violence Intervention and Prevention (CB-VIP) | C85: 172212 CAC | D85: 2117 | E85: Greater Chatham Initiative | F85: 44593 | G85: 45473 | H85: 156229 | I85: 2023 | M85: =IF(ISNUMBER(MATCH(E85,_xlfn.VSTACK('VLookup Lists'!$E$2:$E$17,'VLookup Lists'!$H$2:$H$38,'VLookup Lists'!$J$2:$J$8),0)),1,0) -> 0 | N85: =IFERROR(IF(VLOOKUP($D85,'VLookup Lists'!$B$11:$C$29,2,FALSE)="FLIP",1,0),"") | O85: =ISNUMBER(MATCH($E85,'VLookup Lists'!$E$2:$E$17,0)) -> FALSE
A86: =IF(ISBLANK(B86),"","ICJIA") -> ICJIA | B86: Community-Based Violence Intervention and Prevention (CB-VIP) | D86: 2117 | E86: GRO Community | F86: 44666 | G86: 45396 | H86: 379466 | I86: 2023 | M86: =IF(ISNUMBER(MATCH(E86,_xlfn.VSTACK('VLookup Lists'!$E$2:$E$17,'VLookup Lists'!$H$2:$H$38,'VLookup Lists'!$J$2:$J$8),0)),1,0) -> 0 | N86: =IFERROR(IF(VLOOKUP($D86,'VLookup Lists'!$B$11:$C$29,2,FALSE)="FLIP",1,0),"") | O86: =ISNUMBER(MATCH($E86,'VLookup Lists'!$E$2:$E$17,0)) -> FALSE
A87: =IF(ISBLANK(B87),"","ICJIA") -> ICJIA | B87: Community-Based Violence Intervention and Prevention (CB-VIP) | C87: 592206 KS | D87: 2117 | E87: Lake County Crisis Center for the Prevention and Treatment of Domestic Violence, INC DBA A Safe Place | F87: 44743 | G87: 45107 | H87: 441413 | I87: 2023 | M87: =IF(ISNUMBER(MATCH(E87,_xlfn.VSTACK('VLookup Lists'!$E$2:$E$17,'VLookup Lists'!$H$2:$H$38,'VLookup Lists'!$J$2:$J$8),0)),1,0) -> 0 | N87: =IFERROR(IF(VLOOKUP($D87,'VLookup Lists'!$B$11:$C$29,2,FALSE)="FLIP",1,0),"") | O87: =ISNUMBER(MATCH($E87,'VLookup Lists'!$E$2:$E$17,0)) -> FALSE
A88: =IF(ISBLANK(B88),"","ICJIA") -> ICJIA | B88: Community-Based Violence Intervention and Prevention (CB-VIP) | C88: 172217 AB | D88: 2117 | E88: Lost Boyz, Inc. | F88: 44593 | G88: 45473 | H88: 203834 | I88: 2023 | M88: =IF(ISNUMBER(MATCH(E88,_xlfn.VSTACK('VLookup Lists'!$E$2:$E$17,'VLookup Lists'!$H$2:$H$38,'VLookup Lists'!$J$2:$J$8),0)),1,0) -> 0 | N88: =IFERROR(IF(VLOOKUP($D88,'VLookup Lists'!$B$11:$C$29,2,FALSE)="FLIP",1,0),"") | O88: =ISNUMBER(MATCH($E88,'VLookup Lists'!$E$2:$E$17,0)) -> FALSE
A89: =IF(ISBLANK(B89),"","ICJIA") -> ICJIA | B89: Community-Based Violence Intervention and Prevention (CB-VIP) | C89: 822039 AB | D89: 2117 | E89: Promise Academy of Peoria | F89: 44666 | G89: 45396 | H89: 220998 | I89: 2023 | M89: =IF(ISNUMBER(MATCH(E89,_xlfn.VSTACK('VLookup Lists'!$E$2:$E$17,'VLookup Lists'!$H$2:$H$38,'VLookup Lists'!$J$2:$J$8),0)),1,0) -> 0 | N89: =IFERROR(IF(VLOOKUP($D89,'VLookup Lists'!$B$11:$C$29,2,FALSE)="FLIP",1,0),"") | O89: =ISNUMBER(MATCH($E89,'VLookup Lists'!$E$2:$E$17,0)) -> FALSE
A90: =IF(ISBLANK(B90),"","ICJIA") -> ICJIA | B90: Community-Based Violence Intervention and Prevention (CB-VIP) | C90: 172220 - AB | D90: 2117 | E90: Ring of Hope | F90: 44593 | G90: 45473 | H90: 639443 | I90: 2023 | M90: =IF(ISNUMBER(MATCH(E90,_xlfn.VSTACK('VLookup Lists'!$E$2:$E$17,'VLookup Lists'!$H$2:$H$38,'VLookup Lists'!$J$2:$J$8),0)),1,0) -> 0 | N90: =IFERROR(IF(VLOOKUP($D90,'VLookup Lists'!$B$11:$C$29,2,FALSE)="FLIP",1,0),"") | O90: =ISNUMBER(MATCH($E90,'VLookup Lists'!$E$2:$E$17,0)) -> FALSE
A91: =IF(ISBLANK(B91),"","ICJIA") -> ICJIA | B91: Community-Based Violence Intervention and Prevention (CB-VIP) | C91: 172221 JG | D91: 2117 | E91: River City Community Development Center | F91: 44593 | G91: 45473 | H91: 1216721 | I91: 2023 | M91: =IF(ISNUMBER(MATCH(E91,_xlfn.VSTACK('VLookup Lists'!$E$2:$E$17,'VLookup Lists'!$H$2:$H$38,'VLookup Lists'!$J$2:$J$8),0)),1,0) -> 0 | N91: =IFERROR(IF(VLOOKUP($D91,'VLookup Lists'!$B$11:$C$29,2,FALSE)="FLIP",1,0),"") | O91: =ISNUMBER(MATCH($E91,'VLookup Lists'!$E$2:$E$17,0)) -> FALSE
A92: =IF(ISBLANK(B92),"","ICJIA") -> ICJIA | B92: Community-Based Violence Intervention and Prevention (CB-VIP) | D92: 2117 | E92: Storycatchers Theatre | F92: 44666 | G92: 45030 | H92: 482160 | I92: 2023 | M92: =IF(ISNUMBER(MATCH(E92,_xlfn.VSTACK('VLookup Lists'!$E$2:$E$17,'VLookup Lists'!$H$2:$H$38,'VLookup Lists'!$J$2:$J$8),0)),1,0) -> 0 | N92: =IFERROR(IF(VLOOKUP($D92,'VLookup Lists'!$B$11:$C$29,2,FALSE)="FLIP",1,0),"") | O92: =ISNUMBER(MATCH($E92,'VLookup Lists'!$E$2:$E$17,0)) -> FALSE
A93: =IF(ISBLANK(B93),"","ICJIA") -> ICJIA | B93: Community-Based Violence Intervention and Prevention (CB-VIP) | C93: 172226-CW | D93: 2117 | E93: The Support Group | F93: 44593 | G93: 45473 | H93: 199980 | I93: 2023 | M93: =IF(ISNUMBER(MATCH(E93,_xlfn.VSTACK('VLookup Lists'!$E$2:$E$17,'VLookup Lists'!$H$2:$H$38,'VLookup Lists'!$J$2:$J$8),0)),1,0) -> 0 | N93: =IFERROR(IF(VLOOKUP($D93,'VLookup Lists'!$B$11:$C$29,2,FALSE)="FLIP",1,0),"") | O93: =ISNUMBER(MATCH($E93,'VLookup Lists'!$E$2:$E$17,0)) -> FALSE
A94: =IF(ISBLANK(B94),"","ICJIA") -> ICJIA | B94: Community-Based Violence Intervention and Prevention (CB-VIP) | C94: 822012 | D94: 2117 | E94: Annie B. Jones Civic Arts Center. | F94: 45108 | G94: 45396 | H94: 253022 | I94: 2024 | M94: =IF(ISNUMBER(MATCH(E94,_xlfn.VSTACK('VLookup Lists'!$E$2:$E$17,'VLookup Lists'!$H$2:$H$38,'VLookup Lists'!$J$2:$J$8),0)),1,0) -> 0 | N94: =IFERROR(IF(VLOOKUP($D94,'VLookup Lists'!$B$11:$C$29,2,FALSE)="FLIP",1,0),"") | O94: =ISNUMBER(MATCH($E94,'VLookup Lists'!$E$2:$E$17,0)) -> FALSE
A95: =IF(ISBLANK(B95),"","ICJIA") -> ICJIA | B95: Community-Based Violence Intervention and Prevention (CB-VIP) | C95: 822013 | D95: 2117 | E95: Apna Ghar, Inc. | F95: 45108 | G95: 45396 | H95: 97858 | I95: 2024 | M95: =IF(ISNUMBER(MATCH(E95,_xlfn.VSTACK('VLookup Lists'!$E$2:$E$17,'VLookup Lists'!$H$2:$H$38,'VLookup Lists'!$J$2:$J$8),0)),1,0) -> 0 | N95: =IFERROR(IF(VLOOKUP($D95,'VLookup Lists'!$B$11:$C$29,2,FALSE)="FLIP",1,0),"") | O95: =ISNUMBER(MATCH($E95,'VLookup Lists'!$E$2:$E$17,0)) -> FALSE
A96: =IF(ISBLANK(B96),"","ICJIA") -> ICJIA | B96: Community-Based Violence Intervention and Prevention (CB-VIP) | C96: 822014 FSGU SBB | D96: 2117 | E96: Bella Ease | F96: 45108 | G96: 45396 | H96: 229844 | I96: 2024 | M96: =IF(ISNUMBER(MATCH(E96,_xlfn.VSTACK('VLookup Lists'!$E$2:$E$17,'VLookup Lists'!$H$2:$H$38,'VLookup Lists'!$J$2:$J$8),0)),1,0) -> 0 | N96: =IFERROR(IF(VLOOKUP($D96,'VLookup Lists'!$B$11:$C$29,2,FALSE)="FLIP",1,0),"") | O96: =ISNUMBER(MATCH($E96,'VLookup Lists'!$E$2:$E$17,0)) -> FALSE
A97: =IF(ISBLANK(B97),"","ICJIA") -> ICJIA | B97: Community-Based Violence Intervention and Prevention (CB-VIP) | C97: 822015- LM | D97: 2117 | E97: Black Educational Advocacy Coalition | F97: 45108 | G97: 45396 | H97: 278264 | I97: 2024 | M97: =IF(ISNUMBER(MATCH(E97,_xlfn.VSTACK('VLookup Lists'!$E$2:$E$17,'VLookup Lists'!$H$2:$H$38,'VLookup Lists'!$J$2:$J$8),0)),1,0) -> 0 | N97: =IFERROR(IF(VLOOKUP($D97,'VLookup Lists'!$B$11:$C$29,2,FALSE)="FLIP",1,0),"") | O97: =ISNUMBER(MATCH($E97,'VLookup Lists'!$E$2:$E$17,0)) -> FALSE
A98: =IF(ISBLANK(B98),"","ICJIA") -> ICJIA | B98: Community-Based Violence Intervention and Prevention (CB-VIP) | C98: 822016- LM | D98: 2117 | E98: Books Over Balls | F98: 45108 | G98: 45396 | H98: 279864 | I98: 2024 | M98: =IF(ISNUMBER(MATCH(E98,_xlfn.VSTACK('VLookup Lists'!$E$2:$E$17,'VLookup Lists'!$H$2:$H$38,'VLookup Lists'!$J$2:$J$8),0)),1,0) -> 0 | N98: =IFERROR(IF(VLOOKUP($D98,'VLookup Lists'!$B$11:$C$29,2,FALSE)="FLIP",1,0),"") | O98: =ISNUMBER(MATCH($E98,'VLookup Lists'!$E$2:$E$17,0)) -> FALSE
A99: =IF(ISBLANK(B99),"","ICJIA") -> ICJIA | B99: Community-Based Violence Intervention and Prevention (CB-VIP) | C99: 822018 FSGU SBB | D99: 2117 | E99: Catholic Bishop of Chicago - St. Sabina | F99: 45108 | G99: 45473 | H99: 137360 | I99: 2024 | M99: =IF(ISNUMBER(MATCH(E99,_xlfn.VSTACK('VLookup Lists'!$E$2:$E$17,'VLookup Lists'!$H$2:$H$38,'VLookup Lists'!$J$2:$J$8),0)),1,0) -> 0 | N99: =IFERROR(IF(VLOOKUP($D99,'VLookup Lists'!$B$11:$C$29,2,FALSE)="FLIP",1,0),"") | O99: =ISNUMBER(MATCH($E99,'VLookup Lists'!$E$2:$E$17,0)) -> FALSE
A100: =IF(ISBLANK(B100),"","ICJIA") -> ICJIA | B100: Community-Based Violence Intervention and Prevention (CB-VIP) | C100: 822019-J.G | D100: 2117 | E100: Center for Conflict Resolution | F100: 45108 | G100: 45396 | H100: 113693 | I100: 2024 | M100: =IF(ISNUMBER(MATCH(E100,_xlfn.VSTACK('VLookup Lists'!$E$2:$E$17,'VLookup Lists'!$H$2:$H$38,'VLookup Lists'!$J$2:$J$8),0)),1,0) -> 0 | N100: =IFERROR(IF(VLOOKUP($D100,'VLookup Lists'!$B$11:$C$29,2,FALSE)="FLIP",1,0),"") | O100: =ISNUMBER(MATCH($E100,'VLookup Lists'!$E$2:$E$17,0)) -> FALSE
...

Sheet Master List
A1: {=_xlfn._xlws.FILTER(_xlfn.VSTACK(OFVP!A1:O9496,ICJIA!A2:O9583),_xlfn.VSTACK(OFVP!B1:B9496,ICJIA!B2:B9583)<>"")} -> Source | B1: Grant Type | C1: Award ID | D1: CSFA | E1: Grantee Name | F1: Start Date | G1: End Date | H1: Award Amount | I1: Fiscal Year | J1: Chicago/Greater Illinois | K1: County | L1: Community Area | M1: CVI | N1: FLIP | O1: CP4P
A2: OFVP | B2: TA Services Violence Prevention | C2: 0 | D2: 2771 | E2: Acclivus, Inc. | F2: 0 | G2: 45930 | H2: 150000 | I2: 2022 | J2: Chicago | K2: Cook | L2: z TTAS - Chicago | M2: 1 | N2: 0 | O2: FALSE
A3: OFVP | B3: TA Services Violence Prevention | C3: 0 | D3: 2771 | E3: Metropolitan Family Services | F3: 0 | G3: 45565 | H3: 188061 | I3: 2022 | J3: Chicago | K3: Cook | L3: z TTAS - Chicago | M3: 1 | N3: 0 | O3: TRUE
A4: OFVP | B4: TA Services Violence Prevention | C4: 0 | D4: 2771 | E4: UNIVERSAL FAMILY CONNECTION | F4: 0 | G4: 45344 | H4: 159600 | I4: 2022 | J4: Chicago | K4: Cook | L4: z TTAS - Chicago | M4: 0 | N4: 0 | O4: FALSE
A5: OFVP | B5: TA Services Youth Development | C5: 0 | D5: 2772 | E5: BLACK COMMUNITY PROVIDER | F5: 0 | G5: 45565 | H5: 145486 | I5: 2022 | J5: Chicago | K5: Cook | L5: z TTAS - Chicago | M5: 0 | N5: 0 | O5: FALSE
A6: OFVP | B6: TA Services Youth Development | C6: 0 | D6: 2772 | E6: Metropolitan Family Services | F6: 0 | G6: 45565 | H6: 203463 | I6: 2022 | J6: Chicago | K6: Cook | L6: z TTAS - Chicago | M6: 1 | N6: 0 | O6: TRUE
A7: OFVP | B7: TA Services Youth Development | C7: 0 | D7: 2772 | E7: Prevention First, Inc | F7: 0 | G7: 45565 | H7: 168150 | I7: 2022 | J7: Chicago | K7: Cook | L7: z TTAS - Chicago | M7: 0 | N7: 0 | O7: FALSE
A8: OFVP | B8: Chicago Conveners | C8: 0 | D8: 2773 | E8: Lawrence Hall Youth Services | F8: 0 | G8: 45747 | H8: 25000 | I8: 2022 | J8: Chicago | K8: Cook | L8: South Shore | M8: 0 | N8: 0 | O8: FALSE
A9: OFVP | B9: Chicago Conveners | C9: 0 | D9: 2773 | E9: UNIVERSAL FAMILY CONNECTION | F9: 0 | G9: 45747 | H9: 24999.95 | I9: 2022 | J9: Chicago | K9: Cook | L9: Auburn Gresham | M9: 0 | N9: 0 | O9: FALSE
A10: OFVP | B10: Chicago Conveners | C10: 0 | D10: 2773 | E10: UNIVERSAL FAMILY CONNECTION | F10: 0 | G10: 45747 | H10: 24999.95 | I10: 2022 | J10: Chicago | K10: Cook | L10: Englewood | M10: 0 | N10: 0 | O10: FALSE
A11: OFVP | B11: Chicago Conveners | C11: 0 | D11: 2773 | E11: WHAT ABOUT US CHARITABLE | F11: 0 | G11: 45747 | H11: 25000 | I11: 2022 | J11: Chicago | K11: Cook | L11: Austin | M11: 0 | N11: 0 | O11: FALSE
A12: OFVP | B12: Chicago Conveners | C12: 0 | D12: 2773 | E12: YMCA OF METROPOLITAN CHICAGO | F12: 0 | G12: 45747 | H12: 24075 | I12: 2022 | J12: Chicago | K12: Cook | L12: Chicago Lawn | M12: 1 | N12: 0 | O12: FALSE
A13: OFVP | B13: Chicago Conveners | C13: 0 | D13: 2773 | E13: YMCA OF METROPOLITAN CHICAGO | F13: 0 | G13: 45747 | H13: 24075 | I13: 2022 | J13: Chicago | K13: Cook | L13: East Garfield Park | M13: 1 | N13: 0 | O13: FALSE
... A1584: OFVP | B1584: Back To Our Future | C1584: 0 | D1584: 3621 | E1584: Chicago Public Schools | F1584: 0 | G1584: 0 | H1584: 2000000 | I1584: 2026 | J1584: Chicago | K1584: Cook | L1584: 3621 Chicago Only | M1584: 0 | N1584: 0 | O1584: FALSE
A1585: ICJIA | B1585: Community-based Violence Intervention & Prevention (Fed) | C1585: 662314 JES | D1585: 3380 | E1585: Angel of God Resource Center, Inc. | F1585: 45566 | G1585: 45930 | H1585: 300000 | I1585: 2025 | J1585: 0 | K1585: 0 | L1585: 0 | M1585: 0 | O1585: FALSE
A1586: ICJIA | B1586: Community-based Violence Intervention & Prevention (Fed) | C1586: 662315 JES | D1586: 3380 | E1586: Breakthrough Urban Ministries | F1586: 45566 | G1586: 45930 | H1586: 128577 | I1586: 2025 | J1586: 0 | K1586: 0 | L1586: 0 | M1586: 1 | O1586: TRUE
A1587: ICJIA | B1587: Community-based Violence Intervention & Prevention (Fed) | C1587: 662313 JES | D1587: 3380 | E1587: BUILD Inc. | F1587: 45566 | G1587: 45930 | H1587: 260640 | I1587: 2025 | J1587: 0 | K1587: 0 | L1587: 0 | M1587: 1 | O1587: FALSE
A1588: ICJIA | B1588: Community-based Violence Intervention & Prevention (Fed) | C1588: 662310 JES | D1588: 3380 | E1588: Lawndale Christian Legal Center | F1588: 45474 | G1588: 45838 | H1588: 100000 | I1588: 2025 | J1588: 0 | K1588: 0 | L1588: 0 | M1588: 0 | O1588: FALSE
A1589: ICJIA | B1589: Community-based Violence Intervention & Prevention (Fed) | C1589: 662311 JES | D1589: 3380 | E1589: New Eclipse Community Alliance | F1589: 45566 | G1589: 45930 | H1589: 614014 | I1589: 2025 | J1589: 0 | K1589: 0 | L1589: 0 | M1589: 0 | O1589: FALSE
A1590: ICJIA | B1590: Community-based Violence Intervention & Prevention (Fed) | C1590: 662312 JS | D1590: 3380 | E1590: Roseland Ceasefire Project Inc. | F1590: 45474 | G1590: 45838 | H1590: 177455 | I1590: 2025 | J1590: 0 | K1590: 0 | L1590: 0 | M1590: 1 | O1590: FALSE
A1591: ICJIA | B1591: Community-based Violence Intervention & Prevention (Fed) | C1591: 662316 JES | D1591: 3380 | E1591: Southwest Organizing Project (SWOP) | F1591: 45566 | G1591: 45930 | H1591: 214461 | I1591: 2025 | J1591: 0 | K1591: 0 | L1591: 0 | M1591: 1 | O1591: TRUE
A1592: ICJIA | B1592: Community-Based Violence Intervention and Prevention (CB-VIP) | C1592: 172000 SW | D1592: 2117 | E1592: Alternatives, Inc. | F1592: 43647 | G1592: 44012 | H1592: 317210 | I1592: 2020 | J1592: 0 | K1592: 0 | L1592: 0 | M1592: 0 | O1592: FALSE
A1593: ICJIA | B1593: Community-Based Violence Intervention and Prevention (CB-VIP) | C1593: 172001 | D1593: 2117 | E1593: BIG BROTHERS-BIG SISTERS OF METROPOLITAN CHICAGO | F1593: 43647 | G1593: 44012 | H1593: 291588 | I1593: 2020 | J1593: 0 | K1593: 0 | L1593: 0 | M1593: 0 | O1593: FALSE
A1594: ICJIA | B1594: Community-Based Violence Intervention and Prevention (CB-VIP) | C1594: 172002 STB | D1594: 2117 | E1594: Bright Star Community Outreach | F1594: 43647 | G1594: 44012 | H1594: 690921 | I1594: 2020 | J1594: 0 | K1594: 0 | L1594: 0 | M1594: 0 | O1594: FALSE
A1595: ICJIA | B1595: Community-Based Violence Intervention and Prevention (CB-VIP) | C1595: 172003 STB | D1595: 2117 | E1595: Cabrini Green Legal AId | F1595: 43647 | G1595: 44012 | H1595: 173418 | I1595: 2020 | J1595: 0 | K1595: 0 | L1595: 0 | M1595: 0 | O1595: FALSE
A1596: ICJIA | B1596: Community-Based Violence Intervention and Prevention (CB-VIP) | C1596: 172004 | D1596: 2117 | E1596: Catholic Charities of the Archdiocese of Chicago | F1596: 43647 | G1596: 44012 | H1596: 569782 | I1596: 2020 | J1596: 0 | K1596: 0 | L1596: 0 | M1596: 0 | O1596: FALSE
A1597: ICJIA | B1597: Community-Based Violence Intervention and Prevention (CB-VIP) | C1597: 172005 | D1597: 2117 | E1597: Children's Home & Aid Society of Illinois dba Brightpoint | F1597: 43647 | G1597: 44012 | H1597: 102173 | I1597: 2020 | J1597: 0 | K1597: 0 | L1597: 0 | M1597: 0 | O1597: FALSE
A1598: ICJIA | B1598: Community-Based Violence Intervention and Prevention (CB-VIP) | C1598: 172006 STB | D1598: 2117 | E1598: Gary Comer Youth Center, Inc. | F1598: 43647 | G1598: 44012 | H1598: 807505 | I1598: 2020 | J1598: 0 | K1598: 0 | L1598: 0 | M1598: 0 | O1598: FALSE
A1599: ICJIA | B1599: Community-Based Violence Intervention and Prevention (CB-VIP) | C1599: 172007 STB | D1599: 2117 | E1599: Heartland Alliance | F1599: 43647 | G1599: 44012 | H1599: 659942 | I1599: 2020 | J1599: 0 | K1599: 0 | L1599: 0 | M1599: 0 | O1599: FALSE
A1600: ICJIA | B1600: Community-Based Violence Intervention and Prevention (CB-VIP) | C1600: 172008 SW | D1600: 2117 | E1600: Illinois Association of Juvenile Justice Councils | F1600: 43647 | G1600: 44012 | H1600: 929606 | I1600: 2020 | J1600: 0 | K1600: 0 | L1600: 0 | M1600: 0 | O1600: FALSE
A1601: ICJIA | B1601: Community-Based Violence Intervention and Prevention (CB-VIP) | C1601: 172014 SW | D1601: 2117 | E1601: Lawrence Hall Youth Services | F1601: 43647 | G1601: 44012 | H1601: 192556 | I1601: 2020 | J1601: 0 | K1601: 0 | L1601: 0 | M1601: 0 | O1601: FALSE
A1602: ICJIA | B1602: Community-Based Violence Intervention and Prevention (CB-VIP) | C1602: 172010 SW | D1602: 2117 | E1602: Northeast DuPage Family and Youth Services | F1602: 43647 | G1602: 44012 | H1602: 132352 | I1602: 2020 | J1602: 0 | K1602: 0 | L1602: 0 | M1602: 0 | O1602: FALSE
A1603: ICJIA | B1603: Community-Based Violence Intervention and Prevention (CB-VIP) | C1603: 172011 SW | D1603: 2117 | E1603: Pilsen Wellness Center, Inc. | F1603: 43647 | G1603: 44012 | H1603: 251072 | I1603: 2020 | J1603: 0 | K1603: 0 | L1603: 0 | M1603: 0 | O1603: FALSE
A1604: ICJIA | B1604: Community-Based Violence Intervention and Prevention (CB-VIP) | C1604: 172012 SW | D1604: 2117 | E1604: Region 1 Planning Council | F1604: 43647 | G1604: 44012 | H1604: 195923 | I1604: 2020 | J1604: 0 | K1604: 0 | L1604: 0 | M1604: 0 | O1604: FALSE
A1605: ICJIA | B1605: Community-Based Violence Intervention and Prevention (CB-VIP) | C1605: 172015 SW | D1605: 2117 | E1605: South Shore Drill Team & Performing Arts Ensemble | F1605: 43647 | G1605: 44012 | H1605: 83195 | I1605: 2020 | J1605: 0 | K1605: 0 | L1605: 0 | M1605: 0 | O1605: FALSE
A1606: ICJIA | B1606: Community-Based Violence Intervention and Prevention (CB-VIP) | C1606: 172004 | D1606: 2117 | E1606: Springfield Urban League, Inc. | F1606: 43647 | G1606: 44012 | H1606: 313943 | I1606: 2020 | J1606: 0 | K1606: 0 | L1606: 0 | M1606: 0 | O1606: FALSE
A1607: ICJIA | B1607: Community-Based Violence Intervention and Prevention (CB-VIP) | C1607: 172017 SW | D1607: 2117 | E1607: UNIVERSAL FAMILY CONNECTION, INC. | F1607: 43647 | G1607: 44012 | H1607: 682382 | I1607: 2020 | J1607: 0 | K1607: 0 | L1607: 0 | M1607: 0 | O1607: FALSE
A1608: ICJIA | B1608: Community-Based Violence Intervention and Prevention (CB-VIP) | C1608: 0 | D1608: 2117 | E1608: Alternatives, Inc. | F1608: 44013 | G1608: 44377 | H1608: 317210 | I1608: 2021 | J1608: 0 | K1608: 0 | L1608: 0 | M1608: 0 | O1608: FALSE
A1609: ICJIA | B1609: Community-Based Violence Intervention and Prevention (CB-VIP) | C1609: 172101 LM | D1609: 2117 | E1609: BIG BROTHERS-BIG SISTERS OF METROPOLITAN CHICAGO | F1609: 44013 | G1609: 44377 | H1609: 291368 | I1609: 2021 | J1609: 0 | K1609: 0 | L1609: 0 | M1609: 0 | O1609: FALSE
A1610: ICJIA | B1610: Community-Based Violence Intervention and Prevention (CB-VIP) | C1610: 0 | D1610: 2117 | E1610: Bright Star Community Outreach | F1610: 44013 | G1610: 44377 | H1610: 671649 | I1610: 2021 | J1610: 0 | K1610: 0 | L1610: 0 | M1610: 0 | O1610: FALSE
A1611: ICJIA | B1611: Community-Based Violence Intervention and Prevention (CB-VIP) | C1611: 0 | D1611: 2117 | E1611: Cabrini Green Legal Aid | F1611: 44013 | G1611: 44377 | H1611: 172781 | I1611: 2021 | J1611: 0 | K1611: 0 | L1611: 0 | M1611: 0 | O1611: FALSE
A1612: ICJIA | B1612: Community-Based Violence Intervention and Prevention (CB-VIP) | C1612: 0 | D1612: 2117 | E1612: Catholic Charities of the Archdiocese of Chicago | F1612: 44013 | G1612: 44377 | H1612: 568817 | I1612: 2021 | J1612: 0 | K1612: 0 | L1612: 0 | M1612: 0 | O1612: FALSE
A1613: ICJIA | B1613: Community-Based Violence Intervention and Prevention (CB-VIP) | C1613: 172105 LM | D1613: 2117 | E1613: Children's Home & Aid Society of Illinois dba Brightpoint | F1613: 44013 | G1613: 44377 | H1613: 102173 | I1613: 2021 | J1613: 0 | K1613: 0 | L1613: 0 | M1613: 0 | O1613: FALSE
A1614: ICJIA | B1614: Community-Based Violence Intervention and Prevention (CB-VIP) | C1614: 0 | D1614: 2117 | E1614: Gary Comer Youth Center, Inc. | F1614: 44013 | G1614: 44377 | H1614: 807505 | I1614: 2021 | J1614: 0 | K1614: 0 | L1614: 0 | M1614: 0 | O1614: FALSE
A1615: ICJIA | B1615: Community-Based Violence Intervention and Prevention (CB-VIP) | C1615: 0 | D1615: 2117 | E1615: Heartland Alliance | F1615: 44013 | G1615: 44377 | H1615: 659942 | I1615: 2021 | J1615: 0 | K1615: 0 | L1615: 0 | M1615: 0 | O1615: FALSE
A1616: ICJIA | B1616: Community-Based Violence Intervention and Prevention (CB-VIP) | C1616: 0 | D1616: 2117 | E1616: Illinois Association of Juvenile Justice Councils | F1616: 44013 | G1616: 44377 | H1616: 928239 | I1616: 2021 | J1616: 0 | K1616: 0 | L1616: 0 | M1616: 0 | O1616: FALSE
A1617: ICJIA | B1617: Community-Based Violence Intervention and Prevention (CB-VIP) | C1617: 0 | D1617: 2117 | E1617: Lawrence Hall Youth Services | F1617: 44013 | G1617: 44377 | H1617: 192556 | I1617: 2021 | J1617: 0 | K1617: 0 | L1617: 0 | M1617: 0 | O1617: FALSE
A1618: ICJIA | B1618: Community-Based Violence Intervention and Prevention (CB-VIP) | C1618: 0 | D1618: 2117 | E1618: Northeast DuPage Family and Youth Services | F1618: 44013 | G1618: 44377 | H1618: 132035 | I1618: 2021 | J1618: 0 | K1618: 0 | L1618: 0 | M1618: 0 | O1618: FALSE
A1619: ICJIA | B1619: Community-Based Violence Intervention and Prevention (CB-VIP) | C1619: 172111 LM | D1619: 2117 | E1619: Pilsen Wellness Center, Inc. | F1619: 44013 | G1619: 44377 | H1619: 251061 | I1619: 2021 | J1619: 0 | K1619: 0 | L1619: 0 | M1619: 0 | O1619: FALSE
A1620: ICJIA | B1620: Community-Based Violence Intervention and Prevention (CB-VIP) | C1620: 172112 KE | D1620: 2117 | E1620: Region 1 Planning Council | F1620: 44013 | G1620: 44377 | H1620: 195923 | I1620: 2021 | J1620: 0 | K1620: 0 | L1620: 0 | M1620: 0 | O1620: FALSE
A1621: ICJIA | B1621: Community-Based Violence Intervention and Prevention (CB-VIP) | C1621: 172115 SA | D1621: 2117 | E1621: South Shore Drill Team & Performing Arts Ensemble | F1621: 44013 | G1621: 44377 | H1621: 83195 | I1621: 2021 | J1621: 0 | K1621: 0 | L1621: 0 | M1621: 0 | O1621: FALSE
A1622: ICJIA | B1622: Community-Based Violence Intervention and Prevention (CB-VIP) | C1622: 172113 AB | D1622: 2117 | E1622: Springfield Urban League, Inc. | F1622: 44013 | G1622: 44377 | H1622: 313943 | I1622: 2021 | J1622: 0 | K1622: 0 | L1622: 0 | M1622: 0 | O1622: FALSE
A1623: ICJIA | B1623: Community-Based Violence Intervention and Prevention (CB-VIP) | C1623: 0 | D1623: 2117 | E1623: UNIVERSAL FAMILY CONNECTION, INC. | F1623: 44013 | G1623: 44377 | H1623: 682375 | I1623: 2021 | J1623: 0 | K1623: 0 | L1623: 0 | M1623: 0 | O1623: FALSE
A1624: ICJIA | B1624: Community-Based Violence Intervention and Prevention (CB-VIP) | C1624: 172200 LMurphy | D1624: 2117 | E1624: Alternatives, Inc. | F1624: 44593 | G1624: 44742 | H1624: 166281 | I1624: 2022 | J1624: 0 | K1624: 0 | L1624: 0 | M1624: 0 | O1624: FALSE
A1625: ICJIA | B1625: Community-Based Violence Intervention and Prevention (CB-VIP) | C1625: 172201- LM | D1625: 2117 | E1625: Area Consortium of Educational Services (ACES) 4 Our Youth | F1625: 44593 | G1625: 44742 | H1625: 225436 | I1625: 2022 | J1625: 0 | K1625: 0 | L1625: 0 | M1625: 0 | O1625: FALSE
A1626: ICJIA | B1626: Community-Based Violence Intervention and Prevention (CB-VIP) | C1626: 0 | D1626: 2117 | E1626: BandWith Chicago | F1626: 44593 | G1626: 44742 | H1626: 60465 | I1626: 2022 | J1626: 0 | K1626: 0 | L1626: 0 | M1626: 0 | O1626: FALSE
A1627: ICJIA | B1627: Community-Based Violence Intervention and Prevention (CB-VIP) | C1627: 172203 HA | D1627: 2117 | E1627: Between Friends | F1627: 44593 | G1627: 44742 | H1627: 109399 | I1627: 2022 | J1627: 0 | K1627: 0 | L1627: 0 | M1627: 0 | O1627: FALSE
A1628: ICJIA | B1628: Community-Based Violence Intervention and Prevention (CB-VIP) | C1628: 0 | D1628: 2117 | E1628: Boxing Out Negativity, Inc. | F1628: 44593 | G1628: 44742 | H1628: 199335 | I1628: 2022 | J1628: 0 | K1628: 0 | L1628: 0 | M1628: 0 | O1628: FALSE
A1629: ICJIA | B1629: Community-Based Violence Intervention and Prevention (CB-VIP) | C1629: 822019 MSC | D1629: 2117 | E1629: Center for Conflict Resolution | F1629: 44666 | G1629: 45030 | H1629: 130042 | I1629: 2022 | J1629: 0 | K1629: 0 | L1629: 0 | M1629: 0 | O1629: FALSE
A1630: ICJIA | B1630: Community-Based Violence Intervention and Prevention (CB-VIP) | C1630: 0 | D1630: 2117 | E1630: CHAMPS MALE MENTORING PROGRAM-CHIRISE | F1630: 44593 | G1630: 44742 | H1630: 101459 | I1630: 2022 | J1630: 0 | K1630: 0 | L1630: 0 | M1630: 0 | O1630: FALSE
A1631: ICJIA | B1631: Community-Based Violence Intervention and Prevention (CB-VIP) | C1631: 822020 MSC | D1631: 2117 | E1631: Chicago Alliance Against Sexual Exploitation | F1631: 44666 | G1631: 45030 | H1631: 476658 | I1631: 2022 | J1631: 0 | K1631: 0 | L1631: 0 | M1631: 0 | O1631: FALSE
A1632: ICJIA | B1632: Community-Based Violence Intervention and Prevention (CB-VIP) | C1632: 172206 FSGU AB | D1632: 2117 | E1632: Chicago Youth Boxing Club Inc. | F1632: 44593 | G1632: 44742 | H1632: 87693 | I1632: 2022 | J1632: 0 | K1632: 0 | L1632: 0 | M1632: 0 | O1632: FALSE
A1633: ICJIA | B1633: Community-Based Violence Intervention and Prevention (CB-VIP) | C1633: 0 | D1633: 2117 | E1633: Chicago Youth Programs | F1633: 44593 | G1633: 44742 | H1633: 88450 | I1633: 2022 | J1633: 0 | K1633: 0 | L1633: 0 | M1633: 0 | O1633: FALSE
A1634: ICJIA | B1634: Community-Based Violence Intervention and Prevention (CB-VIP) | C1634: 172208 FSGU SBB | D1634: 2117 | E1634: CircEsteem, Inc. | F1634: 44593 | G1634: 44742 | H1634: 182144 | I1634: 2022 | J1634: 0 | K1634: 0 | L1634: 0 | M1634: 0 | O1634: FALSE
A1635: ICJIA | B1635: Community-Based Violence Intervention and Prevention (CB-VIP) | C1635: 822024 | D1635: 2117 | E1635: Cullar Consulting, LLC | F1635: 44666 | G1635: 45396 | H1635: 811745 | I1635: 2022 | J1635: 0 | K1635: 0 | L1635: 0 | M1635: 0 | O1635: FALSE
A1636: ICJIA | B1636: Community-Based Violence Intervention and Prevention (CB-VIP) | C1636: 172209 CAC | D1636: 2117 | E1636: Duane Dean Behavioral Health Center | F1636: 44593 | G1636: 44742 | H1636: 125000 | I1636: 2022 | J1636: 0 | K1636: 0 | L1636: 0 | M1636: 0 | O1636: FALSE
A1637: ICJIA | B1637: Community-Based Violence Intervention and Prevention (CB-VIP) | C1637: 172210 CAC | D1637: 2117 | E1637: Entrepreneurs Academy | F1637: 44593 | G1637: 44742 | H1637: 193684 | I1637: 2022 | J1637: 0 | K1637: 0 | L1637: 0 | M1637: 0 | O1637: FALSE
A1638: ICJIA | B1638: Community-Based Violence Intervention and Prevention (CB-VIP) | C1638: 822027 Cortisa Evans | D1638: 2117 | E1638: Friends of the Children - Chicago | F1638: 44666 | G1638: 45030 | H1638: 491918 | I1638: 2022 | J1638: 0 | K1638: 0 | L1638: 0 | M1638: 0 | O1638: FALSE
A1639: ICJIA | B1639: Community-Based Violence Intervention and Prevention (CB-VIP) | C1639: 822028 Cortisa Evans | D1639: 2117 | E1639: George Washington Carver Association | F1639: 44666 | G1639: 45030 | H1639: 479664 | I1639: 2022 | J1639: 0 | K1639: 0 | L1639: 0 | M1639: 0 | O1639: FALSE
A1640: ICJIA | B1640: Community-Based Violence Intervention and Prevention (CB-VIP) | C1640: 172211 CAC | D1640: 2117 | E1640: Girls Inc. of Chicago | F1640: 44593 | G1640: 44742 | H1640: 181200 | I1640: 2022 | J1640: 0 | K1640: 0 | L1640: 0 | M1640: 0 | O1640: FALSE
A1641: ICJIA | B1641: Community-Based Violence Intervention and Prevention (CB-VIP) | C1641: 172212 CAC | D1641: 2117 | E1641: Greater Chatham Initiative | F1641: 44593 | G1641: 45473 | H1641: 156229 | I1641: 2022 | J1641: 0 | K1641: 0 | L1641: 0 | M1641: 0 | O1641: FALSE
A1642: ICJIA | B1642: Community-Based Violence Intervention and Prevention (CB-VIP) | C1642: 0 | D1642: 2117 | E1642: GRO Community | F1642: 44666 | G1642: 45396 | H1642: 379466 | I1642: 2022 | J1642: 0 | K1642: 0 | L1642: 0 | M1642: 0 | O1642: FALSE
A1643: ICJIA | B1643: Community-Based Violence Intervention and Prevention (CB-VIP) | C1643: 172213 SBB FSGU | D1643: 2117 | E1643: Hope Center Foundation | F1643: 44593 | G1643: 44742 | H1643: 142678 | I1643: 2022 | J1643: 0 | K1643: 0 | L1643: 0 | M1643: 0 | O1643: FALSE
A1644: ICJIA | B1644: Community-Based Violence Intervention and Prevention (CB-VIP) | C1644: 172214 SBB | D1644: 2117 | E1644: Illinois Association of Juvenile Justice Councils | F1644: 44593 | G1644: 44742 | H1644: 130220 | I1644: 2022 | J1644: 0 | K1644: 0 | L1644: 0 | M1644: 0 | O1644: FALSE
A1645: ICJIA | B1645: Community-Based Violence Intervention and Prevention (CB-VIP) | C1645: 172215 FSGU SBB | D1645: 2117 | E1645: Ladies of Virtue | F1645: 44593 | G1645: 44742 | H1645: 100000 | I1645: 2022 | J1645: 0 | K1645: 0 | L1645: 0 | M1645: 0 | O1645: FALSE
A1646: ICJIA | B1646: Community-Based Violence Intervention and Prevention (CB-VIP) | C1646: 172216- LM | D1646: 2117 | E1646: Leaders in Transformational Education | F1646: 44593 | G1646: 44742 | H1646: 57254 | I1646: 2022 | J1646: 0 | K1646: 0 | L1646: 0 | M1646: 0 | O1646: FALSE
A1647: ICJIA | B1647: Community-Based Violence Intervention and Prevention (CB-VIP) | C1647: 172217 AB | D1647: 2117 | E1647: Lost Boyz, Inc. | F1647: 44593 | G1647: 45473 | H1647: 203834 | I1647: 2022 | J1647: 0 | K1647: 0 | L1647: 0 | M1647: 0 | O1647: FALSE
A1648: ICJIA | B1648: Community-Based Violence Intervention and Prevention (CB-VIP) | C1648: 172218 CAC | D1648: 2117 | E1648: Project HOOD | F1648: 44593 | G1648: 44742 | H1648: 198921 | I1648: 2022 | J1648: 0 | K1648: 0 | L1648: 0 | M1648: 1 | O1648: TRUE
A1649: ICJIA | B1649: Community-Based Violence Intervention and Prevention (CB-VIP) | C1649: 822039 AB | D1649: 2117 | E1649: Promise Academy of Peoria | F1649: 44666 | G1649: 45396 | H1649: 220998 | I1649: 2022 | J1649: 0 | K1649: 0 | L1649: 0 | M1649: 0 | O1649: FALSE
A1650: ICJIA | B1650: Community-Based Violence Intervention and Prevention (CB-VIP) | C1650: 172219- LM | D1650: 2117 | E1650: Reflections Foundation | F1650: 44593 | G1650: 44742 | H1650: 50005 | I1650: 2022 | J1650: 0 | K1650: 0 | L1650: 0 | M1650: 0 | O1650: FALSE
A1651: ICJIA | B1651: Community-Based Violence Intervention and Prevention (CB-VIP) | C1651: 172220 - AB | D1651: 2117 | E1651: Ring of Hope | F1651: 44593 | G1651: 45473 | H1651: 639443 | I1651: 2022 | J1651: 0 | K1651: 0 | L1651: 0 | M1651: 0 | O1651: FALSE
A1652: ICJIA | B1652: Community-Based Violence Intervention and Prevention (CB-VIP) | C1652: 172221 JG | D1652: 2117 | E1652: River City Community Development Center | F1652: 44593 | G1652: 45473 | H1652: 1216721 | I1652: 2022 | J1652: 0 | K1652: 0 | L1652: 0 | M1652: 0 | O1652: FALSE
A1653: ICJIA | B1653: Community-Based Violence Intervention and Prevention (CB-VIP) | C1653: 172222 SBB | D1653: 2117 | E1653: Roseland Ceasefire Project Inc. | F1653: 44593 | G1653: 44742 | H1653: 199682 | I1653: 2022 | J1653: 0 | K1653: 0 | L1653: 0 | M1653: 1 | O1653: FALSE
A1654: ICJIA | B1654: Community-Based Violence Intervention and Prevention (CB-VIP) | C1654: 0 | D1654: 2117 | E1654: Storycatchers Theatre | F1654: 44666 | G1654: 45030 | H1654: 482160 | I1654: 2022 | J1654: 0 | K1654: 0 | L1654: 0 | M1654: 0 | O1654: FALSE
A1655: ICJIA | B1655: Community-Based Violence Intervention and Prevention (CB-VIP) | C1655: 172223 - SW | D1655: 2117 | E1655: Taking Back Our Lives | F1655: 44593 | G1655: 44742 | H1655: 113116 | I1655: 2022 | J1655: 0 | K1655: 0 | L1655: 0 | M1655: 0 | O1655: FALSE
A1656: ICJIA | B1656: Community-Based Violence Intervention and Prevention (CB-VIP) | C1656: 172224 J.G | D1656: 2117 | E1656: The Blessed Child | F1656: 44593 | G1656: 44742 | H1656: 199311 | I1656: 2022 | J1656: 0 | K1656: 0 | L1656: 0 | M1656: 0 | O1656: FALSE
A1657: ICJIA | B1657: Community-Based Violence Intervention and Prevention (CB-VIP) | C1657: 172225 CAC | D1657: 2117 | E1657: The Firehouse Community Arts Center | F1657: 44593 | G1657: 44742 | H1657: 176550 | I1657: 2022 | J1657: 0 | K1657: 0 | L1657: 0 | M1657: 1 | O1657: FALSE
A1658: ICJIA | B1658: Community-Based Violence Intervention and Prevention (CB-VIP) | C1658: 172226-CW | D1658: 2117 | E1658: The Support Group | F1658: 44593 | G1658: 45473 | H1658: 199980 | I1658: 2022 | J1658: 0 | K1658: 0 | L1658: 0 | M1658: 0 | O1658: FALSE
A1659: ICJIA | B1659: Community-Based Violence Intervention and Prevention (CB-VIP) | C1659: 0 | D1659: 2117 | E1659: Trickster Art Gallery | F1659: 44593 | G1659: 44742 | H1659: 50535 | I1659: 2022 | J1659: 0 | K1659: 0 | L1659: 0 | M1659: 0 | O1659: FALSE
A1660: ICJIA | B1660: Community-Based Violence Intervention and Prevention (CB-VIP) | C1660: 0 | D1660: 2117 | E1660: True to Life Foundation | F1660: 44593 | G1660: 44742 | H1660: 137807 | I1660: 2022 | J1660: 0 | K1660: 0 | L1660: 0 | M1660: 0 | O1660: FALSE
A1661: ICJIA | B1661: Community-Based Violence Intervention and Prevention (CB-VIP) | C1661: 172229 | D1661: 2117 | E1661: Vermilion County Rape Crisis Center | F1661: 44593 | G1661: 44742 | H1661: 88000 | I1661: 2022 | J1661: 0 | K1661: 0 | L1661: 0 | M1661: 0 | O1661: FALSE
A1662: ICJIA | B1662: Community-Based Violence Intervention and Prevention (CB-VIP) | C1662: 0 | D1662: 2117 | E1662: Youth With A Positive Direction | F1662: 44593 | G1662: 44742 | H1662: 212380 | I1662: 2022 | J1662: 0 | K1662: 0 | L1662: 0 | M1662: 0 | O1662: FALSE
A1663: ICJIA | B1663: Community-Based Violence Intervention and Prevention (CB-VIP) | C1663: 822019 MSC | D1663: 2117 | E1663: Center for Conflict Resolution | F1663: 44666 | G1663: 45030 | H1663: 130042 | I1663: 2023 | J1663: 0 | K1663: 0 | L1663: 0 | M1663: 0 | O1663: FALSE
A1664: ICJIA | B1664: Community-Based Violence Intervention and Prevention (CB-VIP) | C1664: 822020 MSC | D1664: 2117 | E1664: Chicago Alliance Against Sexual Exploitation | F1664: 44666 | G1664: 45030 | H1664: 476658 | I1664: 2023 | J1664: 0 | K1664: 0 | L1664: 0 | M1664: 0 | O1664: FALSE
A1665: ICJIA | B1665: Community-Based Violence Intervention and Prevention (CB-VIP) | C1665: 822024 | D1665: 2117 | E1665: Cullar Consulting, LLC | F1665: 44666 | G1665: 45396 | H1665: 811745 | I1665: 2023 | J1665: 0 | K1665: 0 | L1665: 0 | M1665: 0 | O1665: FALSE
A1666: ICJIA | B1666: Community-Based Violence Intervention and Prevention (CB-VIP) | C1666: 822027 Cortisa Evans | D1666: 2117 | E1666: Friends of the Children - Chicago | F1666: 44666 | G1666: 45030 | H1666: 491918 | I1666: 2023 | J1666: 0 | K1666: 0 | L1666: 0 | M1666: 0 | O1666: FALSE
A1667: ICJIA | B1667: Community-Based Violence Intervention and Prevention (CB-VIP) | C1667: 822028 Cortisa Evans | D1667: 2117 | E1667: George Washington Carver Association | F1667: 44666 | G1667: 45030 | H1667: 479664 | I1667: 2023 | J1667: 0 | K1667: 0 | L1667: 0 | M1667: 0 | O1667: FALSE
A1668: ICJIA | B1668: Community-Based Violence Intervention and Prevention (CB-VIP) | C1668: 172212 CAC | D1668: 2117 | E1668: Greater Chatham Initiative | F1668: 44593 | G1668: 45473 | H1668: 156229 | I1668: 2023 | J1668: 0 | K1668: 0 | L1668: 0 | M1668: 0 | O1668: FALSE
A1669: ICJIA | B1669: Community-Based Violence Intervention and Prevention (CB-VIP) | C1669: 0 | D1669: 2117 | E1669: GRO Community | F1669: 44666 | G1669: 45396 | H1669: 379466 | I1669: 2023 | J1669: 0 | K1669: 0 | L1669: 0 | M1669: 0 | O1669: FALSE
A1670: ICJIA | B1670: Community-Based Violence Intervention and Prevention (CB-VIP) | C1670: 592206 KS | D1670: 2117 | E1670: Lake County Crisis Center for the Prevention and Treatment of Domestic Violence, INC DBA A Safe Place | F1670: 44743 | G1670: 45107 | H1670: 441413 | I1670: 2023 | J1670: 0 | K1670: 0 | L1670: 0 | M1670: 0 | O1670: FALSE
...

Sheet Master Pivot
A3: CP4P | B3: (All)
A5: Sum of Award Amount | B5: Column Labels
A6: Row Labels | B6: ICJIA | C6: OFVP | D6: Grand Total
A7: Institute for Nonviolence Chicago (INVC) | B7: 571300 | C7: 6788871 | D7: 7360171
A8: Institute for Nonviolence Chicago | B8: 197000 | D8: 197000
A9: Grand Total | B9: 768300 | C9: 6788871 | D9: 7557171

Sheet Data Check
A1: Question | B1: Answer
A2: How much money has OFVP given total? | B2: 4.5729551e+08
A3: What year had the most ICJIA money? | B3: 2023
A4: What percent of money of R3 was given to CVI organizations in 2026? | B4: 0.0468
A5: List top 10 receivers of gvmt funding and their alloted amount | B5: Metropolitan Family Services | C5: 1.3481785e+08
B6: Acclivus, Inc. | C6: 104075870
B7: Illinois Coalition Against Domestic Violence | C7: 88755000
B8: Illinois Coalition Against Sexual Assault | C8: 79280903
B9: Emerald South Economic Development Collaborative | C9: 41310812
B10: Children's Advocacy Center of Illinois | C10: 36681256
B11: Chicago Urban League | C11: 35867392
B12: Chicago Westside Branch NAACP | C12: 34014825
B13: Cook County Justice Advisory Council | C13: 32202942
B14: Prairie State Legal Services, Inc | C14: 31119179
A15: Who gave more money to CVI, ICJIA or OFVP? | B15: OFVP
A16: Provide a summary table of INVC public funding by source | B16: Row Labels | C16: ICJIA | D16: OFVP | E16: Grand Total
B17: Institute for Nonviolence Chicago (INVC) | C17: 571300 | D17: 6788871 | E17: 7360171
B18: Institute for Nonviolence Chicago | C18: 197000 | E18: 197000 | F18: <- see if it flags naming error

Sheet VLookup Lists
A1: ICJIA Codes | E1: CP4P Organizations | G1: SC2 Neighborhood | H1: SC2 Organizations | J1: Other CVI Orgs
A2: Program Name | B2: CSFA Codes | C2: Tag | E2: Alliance of Local Service Organizations (ALSO) | G2: Multiple | H2: Institute for Nonviolence Chicago (INVC) | J2: Acclivus, Inc.
A3: R3 | B3: 2378 | E3: Breakthrough Urban Ministries | G3: Multiple | H3: BUILD Inc. | J3: Cook County Justice Advisory Council
A4: Violence Prevention - Line Items | B4: 2440, 3244, 3319, 2977, 3657 | E4: Claretian Associates, Inc. | G4: Multiple | H4: Together Chicago | J4: ELITE COMMUNITY OUTREACH INC
A5: Violence Prevention and Reduction | B5: 2977 | E5: Enlace Chicago | G5: Austin | H5: Austin Coming Together | J5: Phalanx Family Services
A6: Community-Based Violence Intervention and Prevention (CB-VIP) | B6: 2117 | E6: Institute for Nonviolence Chicago (INVC) | G6: Austin | H6: Heartland Human Care Services (HHCS) | J6: Puerto Rican Cultural Center
A7: Community-based Violence Intervention & Prevention | B7: 3380 | E7: New Life Centers | G7: Austin | H7: Jehovah Jireh | J7: Roseland Ceasefire Project Inc.
A8: Street Intervention Programs (SIP) | B8: 2120 | E8: ONE Northside | G8: Austin | H8: Westside Health Authority | J8: Unstacked, Inc.
E9: Precious Blood Ministry of Reconciliation | G9: Austin | H9: What About Us | J9: Youth Peace Center of Roseland
A10: OFVP Codes | E10: Project HOOD | G10: Back of the Yards | H10: Back of the Yards Neighborhood Council
A11: Program Name | B11: CSFA Codes | C11: Tag | E11: Public Equity | G11: Back of the Yards | H11: Hope Culture
A12: Greater Illinois Trauma Informed Behavioral Health Services (TIBHS) | B12: 2600 | E12: Southwest Organizing Project (SWOP) | G12: Back of the Yards | H12: Precious Blood Ministry of Reconciliation
A13: RPSA Violence Prevention Training, Technical Assistance and Support (RVP-TTAS) | B13: 2771 | E13: Target Area Development Corp | G13: Englewood | H13: Englewood First Responders
A14: RPSA Youth Development Training, Technical Assistance and Support (RYD-TTAS) | B14: 2772 | E14: Think Outside Da Block | G14: Englewood | H14: Englewood Heroes
A15: Reimagine Public Safety Act Conveners | B15: 2773 | E15: Together Chicago, Inc. | G15: Englewood | H15: Public Equity
A16: Violence Prevention | B16: 2774 | C16: CVI | E16: UCAN | G16: Englewood | H16: Target Area Development Corp
A17: RPSA Violence Prevention Services (RVPS) | B17: 3422 | C17: CVI | E17: Metropolitan Family Services | G17: Englewood | H17: The Restorative Project, Inc.
A18: Reimagine High-Risk Youth Intervention Services | B18: 2776 | G18: Englewood | H18: Think Outside Da Block
A19: Greater Illinois Reimagine Youth Intervention Services | B19: 3005 | G19: Garfield Park | H19: A & L Youth and Family Services
A20: Chicago Youth Development & Intervention Services (CYDIS) | B20: 3007 | G20: Garfield Park | H20: Black Men United
A21: Peacekeepers Program | B21: 3013 | C21: FLIP | G21: Garfield Park | H21: Breakthrough Urban Ministries
A22: RPSA Greater Illinois Training and Technical Assistance Program (GI-TTAS) | B22: 3014 | G22: Garfield Park | H22: Lifeline to Hope
A23: Greater Illinois Violence Prevention Council Coordinator (GI-VPCC) | B23: 3023 | G23: Humboldt Park | H23: Alliance of Local Service Organizations (ALSO)
A24: RPSA Youth Development Services | B24: 2775 | G24: Humboldt Park | H24: Association House of Chicago
A25: RPSA Youth Development Services | B25: 3416 | G25: Humboldt Park | H25: Chicago Community Justice Foundation
A26: RPSA Community Convener | B26: 3484 | G26: Little Village | H26: New Life Centers
A27: Greater Illinois Violence Prevention Services | B27: 2774.03 | C27: CVI | G27: Little Village | H27: Wilbur Wright College
A28: Cook County Violence Prevention (aka JAC expansion) | B28: 3068 | C28: CVI | G28: Little Village | H28: YMCA OF METROPOLITAN CHICAGO
A29: Back To Our Future | B29: 3621 | G29: Little Village | H29: Beyond The Ball NFP
G30: Little Village | H30: Central States SER
G31: Little Village | H31: Enlace Chicago
G32: Little Village | H32: Erie Neighborhood House
G33: Little Village | H33: Helping Our People Excel (H.O.P.E.)
G34: Little Village | H34: Universidad Popular
G35: North Lawndale | H35: CRED
G36: North Lawndale | H36: The Firehouse Community Arts Center
G37: North Lawndale | H37: Metropolitan Family Services
G38: North Lawndale | H38: UCAN
